Workbook

Sheet Cover
B2: [PROJECT] — Project Finance Model
B4: Sector: | C4: Infrastructure / Energy / PPP
B5: Financial close date: | C5: [date]
B6: Last refreshed: | C6: [date]
B7: Refresh cadence: | C7: Weekly during construction; monthly during ops

Sheet Construction Budget
B2: Construction Budget & Drawdown
B5: Total project cost ($) | C5: 0
B6: Debt / equity ratio (e.g. 0.70 = 70% debt) | C6: 0.7
B7: Construction period (months) | C7: 24
B8: Interest during construction rate (%) | C8: 0.06
B11: Debt drawn | C11: =C5*C6 -> 0
B12: Equity drawn | C12: =C5*(1-C6) -> 0
B13: Interest during construction (IDC, simple approx.) | C13: =C11*C8*(C7/12)/2 -> 0 | D13: Approximation: avg drawn balance x rate x period, /2 for linear drawdown
B14: Total debt at COD (incl. capitalized IDC) | C14: =C11+C13 -> 0

Sheet Operating Cash Flow
B2: Operating Period Cash Flow ($mm)
B4: Line item | C4: Yr1 | D4: Yr2 | E4: Yr3 | F4: Yr4 | G4: Yr5
B5: Contracted/merchant revenue | C5: 0 | D5: 0 | E5: 0 | F5: 0 | G5: 0
B6: - Operating costs | C6: 0 | D6: 0 | E6: 0 | F6: 0 | G6: 0
B7: EBITDA | C7: =C5+C6 -> 0 | D7: =D5+D6 -> 0 | E7: =E5+E6 -> 0 | F7: =F5+F6 -> 0 | G7: =G5+G6 -> 0
B8: - Maintenance capex reserve | C8: 0 | D8: 0 | E8: 0 | F8: 0 | G8: 0
B9: Cash flow available for debt service (CFADS) | C9: =C7+C8 -> 0 | D9: =D7+D8 -> 0 | E9: =E7+E8 -> 0 | F9: =F7+F8 -> 0 | G9: =G7+G8 -> 0

Sheet DSCR & Debt Sizing
B2: DSCR & Debt Sizing
C4: Yr1 | D4: Yr2 | E4: Yr3 | F4: Yr4 | G4: Yr5
B5: CFADS | C5: ='Operating Cash Flow'!C9 -> 0 | D5: ='Operating Cash Flow'!D9 -> 0 | E5: ='Operating Cash Flow'!E9 -> 0 | F5: ='Operating Cash Flow'!F9 -> 0 | G5: ='Operating Cash Flow'!G9 -> 0
B6: Debt service (P&I) | C6: 0 | D6: 0 | E6: 0 | F6: 0 | G6: 0
B7: DSCR (CFADS / Debt service) | C7: =IFERROR(C5/C6,"-") -> - | D7: =IFERROR(D5/D6,"-") -> - | E7: =IFERROR(E5/E6,"-") -> - | F7: =IFERROR(F5/F6,"-") -> - | G7: =IFERROR(G5/G6,"-") -> -
B9: Minimum DSCR covenant | C9: 1.2
B10: Debt interest rate (for sizing PV) | C10: 0.06
B12: Debt sizing (sculpted to the DSCR covenant)
B13: Max annual debt service (CFADS / target DSCR) | C13: =IFERROR(C5/$C$9,"-") -> 0 | D13: =IFERROR(D5/$C$9,"-") -> 0 | E13: =IFERROR(E5/$C$9,"-") -> 0 | F13: =IFERROR(F5/$C$9,"-") -> 0 | G13: =IFERROR(G5/$C$9,"-") -> 0
B14: PV of max debt service (discounted at debt rate) | C14: =IFERROR(C13/(1+$C$10)^1,"-") -> 0 | D14: =IFERROR(D13/(1+$C$10)^2,"-") -> 0 | E14: =IFERROR(E13/(1+$C$10)^3,"-") -> 0 | F14: =IFERROR(F13/(1+$C$10)^4,"-") -> 0 | G14: =IFERROR(G13/(1+$C$10)^5,"-") -> 0
B16: Max sculpted debt (sum of PVs of annual capacity) | C16: =SUM(C14:G14) -> 0 | D16: This is capacity, not a repayment schedule — a real deal still needs an amortization profile (sculpted or level) that fits within it and keeps DSCR above covenant every period, not just on average

Sheet RefreshLog
B2: Refresh Log
B4: Date | C4: Trigger | D4: What changed | E4: Reviewer notes | F4: Next check
