Workbook

Sheet Cover
B2: [ISSUER] — Public Finance Credit Model
B4: Issuer: | C4: [Sovereign / state / municipality / authority]
B5: Instrument: | C5: GO / revenue bond / sovereign note
B6: Last refreshed: | C6: [date]
B7: Next payment / issuance: | C7: [date]
B8: Refresh cadence: | C8: Weekly
B9: Active scenario: | C9: Base
B10: Units: | C10: $ in millions unless noted
B13: Modeling conventions
B14: Blue text / yellow fill | C14: Hardcoded input or selected scenario
B15: Black text | C15: Formula / same-sheet calculation
B16: Green text | C16: Cross-sheet formula / link
B17: Checks | C17: PASS / REVIEW / FAIL must remain visible

Sheet Assumptions
B2: Public Finance Assumptions
B4: Assumption | C4: Base | D4: Downside | E4: Active | F4: Units / note
B5: Population / service base | C5: 1000000 | D5: 950000 | E5: =IF(Cover!$C$9="Downside",D5,C5)
B6: Recurring revenue | C6: 1200 | D6: 1080 | E6: =IF(Cover!$C$9="Downside",D6,C6)
B7: Recurring expenditure | C7: 1050 | D7: 1090 | E7: =IF(Cover!$C$9="Downside",D7,C7)
B8: Capital expenditure | C8: 180 | D8: 220 | E8: =IF(Cover!$C$9="Downside",D8,C8)
B9: Cash & unrestricted reserves | C9: 300 | D9: 220 | E9: =IF(Cover!$C$9="Downside",D9,C9)
B10: Gross debt | C10: 2500 | D10: 2500 | E10: =IF(Cover!$C$9="Downside",D10,C10)
B11: Annual scheduled principal | C11: 125 | D11: 125 | E11: =IF(Cover!$C$9="Downside",D11,C11)
B12: Pledged revenue | C12: 420 | D12: 360 | E12: =IF(Cover!$C$9="Downside",D12,C12)
B13: Intergovernmental transfers | C13: 150 | D13: 120 | E13: =IF(Cover!$C$9="Downside",D13,C13)
B14: Revenue growth | C14: 0.03 | D14: -0.02 | E14: =IF(Cover!$C$9="Downside",D14,C14)
B15: Expenditure growth | C15: 0.035 | D15: 0.05 | E15: =IF(Cover!$C$9="Downside",D15,C15)
B16: Effective interest rate (r) | C16: 0.045 | D16: 0.06 | E16: =IF(Cover!$C$9="Downside",D16,C16)
... B23: Debt-service reserve fund | C23: 50 | D23: 40 | E23: =IF(Cover!$C$9="Downside",D23,C23)

Sheet Debt Sustainability
B2: Debt Sustainability Analysis
B4: Metric | C4: Active | D4: Downside | E4: Units | F4: Interpretation
B5: Debt ratio | C5: =IFERROR(Assumptions!E10/Assumptions!E6,0) | D5: =IFERROR(Assumptions!D10/Assumptions!D6,0) | E5: 0.0x;[Red](0.0x);- | F5: Debt / recurring revenue or GDP proxy
B6: Effective rate (r) | C6: =Assumptions!E16 | D6: =Assumptions!D16 | E6: 0.0%;[Red](0.0%);- | F6: Weighted effective debt cost
B7: Nominal growth (g) | C7: =Assumptions!E21 | D7: =Assumptions!D21 | E7: 0.0%;[Red](0.0%);- | F7: Nominal revenue-base growth
B8: r - g | C8: =C6-C7 | D8: =D6-D7 | E8: 0.0%;[Red](0.0%);- | F8: Positive differential raises stabilization burden
B9: Current primary balance | C9: =Assumptions!E22 | D9: =Assumptions!D22 | E9: 0.0%;[Red](0.0%);- | F9: Surplus positive
B10: Debt-stabilizing primary balance | C10: =IFERROR((C6-C7)/(1+C7)*C5,0) | D10: =IFERROR((D6-D7)/(1+D7)*D5,0) | E10: 0.0%;[Red](0.0%);- | F10: Required balance to stabilize debt ratio
B11: Primary-balance gap | C11: =C9-C10 | D11: =D9-D10 | E11: 0.0%;[Red](0.0%);- | F11: Positive is stronger than stabilizing
B12: One-year projected debt ratio | C12: =IFERROR((1+C6)/(1+C7)*C5-C9,0) | D12: =IFERROR((1+D6)/(1+D7)*D5-D9,0) | E12: 0.0x;[Red](0.0x);- | F12: Standard debt-dynamics identity
B13: Trajectory | C13: =IF(C12<=C5,"STABILIZING / FALLING","RISING") | D13: =IF(D12<=D5,"STABILIZING / FALLING","RISING") | E13: status | F13: Screen excludes stock-flow adjustments

Sheet Revenue & Expenditure
B2: Operating Forecast
B4: $mm | C4: Current | D4: Year 1 | E4: Year 2 | F4: Year 3 | G4: Year 4 | H4: Year 5
B5: Recurring revenue | C5: =Assumptions!E6 | D5: =C5*(1+Assumptions!$E$14) | E5: =D5*(1+Assumptions!$E$14) | F5: =E5*(1+Assumptions!$E$14) | G5: =F5*(1+Assumptions!$E$14) | H5: =G5*(1+Assumptions!$E$14)
B6: Revenue growth | D6: =IFERROR(D5/C5-1,0) | E6: =IFERROR(E5/D5-1,0) | F6: =IFERROR(F5/E5-1,0) | G6: =IFERROR(G5/F5-1,0) | H6: =IFERROR(H5/G5-1,0)
B7: Recurring expenditure | C7: =Assumptions!E7 | D7: =C7*(1+Assumptions!$E$15) | E7: =D7*(1+Assumptions!$E$15) | F7: =E7*(1+Assumptions!$E$15) | G7: =F7*(1+Assumptions!$E$15) | H7: =G7*(1+Assumptions!$E$15)
B8: Expenditure growth | D8: =IFERROR(D7/C7-1,0) | E8: =IFERROR(E7/D7-1,0) | F8: =IFERROR(F7/E7-1,0) | G8: =IFERROR(G7/F7-1,0) | H8: =IFERROR(H7/G7-1,0)
B9: Operating surplus | C9: =C5-C7 | D9: =D5-D7 | E9: =E5-E7 | F9: =F5-F7 | G9: =G5-G7 | H9: =H5-H7
B10: Operating margin | C10: =IFERROR(C9/C5,0) | D10: =IFERROR(D9/D5,0) | E10: =IFERROR(E9/E5,0) | F10: =IFERROR(F9/F5,0) | G10: =IFERROR(G9/G5,0) | H10: =IFERROR(H9/H5,0)
B11: Pension / OPEB contribution | C11: =Assumptions!E20 | D11: =Assumptions!$E$20 | E11: =Assumptions!$E$20 | F11: =Assumptions!$E$20 | G11: =Assumptions!$E$20 | H11: =Assumptions!$E$20
B12: Net operating result | C12: =C9-C11 | D12: =D9-D11 | E12: =E9-E11 | F12: =F9-F11 | G12: =G9-G11 | H12: =H9-H11
B13: Capital expenditure | C13: =Assumptions!E8 | D13: =Assumptions!$E$8 | E13: =Assumptions!$E$8 | F13: =Assumptions!$E$8 | G13: =Assumptions!$E$8 | H13: =Assumptions!$E$8
B14: FCF before debt service | C14: =C12-C13 | D14: =D12-D13 | E14: =E12-E13 | F14: =F12-F13 | G14: =G12-G13 | H14: =H12-H13

Sheet Debt Service
B2: Debt Service, Borrowing & Reserves
B4: $mm | C4: Year 1 | D4: Year 2 | E4: Year 3 | F4: Year 4 | G4: Year 5
B5: Beginning debt | C5: =Assumptions!E10 | D5: =C11 | E5: =D11 | F5: =E11 | G5: =F11
B6: Scheduled principal | C6: =MIN(C5,Assumptions!$E$11) | D6: =MIN(D5,Assumptions!$E$11) | E6: =MIN(E5,Assumptions!$E$11) | F6: =MIN(F5,Assumptions!$E$11) | G6: =MIN(G5,Assumptions!$E$11)
B7: Cash interest | C7: =C5*Assumptions!$E$16 | D7: =D5*Assumptions!$E$16 | E7: =E5*Assumptions!$E$16 | F7: =F5*Assumptions!$E$16 | G7: =G5*Assumptions!$E$16
B8: Total debt service | C8: =C6+C7 | D8: =D6+D7 | E8: =E6+E7 | F8: =F6+F7 | G8: =G6+G7
B9: FCF before debt service | C9: ='Revenue & Expenditure'!D14 | D9: ='Revenue & Expenditure'!E14 | E9: ='Revenue & Expenditure'!F14 | F9: ='Revenue & Expenditure'!G14 | G9: ='Revenue & Expenditure'!H14
B10: New borrowing / funding gap | C10: =MAX(0,C8-C9) | D10: =MAX(0,D8-D9) | E10: =MAX(0,E8-E9) | F10: =MAX(0,F8-F9) | G10: =MAX(0,G8-G9)
B11: Ending debt | C11: =C5-C6+C10 | D11: =D5-D6+D10 | E11: =E5-E6+E10 | F11: =F5-F6+F10 | G11: =G5-G6+G10
B12: Beginning reserves | C12: =Assumptions!E9 | D12: =C13 | E12: =D13 | F12: =E13 | G12: =F13
B13: Ending reserves | C13: =MAX(0,C12+C9-C8+C10) | D13: =MAX(0,D12+D9-D8+D10) | E13: =MAX(0,E12+E9-E8+E10) | F13: =MAX(0,F12+F9-F8+F10) | G13: =MAX(0,G12+G9-G8+G10)
B14: Pledged revenue | C14: =Assumptions!$E$12*(1+Assumptions!$E$14)^1 | D14: =Assumptions!$E$12*(1+Assumptions!$E$14)^2 | E14: =Assumptions!$E$12*(1+Assumptions!$E$14)^3 | F14: =Assumptions!$E$12*(1+Assumptions!$E$14)^4 | G14: =Assumptions!$E$12*(1+Assumptions!$E$14)^5
B15: Revenue-bond DSCR | C15: =IFERROR(C14/C8,0) | D15: =IFERROR(D14/D8,0) | E15: =IFERROR(E14/E8,0) | F15: =IFERROR(F14/F8,0) | G15: =IFERROR(G14/G8,0)

Sheet Coverage
B2: Coverage, Liquidity & Debt Burden
B4: Metric | C4: Year 1 | D4: Year 2 | E4: Year 3 | F4: Year 4 | G4: Year 5
B5: Debt / recurring revenue | C5: =IFERROR('Debt Service'!C11/'Revenue & Expenditure'!D5,0) | D5: =IFERROR('Debt Service'!D11/'Revenue & Expenditure'!E5,0) | E5: =IFERROR('Debt Service'!E11/'Revenue & Expenditure'!F5,0) | F5: =IFERROR('Debt Service'!F11/'Revenue & Expenditure'!G5,0) | G5: =IFERROR('Debt Service'!G11/'Revenue & Expenditure'!H5,0)
B6: Maximum debt / revenue | C6: =Assumptions!E17 | D6: =Assumptions!E17 | E6: =Assumptions!E17 | F6: =Assumptions!E17 | G6: =Assumptions!E17
B7: Debt burden headroom | C7: =C6-C5 | D7: =D6-D5 | E7: =E6-E5 | F7: =F6-F5 | G7: =G6-G5
B8: Revenue-bond DSCR | C8: ='Debt Service'!C15 | D8: ='Debt Service'!D15 | E8: ='Debt Service'!E15 | F8: ='Debt Service'!F15 | G8: ='Debt Service'!G15
B9: Minimum DSCR | C9: =Assumptions!E18 | D9: =Assumptions!E18 | E9: =Assumptions!E18 | F9: =Assumptions!E18 | G9: =Assumptions!E18
B10: DSCR headroom | C10: =C8-C9 | D10: =D8-D9 | E10: =E8-E9 | F10: =F8-F9 | G10: =G8-G9
B11: Days cash on hand | C11: =IFERROR('Debt Service'!C13/('Revenue & Expenditure'!D7/365),0) | D11: =IFERROR('Debt Service'!D13/('Revenue & Expenditure'!E7/365),0) | E11: =IFERROR('Debt Service'!E13/('Revenue & Expenditure'!F7/365),0) | F11: =IFERROR('Debt Service'!F13/('Revenue & Expenditure'!G7/365),0) | G11: =IFERROR('Debt Service'!G13/('Revenue & Expenditure'!H7/365),0)
B12: Minimum days cash | C12: =Assumptions!E19 | D12: =Assumptions!E19 | E12: =Assumptions!E19 | F12: =Assumptions!E19 | G12: =Assumptions!E19
B13: Liquidity headroom | C13: =C11-C12 | D13: =D11-D12 | E13: =E11-E12 | F13: =F11-F12 | G13: =G11-G12
B14: Pension burden / revenue | C14: =IFERROR('Revenue & Expenditure'!D11/'Revenue & Expenditure'!D5,0) | D14: =IFERROR('Revenue & Expenditure'!E11/'Revenue & Expenditure'!E5,0) | E14: =IFERROR('Revenue & Expenditure'!F11/'Revenue & Expenditure'!F5,0) | F14: =IFERROR('Revenue & Expenditure'!G11/'Revenue & Expenditure'!G5,0) | G14: =IFERROR('Revenue & Expenditure'!H11/'Revenue & Expenditure'!H5,0)
B15: Status | C15: =IF(AND(C7>=0,C10>=0,C13>=0),"PASS","BREACH") | D15: =IF(AND(D7>=0,D10>=0,D13>=0),"PASS","BREACH") | E15: =IF(AND(E7>=0,E10>=0,E13>=0),"PASS","BREACH") | F15: =IF(AND(F7>=0,F10>=0,F13>=0),"PASS","BREACH") | G15: =IF(AND(G7>=0,G10>=0,G13>=0),"PASS","BREACH")

Sheet Scenarios
B2: Scenario Summary
B4: Metric | C4: Base | D4: Downside | E4: Threshold / interpretation
B5: Operating surplus | C5: =Assumptions!C6-Assumptions!C7-Assumptions!C20 | D5: =Assumptions!D6-Assumptions!D7-Assumptions!D20 | E5: Decision screen
B6: Debt / revenue | C6: =IFERROR(Assumptions!C10/Assumptions!C6,0) | D6: =IFERROR(Assumptions!D10/Assumptions!D6,0) | E6: Decision screen
B7: Revenue-bond DSCR | C7: =IFERROR(Assumptions!C12/(Assumptions!C11+Assumptions!C10*Assumptions!C16),0) | D7: =IFERROR(Assumptions!D12/(Assumptions!D11+Assumptions!D10*Assumptions!D16),0) | E7: Decision screen
B8: Days cash | C8: =IFERROR(Assumptions!C9/(Assumptions!C7/365),0) | D8: =IFERROR(Assumptions!D9/(Assumptions!D7/365),0) | E8: Decision screen
B9: Debt-stabilizing primary balance | C9: =IFERROR((Assumptions!C16-Assumptions!C21)/(1+Assumptions!C21)*(Assumptions!C10/Assumptions!C6),0) | D9: =IFERROR((Assumptions!D16-Assumptions!D21)/(1+Assumptions!D21)*(Assumptions!D10/Assumptions!D6),0) | E9: Decision screen
B10: Overall | C10: =IF(AND(C5>0,C6<=Assumptions!C17,C7>=Assumptions!C18,C8>=Assumptions!C19),"PASS","REVIEW") | D10: =IF(AND(D5>0,D6<=Assumptions!D17,D7>=Assumptions!D18,D8>=Assumptions!D19),"PASS","REVIEW") | E10: Decision screen

Sheet Sensitivity
B2: Debt Ratio Sensitivity — One Year
B4: Primary balance / r-g | C4: -0.02 | D4: 0 | E4: 0.02 | F4: 0.04 | G4: 0.06
B5: -0.05 | C5: ='Debt Sustainability'!$C$5*(1+C$4)-$B5 | D5: ='Debt Sustainability'!$C$5*(1+D$4)-$B5 | E5: ='Debt Sustainability'!$C$5*(1+E$4)-$B5 | F5: ='Debt Sustainability'!$C$5*(1+F$4)-$B5 | G5: ='Debt Sustainability'!$C$5*(1+G$4)-$B5
B6: -0.025 | C6: ='Debt Sustainability'!$C$5*(1+C$4)-$B6 | D6: ='Debt Sustainability'!$C$5*(1+D$4)-$B6 | E6: ='Debt Sustainability'!$C$5*(1+E$4)-$B6 | F6: ='Debt Sustainability'!$C$5*(1+F$4)-$B6 | G6: ='Debt Sustainability'!$C$5*(1+G$4)-$B6
B7: 0 | C7: ='Debt Sustainability'!$C$5*(1+C$4)-$B7 | D7: ='Debt Sustainability'!$C$5*(1+D$4)-$B7 | E7: ='Debt Sustainability'!$C$5*(1+E$4)-$B7 | F7: ='Debt Sustainability'!$C$5*(1+F$4)-$B7 | G7: ='Debt Sustainability'!$C$5*(1+G$4)-$B7
B8: 0.025 | C8: ='Debt Sustainability'!$C$5*(1+C$4)-$B8 | D8: ='Debt Sustainability'!$C$5*(1+D$4)-$B8 | E8: ='Debt Sustainability'!$C$5*(1+E$4)-$B8 | F8: ='Debt Sustainability'!$C$5*(1+F$4)-$B8 | G8: ='Debt Sustainability'!$C$5*(1+G$4)-$B8
B9: 0.05 | C9: ='Debt Sustainability'!$C$5*(1+C$4)-$B9 | D9: ='Debt Sustainability'!$C$5*(1+D$4)-$B9 | E9: ='Debt Sustainability'!$C$5*(1+E$4)-$B9 | F9: ='Debt Sustainability'!$C$5*(1+F$4)-$B9 | G9: ='Debt Sustainability'!$C$5*(1+G$4)-$B9

Sheet Checks
B2: Model Checks
B4: Check | C4: Status
B5: Debt nonnegative | C5: =IF(MIN('Debt Service'!C11:G11)>=0,"PASS","FAIL")
B6: Reserves nonnegative | C6: =IF(MIN('Debt Service'!C13:G13)>=0,"PASS","FAIL")
B7: Coverage finite | C7: =IF(AND(MAX(Coverage!C5:G14)<1000,MIN(Coverage!C5:G14)>-1000),"PASS","FAIL")
B8: No coverage breach | C8: =IF(COUNTIF(Coverage!C15:G15,"BREACH")=0,"PASS","REVIEW")
B9: Debt dynamics bounded | C9: =IF(AND('Debt Sustainability'!C12>=0,'Debt Sustainability'!C12<10),"PASS","REVIEW")
B10: Overall | C10: =IF(COUNTIF(C5:C9,"FAIL")+COUNTIF(C5:C9,"REVIEW")=0,"PASS","REVIEW")

Sheet Sources
B2: Source Register
B4: Input / dataset | C4: Source URL or document | D4: As-of | E4: Notes / transformation
B5: Official statements / disclosures | C5: EMMA, finance ministry, issuer or audited report | D5: [period] | E5: Revenue, expenditure, debt and reserves
B6: Accounting standards | C6: GASB, IPSAS, or applicable national standards | D6: [date] | E6: Map reporting consistently
B7: Economic and demographic data | C7: Official statistics, FRED, or multilateral dataset | D7: [period] | E7: Freeze series and release vintage
B8: Benchmark rates | C8: Treasury or sovereign curve | D8: [date] | E8: Refinancing and relative-value assumptions
B9: Debt sustainability method | C9: IMF / World Bank public methodology | D9: [date] | E9: Document debt-dynamics and stress choices

Sheet RefreshLog
B2: Refresh Log
B4: Date | C4: Trigger | D4: Source snapshot | E4: What changed | F4: Reviewer / challenge | G4: Next check
