Workbook

Sheet Cover
B2: [TARGET] — LBO Underwriting Model
B4: Target / transaction: | C4: [Name]
B5: Sponsor / principal: | C5: [Fund / merchant bank]
B6: Entry / close date: | C6: [date]
B7: Last refreshed: | C7: [date]
B8: Next IC / financing event: | C8: [date]
B9: Active scenario: | C9: Base
B10: Units: | C10: $ in millions unless noted
B13: Modeling conventions
B14: Blue text / yellow fill | C14: Hardcoded input or selected scenario
B15: Black text | C15: Formula / same-sheet calculation
B16: Green text | C16: Cross-sheet formula / link
B17: Checks | C17: PASS / REVIEW / FAIL must remain visible

Sheet Assumptions
B2: Transaction, Operating, and Financing Assumptions
B4: Assumption | C4: Base | D4: Downside | E4: Active | F4: Units / note
B5: LTM revenue | C5: 600 | D5: 600 | E5: =IF(Cover!$C$9="Downside",D5,C5) -> 600 | F5: $mm
B6: LTM EBITDA margin | C6: 0.2 | D6: 0.17 | E6: =IF(Cover!$C$9="Downside",D6,C6) -> 0.2 | F6: %
B7: Annual revenue growth | C7: 0.06 | D7: -0.02 | E7: =IF(Cover!$C$9="Downside",D7,C7) -> 0.06 | F7: %
B8: Annual EBITDA margin expansion | C8: 0.005 | D8: -0.003 | E8: =IF(Cover!$C$9="Downside",D8,C8) -> 0.005 | F8: % points
B9: D&A / revenue | C9: 0.025 | D9: 0.025 | E9: =IF(Cover!$C$9="Downside",D9,C9) -> 0.025 | F9: %
B10: Capex / revenue | C10: 0.035 | D10: 0.045 | E10: =IF(Cover!$C$9="Downside",D10,C10) -> 0.035 | F10: %
B11: NWC / revenue | C11: 0.08 | D11: 0.1 | E11: =IF(Cover!$C$9="Downside",D11,C11) -> 0.08 | F11: %
B12: Cash tax rate | C12: 0.25 | D12: 0.2 | E12: =IF(Cover!$C$9="Downside",D12,C12) -> 0.25 | F12: %
B13: Entry EBITDA multiple | C13: 10 | D13: 9 | E13: =IF(Cover!$C$9="Downside",D13,C13) -> 10 | F13: x
B14: Transaction fees / enterprise value | C14: 0.02 | D14: 0.025 | E14: =IF(Cover!$C$9="Downside",D14,C14) -> 0.02 | F14: %
B15: Existing net debt refinanced | C15: 100 | D15: 100 | E15: =IF(Cover!$C$9="Downside",D15,C15) -> 100 | F15: $mm
B16: Minimum cash | C16: 20 | D16: 25 | E16: =IF(Cover!$C$9="Downside",D16,C16) -> 20 | F16: $mm
... B32: Management catch-up above hurdle | C32: 0.2 | D32: 0.2 | E32: =IF(Cover!$C$9="Downside",D32,C32) -> 0.2 | F32: % incremental

Sheet Sources & Uses
B2: Transaction Sources & Uses
B4: Uses | C4: Amount | E4: Sources | F4: Amount
B5: Purchase enterprise value | C5: =Assumptions!E5*Assumptions!E6*Assumptions!E13 -> 1200 | E5: Revolver at close | F5: 0
B6: Refinance existing net debt | C6: =Assumptions!E15 -> 100 | E6: Term loan B | F6: =Assumptions!E5*Assumptions!E6*Assumptions!E19 -> 480
B7: Transaction fees | C7: =C5*Assumptions!E14 -> 24 | E7: Second-lien / holdco debt | F7: =Assumptions!E5*Assumptions!E6*Assumptions!E22 -> 180
B8: Minimum cash funded | C8: =Assumptions!E16 -> 20 | E8: Sponsor equity | F8: =C9-SUM(F5:F7) -> 684
B9: Total uses | C9: =SUM(C5:C8) -> 1344 | E9: Total sources | F9: =SUM(F5:F8) -> 1344
E10: Sources less uses | F10: =F9-C9 -> 0

Sheet Operating Model
B2: Seven-Year Operating, Tax, and Cash Flow Model
B4: $mm / % | C4: LTM | D4: Year 1 | E4: Year 2 | F4: Year 3 | G4: Year 4 | H4: Year 5 | I4: Year 6 | J4: Year 7
B5: Revenue | C5: =Assumptions!E5 -> 600 | D5: =C5*(1+Assumptions!$E$7) -> 636 | E5: =D5*(1+Assumptions!$E$7) -> 674.16 | F5: =E5*(1+Assumptions!$E$7) -> 714.6096 | G5: =F5*(1+Assumptions!$E$7) -> 757.48618 | H5: =G5*(1+Assumptions!$E$7) -> 802.93535 | I5: =H5*(1+Assumptions!$E$7) -> 851.11147 | J5: =I5*(1+Assumptions!$E$7) -> 902.17816
B6: Revenue growth | D6: =IFERROR(D5/C5-1,0) -> 0.06 | E6: =IFERROR(E5/D5-1,0) -> 0.06 | F6: =IFERROR(F5/E5-1,0) -> 0.06 | G6: =IFERROR(G5/F5-1,0) -> 0.06 | H6: =IFERROR(H5/G5-1,0) -> 0.06 | I6: =IFERROR(I5/H5-1,0) -> 0.06 | J6: =IFERROR(J5/I5-1,0) -> 0.06
B7: EBITDA margin | C7: =Assumptions!E6 -> 0.2 | D7: =MAX(0,MIN(0.6,C7+Assumptions!$E$8)) -> 0.205 | E7: =MAX(0,MIN(0.6,D7+Assumptions!$E$8)) -> 0.21 | F7: =MAX(0,MIN(0.6,E7+Assumptions!$E$8)) -> 0.215 | G7: =MAX(0,MIN(0.6,F7+Assumptions!$E$8)) -> 0.22 | H7: =MAX(0,MIN(0.6,G7+Assumptions!$E$8)) -> 0.225 | I7: =MAX(0,MIN(0.6,H7+Assumptions!$E$8)) -> 0.23 | J7: =MAX(0,MIN(0.6,I7+Assumptions!$E$8)) -> 0.235
B8: EBITDA | C8: =C5*C7 -> 120 | D8: =D5*D7 -> 130.38 | E8: =E5*E7 -> 141.5736 | F8: =F5*F7 -> 153.64106 | G8: =G5*G7 -> 166.64696 | H8: =H5*H7 -> 180.66045 | I8: =I5*I7 -> 195.75564 | J8: =J5*J7 -> 212.01187
B9: D&A | C9: =C5*Assumptions!E9 -> 15 | D9: =D5*Assumptions!$E$9 -> 15.9 | E9: =E5*Assumptions!$E$9 -> 16.854 | F9: =F5*Assumptions!$E$9 -> 17.86524 | G9: =G5*Assumptions!$E$9 -> 18.937154 | H9: =H5*Assumptions!$E$9 -> 20.073384 | I9: =I5*Assumptions!$E$9 -> 21.277787 | J9: =J5*Assumptions!$E$9 -> 22.554454
B10: EBIT | C10: =C8-C9 -> 105 | D10: =D8-D9 -> 114.48 | E10: =E8-E9 -> 124.7196 | F10: =F8-F9 -> 135.77582 | G10: =G8-G9 -> 147.7098 | H10: =H8-H9 -> 160.58707 | I10: =I8-I9 -> 174.47785 | J10: =J8-J9 -> 189.45741
B11: Cash interest | D11: ='Debt Schedule'!D7 -> 60.6 | E11: ='Debt Schedule'!E7 -> 58.561031 | F11: ='Debt Schedule'!F7 -> 55.65428 | G11: ='Debt Schedule'!G7 -> 51.854362 | H11: ='Debt Schedule'!H7 -> 47.044335 | I11: ='Debt Schedule'!I7 -> 41.08918 | J11: ='Debt Schedule'!J7 -> 33.838847
B12: EBT | D12: =D10-D11 -> 53.88 | E12: =E10-E11 -> 66.158569 | F12: =F10-F11 -> 80.121544 | G12: =G10-G11 -> 95.855443 | H12: =H10-H11 -> 113.54273 | I12: =I10-I11 -> 133.38867 | J12: =J10-J11 -> 155.61857
B13: Cash taxes | D13: =MAX(0,D12*Assumptions!$E$12) -> 13.47 | E13: =MAX(0,E12*Assumptions!$E$12) -> 16.539642 | F13: =MAX(0,F12*Assumptions!$E$12) -> 20.030386 | G13: =MAX(0,G12*Assumptions!$E$12) -> 23.963861 | H13: =MAX(0,H12*Assumptions!$E$12) -> 28.385684 | I13: =MAX(0,I12*Assumptions!$E$12) -> 33.347168 | J13: =MAX(0,J12*Assumptions!$E$12) -> 38.904641
B14: Net income | D14: =D12-D13 -> 40.41 | E14: =E12-E13 -> 49.618927 | F14: =F12-F13 -> 60.091158 | G14: =G12-G13 -> 71.891582 | H14: =H12-H13 -> 85.157051 | I14: =I12-I13 -> 100.0415 | J14: =J12-J13 -> 116.71392
B15: Capex | D15: =D5*Assumptions!$E$10 -> 22.26 | E15: =E5*Assumptions!$E$10 -> 23.5956 | F15: =F5*Assumptions!$E$10 -> 25.011336 | G15: =G5*Assumptions!$E$10 -> 26.512016 | H15: =H5*Assumptions!$E$10 -> 28.102737 | I15: =I5*Assumptions!$E$10 -> 29.788901 | J15: =J5*Assumptions!$E$10 -> 31.576235
B16: NWC | C16: =C5*Assumptions!E11 -> 48 | D16: =D5*Assumptions!$E$11 -> 50.88 | E16: =E5*Assumptions!$E$11 -> 53.9328 | F16: =F5*Assumptions!$E$11 -> 57.168768 | G16: =G5*Assumptions!$E$11 -> 60.598894 | H16: =H5*Assumptions!$E$11 -> 64.234828 | I16: =I5*Assumptions!$E$11 -> 68.088917 | J16: =J5*Assumptions!$E$11 -> 72.174252
B17: Change in NWC | D17: =D16-C16 -> 2.88 | E17: =E16-D16 -> 3.0528 | F17: =F16-E16 -> 3.235968 | G17: =G16-F16 -> 3.4301261 | H17: =H16-G16 -> 3.6359336 | I17: =I16-H16 -> 3.8540897 | J17: =J16-I16 -> 4.085335
B18: FCF before financing | D18: =D14+D9-D15-D17 -> 31.17 | E18: =E14+E9-E15-E17 -> 39.824527 | F18: =F14+F9-F15-F17 -> 49.709094 | G18: =G14+G9-G15-G17 -> 60.886594 | H18: =H14+H9-H15-H17 -> 73.491764 | I18: =I14+I9-I15-I17 -> 87.676299 | J18: =J14+J9-J15-J17 -> 103.60681
B19: FCF before interest | D19: =D8-D13-D15-D17 -> 91.77 | E19: =E8-E13-E15-E17 -> 98.385558 | F19: =F8-F13-F15-F17 -> 105.36337 | G19: =G8-G13-G15-G17 -> 112.74096 | H19: =H8-H13-H15-H17 -> 120.5361 | I19: =I8-I13-I15-I17 -> 128.76548 | J19: =J8-J13-J15-J17 -> 137.44565

Sheet Debt Schedule
B2: Multi-Tranche Debt and Cash Sweep
B4: $mm / % | C4: Close | D4: Year 1 | E4: Year 2 | F4: Year 3 | G4: Year 4 | H4: Year 5 | I4: Year 6 | J4: Year 7
B5: Beginning cash | C5: =Assumptions!E16 -> 20 | D5: =C13 -> 20 | E5: =D13 -> 21.648125 | F5: =E13 -> 22.292041 | G5: =F13 -> 22.950071 | H5: =G13 -> 23.689792 | I5: =H13 -> 24.523847 | J5: =I13 -> 25.462509
B6: FCF before interest | D6: ='Operating Model'!D19 -> 91.77 | E6: ='Operating Model'!E19 -> 98.385558 | F6: ='Operating Model'!F19 -> 105.36337 | G6: ='Operating Model'!G19 -> 112.74096 | H6: ='Operating Model'!H19 -> 120.5361 | I6: ='Operating Model'!I19 -> 128.76548 | J6: ='Operating Model'!J19 -> 137.44565
B7: Cash interest | D7: =SUM(D15,D18,D23) -> 60.6 | E7: =SUM(E15,E18,E23) -> 58.561031 | F7: =SUM(F15,F18,F23) -> 55.65428 | G7: =SUM(G15,G18,G23) -> 51.854362 | H7: =SUM(H15,H18,H23) -> 47.044335 | I7: =SUM(I15,I18,I23) -> 41.08918 | J7: =SUM(J15,J18,J23) -> 33.838847
B8: Mandatory TLB amortization | D8: =D19 -> 4.8 | E8: =E19 -> 4.8 | F8: =F19 -> 4.8 | G8: =G19 -> 4.8 | H8: =H19 -> 4.8 | I8: =I19 -> 4.8 | J8: =J19 -> 4.8
B9: Cash before revolver / sweep | D9: =D5+D6-D7-D8 -> 46.37 | E9: =E5+E6-E7-E8 -> 56.672652 | F9: =F5+F6-F7-F8 -> 67.201135 | G9: =G5+G6-G7-G8 -> 79.036665 | H9: =H5+H6-H7-H8 -> 92.381555 | I9: =I5+I6-I7-I8 -> 107.40015 | J9: =J5+J6-J7-J8 -> 124.26932
B10: Revolver draw / (repayment) | D10: =IF(D9<Assumptions!$E$16,MIN(Assumptions!$E$17-D14,Assumptions!$E$16-D9),-MIN(D14,MAX(0,D9-Assumptions!$E$16))) -> 0 | E10: =IF(E9<Assumptions!$E$16,MIN(Assumptions!$E$17-E14,Assumptions!$E$16-E9),-MIN(E14,MAX(0,E9-Assumptions!$E$16))) -> 0 | F10: =IF(F9<Assumptions!$E$16,MIN(Assumptions!$E$17-F14,Assumptions!$E$16-F9),-MIN(F14,MAX(0,F9-Assumptions!$E$16))) -> 0 | G10: =IF(G9<Assumptions!$E$16,MIN(Assumptions!$E$17-G14,Assumptions!$E$16-G9),-MIN(G14,MAX(0,G9-Assumptions!$E$16))) -> 0 | H10: =IF(H9<Assumptions!$E$16,MIN(Assumptions!$E$17-H14,Assumptions!$E$16-H9),-MIN(H14,MAX(0,H9-Assumptions!$E$16))) -> 0 | I10: =IF(I9<Assumptions!$E$16,MIN(Assumptions!$E$17-I14,Assumptions!$E$16-I9),-MIN(I14,MAX(0,I9-Assumptions!$E$16))) -> 0 | J10: =IF(J9<Assumptions!$E$16,MIN(Assumptions!$E$17-J14,Assumptions!$E$16-J9),-MIN(J14,MAX(0,J9-Assumptions!$E$16))) -> 0
B11: Cash sweep to TLB | D11: =MIN(MAX(0,D17-D19),MAX(0,D9+D10-Assumptions!$E$16)*Assumptions!$E$25) -> 19.7775 | E11: =MIN(MAX(0,E17-E19),MAX(0,E9+E10-Assumptions!$E$16)*Assumptions!$E$25) -> 27.504489 | F11: =MIN(MAX(0,F17-F19),MAX(0,F9+F10-Assumptions!$E$16)*Assumptions!$E$25) -> 35.400851 | G11: =MIN(MAX(0,G17-G19),MAX(0,G9+G10-Assumptions!$E$16)*Assumptions!$E$25) -> 44.277499 | H11: =MIN(MAX(0,H17-H19),MAX(0,H9+H10-Assumptions!$E$16)*Assumptions!$E$25) -> 54.286166 | I11: =MIN(MAX(0,I17-I19),MAX(0,I9+I10-Assumptions!$E$16)*Assumptions!$E$25) -> 65.550109 | J11: =MIN(MAX(0,J17-J19),MAX(0,J9+J10-Assumptions!$E$16)*Assumptions!$E$25) -> 78.201988
B12: Cash sweep to second lien | D12: =MIN(MAX(0,D22+D24),MAX(0,D9+D10-D11-Assumptions!$E$16)*Assumptions!$E$25) -> 4.944375 | E12: =MIN(MAX(0,E22+E24),MAX(0,E9+E10-E11-Assumptions!$E$16)*Assumptions!$E$25) -> 6.8761222 | F12: =MIN(MAX(0,F22+F24),MAX(0,F9+F10-F11-Assumptions!$E$16)*Assumptions!$E$25) -> 8.8502128 | G12: =MIN(MAX(0,G22+G24),MAX(0,G9+G10-G11-Assumptions!$E$16)*Assumptions!$E$25) -> 11.069375 | H12: =MIN(MAX(0,H22+H24),MAX(0,H9+H10-H11-Assumptions!$E$16)*Assumptions!$E$25) -> 13.571542 | I12: =MIN(MAX(0,I22+I24),MAX(0,I9+I10-I11-Assumptions!$E$16)*Assumptions!$E$25) -> 16.387527 | J12: =MIN(MAX(0,J22+J24),MAX(0,J9+J10-J11-Assumptions!$E$16)*Assumptions!$E$25) -> 19.550497
B13: Ending cash | C13: =C5 -> 20 | D13: =D9+D10-D11-D12 -> 21.648125 | E13: =E9+E10-E11-E12 -> 22.292041 | F13: =F9+F10-F11-F12 -> 22.950071 | G13: =G9+G10-G11-G12 -> 23.689792 | H13: =H9+H10-H11-H12 -> 24.523847 | I13: =I9+I10-I11-I12 -> 25.462509 | J13: =J9+J10-J11-J12 -> 26.516832
B14: Beginning revolver | C14: ='Sources & Uses'!F5 -> 0 | D14: =C16 -> 0 | E14: =D16 -> 0 | F14: =E16 -> 0 | G14: =F16 -> 0 | H14: =G16 -> 0 | I14: =H16 -> 0 | J14: =I16 -> 0
B15: Revolver interest | D15: =D14*Assumptions!$E$18 -> 0 | E15: =E14*Assumptions!$E$18 -> 0 | F15: =F14*Assumptions!$E$18 -> 0 | G15: =G14*Assumptions!$E$18 -> 0 | H15: =H14*Assumptions!$E$18 -> 0 | I15: =I14*Assumptions!$E$18 -> 0 | J15: =J14*Assumptions!$E$18 -> 0
B16: Ending revolver | C16: =C14 -> 0 | D16: =MAX(0,D14+D10) -> 0 | E16: =MAX(0,E14+E10) -> 0 | F16: =MAX(0,F14+F10) -> 0 | G16: =MAX(0,G14+G10) -> 0 | H16: =MAX(0,H14+H10) -> 0 | I16: =MAX(0,I14+I10) -> 0 | J16: =MAX(0,J14+J10) -> 0
B17: Beginning TLB | C17: ='Sources & Uses'!F6 -> 480 | D17: =C21 -> 480 | E17: =D21 -> 455.4225 | F17: =E21 -> 423.11801 | G17: =F21 -> 382.91716 | H17: =G21 -> 333.83966 | I17: =H21 -> 274.75349 | J17: =I21 -> 204.40339
B18: TLB interest | D18: =D17*Assumptions!$E$20 -> 40.8 | E18: =E17*Assumptions!$E$20 -> 38.710912 | F18: =F17*Assumptions!$E$20 -> 35.965031 | G18: =G17*Assumptions!$E$20 -> 32.547959 | H18: =H17*Assumptions!$E$20 -> 28.376371 | I18: =I17*Assumptions!$E$20 -> 23.354047 | J18: =J17*Assumptions!$E$20 -> 17.374288
B19: TLB amortization | D19: =MIN(D17,'Sources & Uses'!$F$6*Assumptions!$E$21) -> 4.8 | E19: =MIN(E17,'Sources & Uses'!$F$6*Assumptions!$E$21) -> 4.8 | F19: =MIN(F17,'Sources & Uses'!$F$6*Assumptions!$E$21) -> 4.8 | G19: =MIN(G17,'Sources & Uses'!$F$6*Assumptions!$E$21) -> 4.8 | H19: =MIN(H17,'Sources & Uses'!$F$6*Assumptions!$E$21) -> 4.8 | I19: =MIN(I17,'Sources & Uses'!$F$6*Assumptions!$E$21) -> 4.8 | J19: =MIN(J17,'Sources & Uses'!$F$6*Assumptions!$E$21) -> 4.8
B20: TLB cash sweep | C20: ='Sources & Uses'!F7 -> 180 | D20: =D11 -> 19.7775 | E20: =E11 -> 27.504489 | F20: =F11 -> 35.400851 | G20: =G11 -> 44.277499 | H20: =H11 -> 54.286166 | I20: =I11 -> 65.550109 | J20: =J11 -> 78.201988
B21: Ending TLB | C21: =C17 -> 480 | D21: =MAX(0,D17-D19-D20) -> 455.4225 | E21: =MAX(0,E17-E19-E20) -> 423.11801 | F21: =MAX(0,F17-F19-F20) -> 382.91716 | G21: =MAX(0,G17-G19-G20) -> 333.83966 | H21: =MAX(0,H17-H19-H20) -> 274.75349 | I21: =MAX(0,I17-I19-I20) -> 204.40339 | J21: =MAX(0,J17-J19-J20) -> 121.4014
B22: Beginning second lien | C22: ='Sources & Uses'!F7 -> 180 | D22: =C26 -> 180 | E22: =D26 -> 180.45562 | F22: =E26 -> 178.99317 | G22: =F26 -> 175.51275 | H22: =G26 -> 169.70876 | I22: =H26 -> 161.22848 | J22: =I26 -> 149.67781
B23: Second-lien cash interest | D23: =D22*Assumptions!$E$23 -> 19.8 | E23: =E22*Assumptions!$E$23 -> 19.850119 | F23: =F22*Assumptions!$E$23 -> 19.689249 | G23: =G22*Assumptions!$E$23 -> 19.306403 | H23: =H22*Assumptions!$E$23 -> 18.667964 | I23: =I22*Assumptions!$E$23 -> 17.735133 | J23: =J22*Assumptions!$E$23 -> 16.464559
B24: Second-lien PIK | D24: =D22*Assumptions!$E$24 -> 5.4 | E24: =E22*Assumptions!$E$24 -> 5.4136688 | F24: =F22*Assumptions!$E$24 -> 5.3697951 | G24: =G22*Assumptions!$E$24 -> 5.2653826 | H24: =H22*Assumptions!$E$24 -> 5.0912629 | I24: =I22*Assumptions!$E$24 -> 4.8368545 | J24: =J22*Assumptions!$E$24 -> 4.4903343
B25: Second-lien cash sweep | C25: =SUM(C16,C20,C13) -> 200 | D25: =D12 -> 4.944375 | E25: =E12 -> 6.8761222 | F25: =F12 -> 8.8502128 | G25: =G12 -> 11.069375 | H25: =H12 -> 13.571542 | I25: =I12 -> 16.387527 | J25: =J12 -> 19.550497
B26: Ending second lien | C26: =C22 -> 180 | D26: =MAX(0,D22+D24-D25) -> 180.45562 | E26: =MAX(0,E22+E24-E25) -> 178.99317 | F26: =MAX(0,F22+F24-F25) -> 175.51275 | G26: =MAX(0,G22+G24-G25) -> 169.70876 | H26: =MAX(0,H22+H24-H25) -> 161.22848 | I26: =MAX(0,I22+I24-I25) -> 149.67781 | J26: =MAX(0,J22+J24-J25) -> 134.61765
B27: Total debt | C27: =SUM(C16,C21,C26) -> 660 | D27: =SUM(D16,D21,D26) -> 635.87812 | E27: =SUM(E16,E21,E26) -> 602.11118 | F27: =SUM(F16,F21,F26) -> 558.42991 | G27: =SUM(G16,G21,G26) -> 503.54842 | H27: =SUM(H16,H21,H26) -> 435.98198 | I27: =SUM(I16,I21,I26) -> 354.0812 | J27: =SUM(J16,J21,J26) -> 256.01905
B28: Net debt | C28: =C27-C13 -> 640 | D28: =D27-D13 -> 614.23 | E28: =E27-E13 -> 579.81914 | F28: =F27-F13 -> 535.47984 | G28: =G27-G13 -> 479.85863 | H28: =H27-H13 -> 411.45813 | I28: =I27-I13 -> 328.61869 | J28: =J27-J13 -> 229.50221

Sheet Covenants
B2: Lender Covenant and Liquidity Dashboard
B4: Metric | C4: Year 1 | D4: Year 2 | E4: Year 3 | F4: Year 4 | G4: Year 5 | H4: Year 6 | I4: Year 7
B5: Gross leverage | C5: =IFERROR('Debt Schedule'!D25/'Operating Model'!D8,0) -> 0.037922803 | D5: =IFERROR('Debt Schedule'!E25/'Operating Model'!E8,0) -> 0.04856924 | E5: =IFERROR('Debt Schedule'!F25/'Operating Model'!F8,0) -> 0.057603173 | F5: =IFERROR('Debt Schedule'!G25/'Operating Model'!G8,0) -> 0.066424103 | G5: =IFERROR('Debt Schedule'!H25/'Operating Model'!H8,0) -> 0.075121818 | H5: =IFERROR('Debt Schedule'!I25/'Operating Model'!I8,0) -> 0.083714204 | I5: =IFERROR('Debt Schedule'!J25/'Operating Model'!J8,0) -> 0.092214163
B6: Maximum leverage | C6: =Assumptions!$E$26 -> 7 | D6: =Assumptions!$E$26 -> 7 | E6: =Assumptions!$E$26 -> 7 | F6: =Assumptions!$E$26 -> 7 | G6: =Assumptions!$E$26 -> 7 | H6: =Assumptions!$E$26 -> 7 | I6: =Assumptions!$E$26 -> 7
B7: Leverage headroom | C7: =C6-C5 -> 6.9620772 | D7: =D6-D5 -> 6.9514308 | E7: =E6-E5 -> 6.9423968 | F7: =F6-F5 -> 6.9335759 | G7: =G6-G5 -> 6.9248782 | H7: =H6-H5 -> 6.9162858 | I7: =I6-I5 -> 6.9077858
B8: Interest coverage | C8: =IFERROR('Operating Model'!D8/'Debt Schedule'!D7,0) -> 2.1514851 | D8: =IFERROR('Operating Model'!E8/'Debt Schedule'!E7,0) -> 2.4175394 | E8: =IFERROR('Operating Model'!F8/'Debt Schedule'!F7,0) -> 2.7606334 | F8: =IFERROR('Operating Model'!G8/'Debt Schedule'!G7,0) -> 3.2137501 | G8: =IFERROR('Operating Model'!H8/'Debt Schedule'!H7,0) -> 3.840217 | H8: =IFERROR('Operating Model'!I8/'Debt Schedule'!I7,0) -> 4.7641651 | I8: =IFERROR('Operating Model'!J8/'Debt Schedule'!J7,0) -> 6.2653396
B9: Minimum coverage | C9: =Assumptions!$E$27 -> 1.75 | D9: =Assumptions!$E$27 -> 1.75 | E9: =Assumptions!$E$27 -> 1.75 | F9: =Assumptions!$E$27 -> 1.75 | G9: =Assumptions!$E$27 -> 1.75 | H9: =Assumptions!$E$27 -> 1.75 | I9: =Assumptions!$E$27 -> 1.75
B10: Coverage headroom | C10: =C8-C9 -> 0.40148515 | D10: =D8-D9 -> 0.66753939 | E10: =E8-E9 -> 1.0106334 | F10: =F8-F9 -> 1.4637501 | G10: =G8-G9 -> 2.090217 | H10: =H8-H9 -> 3.0141651 | I10: =I8-I9 -> 4.5153396
B11: Minimum cash | C11: =Assumptions!$E$16 -> 20 | D11: =Assumptions!$E$16 -> 20 | E11: =Assumptions!$E$16 -> 20 | F11: =Assumptions!$E$16 -> 20 | G11: =Assumptions!$E$16 -> 20 | H11: =Assumptions!$E$16 -> 20 | I11: =Assumptions!$E$16 -> 20
B12: Cash headroom | C12: ='Debt Schedule'!D13-C11 -> 1.648125 | D12: ='Debt Schedule'!E13-D11 -> 2.2920407 | E12: ='Debt Schedule'!F13-E11 -> 2.9500709 | F12: ='Debt Schedule'!G13-F11 -> 3.6897916 | G12: ='Debt Schedule'!H13-G11 -> 4.5238472 | H12: ='Debt Schedule'!I13-H11 -> 5.4625091 | I12: ='Debt Schedule'!J13-I11 -> 6.5168323
B13: Status | C13: =IF(AND(C7>=0,C10>=0,C12>=0),"PASS","BREACH") -> PASS | D13: =IF(AND(D7>=0,D10>=0,D12>=0),"PASS","BREACH") -> PASS | E13: =IF(AND(E7>=0,E10>=0,E12>=0),"PASS","BREACH") -> PASS | F13: =IF(AND(F7>=0,F10>=0,F12>=0),"PASS","BREACH") -> PASS | G13: =IF(AND(G7>=0,G10>=0,G12>=0),"PASS","BREACH") -> PASS | H13: =IF(AND(H7>=0,H10>=0,H12>=0),"PASS","BREACH") -> PASS | I13: =IF(AND(I7>=0,I10>=0,I12>=0),"PASS","BREACH") -> PASS

Sheet Management Equity
B2: Management Equity and Incentive Pool
B4: Metric | C4: Value | D4: Units | E4: Notes
B5: Management fully diluted pool | C5: =Assumptions!E30 -> 0.1 | D5: % | E5: granted / reserved pool
B6: Sponsor ownership before pool | C6: =1-C5 -> 0.9 | D6: % | E6: fully diluted
B7: Sponsor invested equity | C7: ='Sources & Uses'!F8 -> 684 | D7: $mm | E7: entry equity
B8: Preferred return at exit | C8: =C7*(1+Assumptions!E31)^Assumptions!E29 -> 1005.0204 | D8: $mm | E8: sponsor hurdle
B9: Management catch-up rate | C9: =Assumptions!E32 -> 0.2 | D9: % incremental | E9: above preferred return

Sheet Returns Waterfall
B2: Exit Equity and Sponsor / Management Waterfall
B4: Metric | C4: Year 1 | D4: Year 2 | E4: Year 3 | F4: Year 4 | G4: Year 5 | H4: Year 6 | I4: Year 7 | J4: Selected exit
B5: Exit EBITDA | C5: ='Operating Model'!D8 -> 130.38 | D5: ='Operating Model'!E8 -> 141.5736 | E5: ='Operating Model'!F8 -> 153.64106 | F5: ='Operating Model'!G8 -> 166.64696 | G5: ='Operating Model'!H8 -> 180.66045 | H5: ='Operating Model'!I8 -> 195.75564 | I5: ='Operating Model'!J8 -> 212.01187 | J5: =INDEX(C5:I5,1,Assumptions!E29) -> 180.66045
B6: Exit multiple | C6: =Assumptions!$E$28 -> 10 | D6: =Assumptions!$E$28 -> 10 | E6: =Assumptions!$E$28 -> 10 | F6: =Assumptions!$E$28 -> 10 | G6: =Assumptions!$E$28 -> 10 | H6: =Assumptions!$E$28 -> 10 | I6: =Assumptions!$E$28 -> 10 | J6: =INDEX(C6:I6,1,Assumptions!E29) -> 10
B7: Exit enterprise value | C7: =C5*C6 -> 1303.8 | D7: =D5*D6 -> 1415.736 | E7: =E5*E6 -> 1536.4106 | F7: =F5*F6 -> 1666.4696 | G7: =G5*G6 -> 1806.6045 | H7: =H5*H6 -> 1957.5564 | I7: =I5*I6 -> 2120.1187 | J7: =INDEX(C7:I7,1,Assumptions!E29) -> 1806.6045
B8: Net debt | C8: ='Debt Schedule'!D28 -> 614.23 | D8: ='Debt Schedule'!E28 -> 579.81914 | E8: ='Debt Schedule'!F28 -> 535.47984 | F8: ='Debt Schedule'!G28 -> 479.85863 | G8: ='Debt Schedule'!H28 -> 411.45813 | H8: ='Debt Schedule'!I28 -> 328.61869 | I8: ='Debt Schedule'!J28 -> 229.50221 | J8: =INDEX(C8:I8,1,Assumptions!E29) -> 411.45813
B9: Gross equity value | C9: =MAX(0,C7-C8) -> 689.57 | D9: =MAX(0,D7-D8) -> 835.91686 | E9: =MAX(0,E7-E8) -> 1000.9308 | F9: =MAX(0,F7-F8) -> 1186.611 | G9: =MAX(0,G7-G8) -> 1395.1464 | H9: =MAX(0,H7-H8) -> 1628.9377 | I9: =MAX(0,I7-I8) -> 1890.6165 | J9: =INDEX(C9:I9,1,Assumptions!E29) -> 1395.1464
B10: Sponsor preferred return | C10: ='Management Equity'!$C$7*(1+Assumptions!$E$31)^1 -> 738.72 | D10: ='Management Equity'!$C$7*(1+Assumptions!$E$31)^2 -> 797.8176 | E10: ='Management Equity'!$C$7*(1+Assumptions!$E$31)^3 -> 861.64301 | F10: ='Management Equity'!$C$7*(1+Assumptions!$E$31)^4 -> 930.57445 | G10: ='Management Equity'!$C$7*(1+Assumptions!$E$31)^5 -> 1005.0204 | H10: ='Management Equity'!$C$7*(1+Assumptions!$E$31)^6 -> 1085.422 | I10: ='Management Equity'!$C$7*(1+Assumptions!$E$31)^7 -> 1172.2558 | J10: =INDEX(C10:I10,1,Assumptions!E29) -> 1005.0204
B11: Equity above preferred | C11: =MAX(0,C9-C10) -> 0 | D11: =MAX(0,D9-D10) -> 38.099258 | E11: =MAX(0,E9-E10) -> 139.28779 | F11: =MAX(0,F9-F10) -> 256.03651 | G11: =MAX(0,G9-G10) -> 390.12599 | H11: =MAX(0,H9-H10) -> 543.51565 | I11: =MAX(0,I9-I10) -> 718.36065 | J11: =INDEX(C11:I11,1,Assumptions!E29) -> 390.12599
B12: Management proceeds | C12: =MIN(C9,C9*Assumptions!$E$30+C11*Assumptions!$E$32) -> 68.957 | D12: =MIN(D9,D9*Assumptions!$E$30+D11*Assumptions!$E$32) -> 91.211537 | E12: =MIN(E9,E9*Assumptions!$E$30+E11*Assumptions!$E$32) -> 127.95064 | F12: =MIN(F9,F9*Assumptions!$E$30+F11*Assumptions!$E$32) -> 169.8684 | G12: =MIN(G9,G9*Assumptions!$E$30+G11*Assumptions!$E$32) -> 217.53984 | H12: =MIN(H9,H9*Assumptions!$E$30+H11*Assumptions!$E$32) -> 271.5969 | I12: =MIN(I9,I9*Assumptions!$E$30+I11*Assumptions!$E$32) -> 332.73378 | J12: =INDEX(C12:I12,1,Assumptions!E29) -> 217.53984
B13: Sponsor proceeds | C13: =MAX(0,C9-C12) -> 620.613 | D13: =MAX(0,D9-D12) -> 744.70532 | E13: =MAX(0,E9-E12) -> 872.98016 | F13: =MAX(0,F9-F12) -> 1016.7426 | G13: =MAX(0,G9-G12) -> 1177.6066 | H13: =MAX(0,H9-H12) -> 1357.3408 | I13: =MAX(0,I9-I12) -> 1557.8827 | J13: =INDEX(C13:I13,1,Assumptions!E29) -> 1177.6066
B14: Sponsor MOIC | C14: =IFERROR(C13/'Sources & Uses'!$F$8,0) -> 0.90732895 | D14: =IFERROR(D13/'Sources & Uses'!$F$8,0) -> 1.0887505 | E14: =IFERROR(E13/'Sources & Uses'!$F$8,0) -> 1.2762868 | F14: =IFERROR(F13/'Sources & Uses'!$F$8,0) -> 1.4864657 | G14: =IFERROR(G13/'Sources & Uses'!$F$8,0) -> 1.721647 | H14: =IFERROR(H13/'Sources & Uses'!$F$8,0) -> 1.9844164 | I14: =IFERROR(I13/'Sources & Uses'!$F$8,0) -> 2.2776063 | J14: =INDEX(C14:I14,1,Assumptions!E29) -> 1.721647
B15: Sponsor IRR | C15: =IFERROR((C13/'Sources & Uses'!$F$8)^(1/1)-1,0) -> -0.092671053 | D15: =IFERROR((D13/'Sources & Uses'!$F$8)^(1/2)-1,0) -> 0.043432062 | E15: =IFERROR((E13/'Sources & Uses'!$F$8)^(1/3)-1,0) -> 0.084716111 | F15: =IFERROR((F13/'Sources & Uses'!$F$8)^(1/4)-1,0) -> 0.10417707 | G15: =IFERROR((G13/'Sources & Uses'!$F$8)^(1/5)-1,0) -> 0.11477911 | H15: =IFERROR((H13/'Sources & Uses'!$F$8)^(1/6)-1,0) -> 0.12099962 | I15: =IFERROR((I13/'Sources & Uses'!$F$8)^(1/7)-1,0) -> 0.12478205 | J15: =INDEX(C15:I15,1,Assumptions!E29) -> 0.11477911

Sheet Sensitivity
B2: Sponsor IRR Sensitivity
B4: Entry / Exit multiple | C4: 7 | D4: 8 | E4: 9 | F4: 10 | G4: 11
B5: 8 | C5: =IFERROR(((('Operating Model'!H8*C$4-'Debt Schedule'!G28)*(1-Assumptions!$E$30))/MAX(0.01,('Operating Model'!C8*$B5+Assumptions!$E$15+'Sources & Uses'!C7+Assumptions!$E$16-'Sources & Uses'!F6-'Sources & Uses'!F7)))^(1/5)-1,0) -> 0.097285858 | D5: =IFERROR(((('Operating Model'!H8*D$4-'Debt Schedule'!G28)*(1-Assumptions!$E$30))/MAX(0.01,('Operating Model'!C8*$B5+Assumptions!$E$15+'Sources & Uses'!C7+Assumptions!$E$16-'Sources & Uses'!F6-'Sources & Uses'!F7)))^(1/5)-1,0) -> 0.1437092 | E5: =IFERROR(((('Operating Model'!H8*E$4-'Debt Schedule'!G28)*(1-Assumptions!$E$30))/MAX(0.01,('Operating Model'!C8*$B5+Assumptions!$E$15+'Sources & Uses'!C7+Assumptions!$E$16-'Sources & Uses'!F6-'Sources & Uses'!F7)))^(1/5)-1,0) -> 0.18362821 | F5: =IFERROR(((('Operating Model'!H8*F$4-'Debt Schedule'!G28)*(1-Assumptions!$E$30))/MAX(0.01,('Operating Model'!C8*$B5+Assumptions!$E$15+'Sources & Uses'!C7+Assumptions!$E$16-'Sources & Uses'!F6-'Sources & Uses'!F7)))^(1/5)-1,0) -> 0.21879162 | G5: =IFERROR(((('Operating Model'!H8*G$4-'Debt Schedule'!G28)*(1-Assumptions!$E$30))/MAX(0.01,('Operating Model'!C8*$B5+Assumptions!$E$15+'Sources & Uses'!C7+Assumptions!$E$16-'Sources & Uses'!F6-'Sources & Uses'!F7)))^(1/5)-1,0) -> 0.25031078
B6: 9 | C6: =IFERROR(((('Operating Model'!H8*C$4-'Debt Schedule'!G28)*(1-Assumptions!$E$30))/MAX(0.01,('Operating Model'!C8*$B6+Assumptions!$E$15+'Sources & Uses'!C7+Assumptions!$E$16-'Sources & Uses'!F6-'Sources & Uses'!F7)))^(1/5)-1,0) -> 0.046021365 | D6: =IFERROR(((('Operating Model'!H8*D$4-'Debt Schedule'!G28)*(1-Assumptions!$E$30))/MAX(0.01,('Operating Model'!C8*$B6+Assumptions!$E$15+'Sources & Uses'!C7+Assumptions!$E$16-'Sources & Uses'!F6-'Sources & Uses'!F7)))^(1/5)-1,0) -> 0.09027584 | E6: =IFERROR(((('Operating Model'!H8*E$4-'Debt Schedule'!G28)*(1-Assumptions!$E$30))/MAX(0.01,('Operating Model'!C8*$B6+Assumptions!$E$15+'Sources & Uses'!C7+Assumptions!$E$16-'Sources & Uses'!F6-'Sources & Uses'!F7)))^(1/5)-1,0) -> 0.12832986 | F6: =IFERROR(((('Operating Model'!H8*F$4-'Debt Schedule'!G28)*(1-Assumptions!$E$30))/MAX(0.01,('Operating Model'!C8*$B6+Assumptions!$E$15+'Sources & Uses'!C7+Assumptions!$E$16-'Sources & Uses'!F6-'Sources & Uses'!F7)))^(1/5)-1,0) -> 0.16185045 | G6: =IFERROR(((('Operating Model'!H8*G$4-'Debt Schedule'!G28)*(1-Assumptions!$E$30))/MAX(0.01,('Operating Model'!C8*$B6+Assumptions!$E$15+'Sources & Uses'!C7+Assumptions!$E$16-'Sources & Uses'!F6-'Sources & Uses'!F7)))^(1/5)-1,0) -> 0.19189706
B7: 10 | C7: =IFERROR(((('Operating Model'!H8*C$4-'Debt Schedule'!G28)*(1-Assumptions!$E$30))/MAX(0.01,('Operating Model'!C8*$B7+Assumptions!$E$15+'Sources & Uses'!C7+Assumptions!$E$16-'Sources & Uses'!F6-'Sources & Uses'!F7)))^(1/5)-1,0) -> 0.0064336656 | D7: =IFERROR(((('Operating Model'!H8*D$4-'Debt Schedule'!G28)*(1-Assumptions!$E$30))/MAX(0.01,('Operating Model'!C8*$B7+Assumptions!$E$15+'Sources & Uses'!C7+Assumptions!$E$16-'Sources & Uses'!F6-'Sources & Uses'!F7)))^(1/5)-1,0) -> 0.049013287 | E7: =IFERROR(((('Operating Model'!H8*E$4-'Debt Schedule'!G28)*(1-Assumptions!$E$30))/MAX(0.01,('Operating Model'!C8*$B7+Assumptions!$E$15+'Sources & Uses'!C7+Assumptions!$E$16-'Sources & Uses'!F6-'Sources & Uses'!F7)))^(1/5)-1,0) -> 0.085627113 | F7: =IFERROR(((('Operating Model'!H8*F$4-'Debt Schedule'!G28)*(1-Assumptions!$E$30))/MAX(0.01,('Operating Model'!C8*$B7+Assumptions!$E$15+'Sources & Uses'!C7+Assumptions!$E$16-'Sources & Uses'!F6-'Sources & Uses'!F7)))^(1/5)-1,0) -> 0.11787909 | G7: =IFERROR(((('Operating Model'!H8*G$4-'Debt Schedule'!G28)*(1-Assumptions!$E$30))/MAX(0.01,('Operating Model'!C8*$B7+Assumptions!$E$15+'Sources & Uses'!C7+Assumptions!$E$16-'Sources & Uses'!F6-'Sources & Uses'!F7)))^(1/5)-1,0) -> 0.14678855
B8: 11 | C8: =IFERROR(((('Operating Model'!H8*C$4-'Debt Schedule'!G28)*(1-Assumptions!$E$30))/MAX(0.01,('Operating Model'!C8*$B8+Assumptions!$E$15+'Sources & Uses'!C7+Assumptions!$E$16-'Sources & Uses'!F6-'Sources & Uses'!F7)))^(1/5)-1,0) -> -0.025582295 | D8: =IFERROR(((('Operating Model'!H8*D$4-'Debt Schedule'!G28)*(1-Assumptions!$E$30))/MAX(0.01,('Operating Model'!C8*$B8+Assumptions!$E$15+'Sources & Uses'!C7+Assumptions!$E$16-'Sources & Uses'!F6-'Sources & Uses'!F7)))^(1/5)-1,0) -> 0.015642813 | E8: =IFERROR(((('Operating Model'!H8*E$4-'Debt Schedule'!G28)*(1-Assumptions!$E$30))/MAX(0.01,('Operating Model'!C8*$B8+Assumptions!$E$15+'Sources & Uses'!C7+Assumptions!$E$16-'Sources & Uses'!F6-'Sources & Uses'!F7)))^(1/5)-1,0) -> 0.051091905 | F8: =IFERROR(((('Operating Model'!H8*F$4-'Debt Schedule'!G28)*(1-Assumptions!$E$30))/MAX(0.01,('Operating Model'!C8*$B8+Assumptions!$E$15+'Sources & Uses'!C7+Assumptions!$E$16-'Sources & Uses'!F6-'Sources & Uses'!F7)))^(1/5)-1,0) -> 0.082317904 | G8: =IFERROR(((('Operating Model'!H8*G$4-'Debt Schedule'!G28)*(1-Assumptions!$E$30))/MAX(0.01,('Operating Model'!C8*$B8+Assumptions!$E$15+'Sources & Uses'!C7+Assumptions!$E$16-'Sources & Uses'!F6-'Sources & Uses'!F7)))^(1/5)-1,0) -> 0.11030772
B9: 12 | C9: =IFERROR(((('Operating Model'!H8*C$4-'Debt Schedule'!G28)*(1-Assumptions!$E$30))/MAX(0.01,('Operating Model'!C8*$B9+Assumptions!$E$15+'Sources & Uses'!C7+Assumptions!$E$16-'Sources & Uses'!F6-'Sources & Uses'!F7)))^(1/5)-1,0) -> -0.052319419 | D9: =IFERROR(((('Operating Model'!H8*D$4-'Debt Schedule'!G28)*(1-Assumptions!$E$30))/MAX(0.01,('Operating Model'!C8*$B9+Assumptions!$E$15+'Sources & Uses'!C7+Assumptions!$E$16-'Sources & Uses'!F6-'Sources & Uses'!F7)))^(1/5)-1,0) -> -0.012225489 | E9: =IFERROR(((('Operating Model'!H8*E$4-'Debt Schedule'!G28)*(1-Assumptions!$E$30))/MAX(0.01,('Operating Model'!C8*$B9+Assumptions!$E$15+'Sources & Uses'!C7+Assumptions!$E$16-'Sources & Uses'!F6-'Sources & Uses'!F7)))^(1/5)-1,0) -> 0.022250913 | F9: =IFERROR(((('Operating Model'!H8*F$4-'Debt Schedule'!G28)*(1-Assumptions!$E$30))/MAX(0.01,('Operating Model'!C8*$B9+Assumptions!$E$15+'Sources & Uses'!C7+Assumptions!$E$16-'Sources & Uses'!F6-'Sources & Uses'!F7)))^(1/5)-1,0) -> 0.052620099 | G9: =IFERROR(((('Operating Model'!H8*G$4-'Debt Schedule'!G28)*(1-Assumptions!$E$30))/MAX(0.01,('Operating Model'!C8*$B9+Assumptions!$E$15+'Sources & Uses'!C7+Assumptions!$E$16-'Sources & Uses'!F6-'Sources & Uses'!F7)))^(1/5)-1,0) -> 0.079841902

Sheet Checks
B2: LBO Model Checks
B4: Check | C4: Status
B5: Sources equal uses | C5: =IF(ABS('Sources & Uses'!F10)<0.000001,"PASS","FAIL") -> PASS
B6: Sponsor equity positive | C6: =IF('Sources & Uses'!F8>0,"PASS","FAIL") -> PASS
B7: Debt balances nonnegative | C7: =IF(MIN('Debt Schedule'!D15:J25)>=0,"PASS","FAIL") -> PASS
B8: Cash at or above minimum | C8: =IF(MIN('Debt Schedule'!D13:J13)>=Assumptions!E16,"PASS","REVIEW") -> PASS
B9: No covenant breaches | C9: =IF(COUNTIF(Covenants!C13:I13,"BREACH")=0,"PASS","REVIEW") -> PASS
B10: Exit equity nonnegative | C10: =IF(MIN('Returns Waterfall'!C9:I9)>=0,"PASS","FAIL") -> PASS
B11: Waterfall conserves equity | C11: =IF(MAX(ABS('Returns Waterfall'!C9:I9-'Returns Waterfall'!C12:I12-'Returns Waterfall'!C13:I13))<0.000001,"PASS","FAIL") -> PASS
B12: Selected exit year valid | C12: =IF(AND(Assumptions!E29>=1,Assumptions!E29<=7),"PASS","FAIL") -> PASS
B13: Overall | C13: =IF(COUNTIF(C5:C12,"FAIL")=0,"PASS","FAIL") -> PASS

Sheet Sources
B2: Source Register
B4: Input / dataset | C4: Source URL or document | D4: As-of | E4: Notes / transformation
B5: Historical financial statements | C5: [filing / data room URL] | D5: [period] | E5: Revenue, margins, capex, working capital, taxes
B6: Quality of earnings and diligence | C6: [advisor report URL] | D6: [date] | E6: EBITDA adjustments, one-time items, risks
B7: Debt term sheets and documentation | C7: [data room URL] | D7: [date] | E7: Rates, PIK, amortization, sweeps, covenants, baskets
B8: Transaction terms | C8: [purchase agreement / process letter] | D8: [date] | E8: Price, fees, minimum cash, rollover, management pool
B9: Market valuation references | C9: [public market / transaction source] | D9: [date] | E9: Entry and exit multiple support

Sheet RefreshLog
B2: Refresh Log
B4: Date | C4: Trigger | D4: Source snapshot | E4: What changed | F4: Reviewer / challenge | G4: Next check
