Workbook
Name FS_MODEL_ID: 'Institutional Surface'!$C$4
Name FS_DOMAIN: 'Institutional Surface'!$C$5
Name FS_MATURITY: 'Institutional Surface'!$C$6

Sheet Cover
B2: [PORTFOLIO] — Multi-Asset Risk Model
B4: Portfolio / desk: | C4: [Name]
B5: Risk horizon: | C5: 1-day and stressed liquidation
B6: Last refreshed: | C6: [timestamp]
B7: Next limit review: | C7: [date]
B8: Refresh cadence: | C8: Intraday / daily
B9: Active scenario: | C9: Base
B10: Units: | C10: $ in millions unless noted
B13: Modeling conventions
B14: Blue text / yellow fill | C14: Hardcoded input or selected scenario
B15: Black text | C15: Formula / same-sheet calculation
B16: Green text | C16: Cross-sheet formula / link
B17: Checks | C17: PASS / REVIEW / FAIL must remain visible

Sheet Institutional Surface
B2: Risk Management — Institutional Decision Surface
B4: Model ID | C4: 09
B5: Domain | C5: Risk Management
B6: Declared maturity | C6: M2
B7: Canonical builder | C7: tools/builders/build_risk_release.py
B8: Decision arena | C8: trading desk, independent risk, model validation, senior risk committee and regulator
B9: Committee artifact | C9: daily risk and limit pack
B10: Operating cadence | C10: intraday monitoring; daily sign-off; monthly committee
B12: Key decision outputs
B13: # | C13: Requirement | D13: Owner | E13: Evidence / location | F13: Status
B14: 1 | C14: VaR / ES and stress loss | F14: OPEN
B15: 2 | C15: factor and component risk | F15: OPEN
B16: 3 | C16: liquidity horizon and liquidation cost | F16: OPEN
B17: 4 | C17: base, downside and break-even outputs | F17: OPEN
B18: 5 | C18: liquidity / funding requirement and binding constraint | F18: OPEN
B20: Insider questions
B21: # | C21: Requirement | D21: Owner | E21: Evidence / location | F21: Status
B22: 1 | C22: What risk is missing from the factor map? | F22: OPEN
B23: 2 | C23: Where does diversification disappear under stress? | F23: OPEN
B24: 3 | C24: Which desk would fail model eligibility? | F24: OPEN
B25: 4 | C25: Which assumption is owner-approved versus modeler judgement? | F25: OPEN
B26: 5 | C26: What fails first and who must act? | F26: OPEN
B28: Scenario families
B29: # | C29: Requirement | D29: Owner | E29: Evidence / location | F29: Status
B30: 1 | C30: historical and hypothetical stress | F30: OPEN
B31: 2 | C31: correlation break | F31: OPEN
B32: 3 | C32: basis and spread dislocation | F32: OPEN
B33: 4 | C33: data freshness / source failure | F33: OPEN
B34: 5 | C34: combined severe-but-plausible downside | F34: OPEN
B36: Primary diligence documents
B37: # | C37: Requirement | D37: Owner | E37: Evidence / location | F37: Status
B38: 1 | C38: risk appetite and limits | F38: OPEN
B39: 2 | C39: product control P&L | F39: OPEN
B40: 3 | C40: market data hierarchy | F40: OPEN
B41: 4 | C41: approved model card and assumption register | F41: OPEN
B42: 5 | C42: independent validation and challenge record | F42: OPEN
B44: Challenge tests
B45: # | C45: Requirement | D45: Owner | E45: Evidence / location | F45: Status
B46: 1 | C46: component risk reconciles to total | F46: OPEN
B47: 2 | C47: ES not below VaR at same confidence | F47: OPEN
B48: 3 | C48: stress loss sign conventions consistent | F48: OPEN
B49: 4 | C49: source-to-model lineage is reproducible | F49: OPEN
B50: 5 | C50: units, signs, dates and legal definitions reconcile | F50: OPEN
B52: Known failure modes
B53: # | C53: Requirement | D53: Owner | E53: Evidence / location | F53: Status
B54: 1 | C54: diversification masking concentration | F54: OPEN
B55: 2 | C55: using stale sensitivities | F55: OPEN
B56: 3 | C56: mapping risks to wrong buckets | F56: OPEN
B57: 4 | C57: stale vintage presented as current | F57: OPEN
B58: 5 | C58: decision output disconnected from a binding constraint | F58: OPEN
B60: Regulatory / methodological anchors
B61: Standard | C61: Scope | D61: Source URL | E61: Applicability | F61: Review note
B62: Federal Reserve SR 26-2 Model Risk Management | C62: governance, validation, change control, monitoring | D62: https://www.federalreserve.gov/supervisionreg/srletters/SR2602.htm | E62: Map explicitly
B63: Basel Framework | C63: prudential capital, liquidity, credit and market risk | D63: https://www.bis.org/basel_framework/ | E63: Map explicitly
B64: Basel MAR21 Sensitivities-Based Method | C64: market-risk factors and aggregation | D64: https://www.bis.org/basel_framework/chapter/MAR/21.htm | E64: Map explicitly

Sheet Challenge Log
B2: Independent Challenge, Override and Closure Log
B4: Date | C4: Reviewer | D4: Challenge | E4: Owner response | F4: Evidence | G4: Impact | H4: Status | I4: Closure
D5: component risk reconciles to total | H5: OPEN
D6: ES not below VaR at same confidence | H6: OPEN
D7: stress loss sign conventions consistent | H7: OPEN
D8: source-to-model lineage is reproducible | H8: OPEN
D9: units, signs, dates and legal definitions reconcile | H9: OPEN

Sheet Lineage Map
B2: Source, Transformation, Ownership and Refresh Map
B4: Source class | C4: Cadence | D4: Control | E4: System / provider | F4: As-of | G4: Owner | H4: Transform | I4: Downstream | J4: Status
B5: positions | C5: intraday/daily | D5: front-to-back reconciliation | J5: TO MAP
B6: market data | C6: intraday/daily | D6: source and stale-point controls | J6: TO MAP
B7: model governance evidence | C7: per release | D7: version, reviewer, sign-off and change log | J7: TO MAP
B8: decision-use snapshot | C8: per decision | D8: immutable as-of date and source receipt | J8: TO MAP

Sheet Assumptions
B2: Risk and Liquidity Assumptions
B4: Assumption | C4: Base | D4: Downside | E4: Active | F4: Units / note
B5: VaR confidence | C5: 0.99 | D5: 0.995 | E5: =IF(Cover!$C$9="Downside",D5,C5) | F5: %
B6: Trading days per year | C6: 252 | D6: 252 | E6: =IF(Cover!$C$9="Downside",D6,C6) | F6: days
B7: Equity annual volatility | C7: 0.22 | D7: 0.35 | E7: =IF(Cover!$C$9="Downside",D7,C7) | F7: %
B8: Rates annual volatility | C8: 0.012 | D8: 0.025 | E8: =IF(Cover!$C$9="Downside",D8,C8) | F8: yield change
B9: Credit annual volatility | C9: 0.015 | D9: 0.035 | E9: =IF(Cover!$C$9="Downside",D9,C9) | F9: spread change
B10: FX annual volatility | C10: 0.12 | D10: 0.2 | E10: =IF(Cover!$C$9="Downside",D10,C10) | F10: %
B11: Volatility-factor annual volatility | C11: 0.3 | D11: 0.5 | E11: =IF(Cover!$C$9="Downside",D11,C11) | F11: %
B12: Maximum portfolio VaR | C12: 12 | D12: 10 | E12: =IF(Cover!$C$9="Downside",D12,C12) | F12: $mm
B13: Maximum stress loss | C13: 40 | D13: 30 | E13: =IF(Cover!$C$9="Downside",D13,C13) | F13: $mm
B14: Maximum illiquid NAV | C14: 0.25 | D14: 0.2 | E14: =IF(Cover!$C$9="Downside",D14,C14) | F14: %
B15: Maximum single-name concentration | C15: 0.2 | D15: 0.15 | E15: =IF(Cover!$C$9="Downside",D15,C15) | F15: %
B16: Maximum gross leverage | C16: 4 | D16: 3 | E16: =IF(Cover!$C$9="Downside",D16,C16) | F16: x
... B18: Available capital / NAV | C18: 250 | D18: 250 | E18: =IF(Cover!$C$9="Downside",D18,C18) | F18: $mm

Sheet Positions
B2: Position-Level Risk Inventory
B4: Instrument | C4: Asset class | D4: Market value | E4: Gross notional | F4: Delta | G4: Beta | H4: Duration | I4: Spread duration | J4: DV01 | K4: Vega | L4: FX delta | M4: Days to liquidate | N4: Equity | O4: Rates | P4: Credit | Q4: FX | R4: Volatility | S4: Weighted risk exposure
B5: Equity Index Future | C5: Equity | D5: 45 | E5: 120 | F5: 1 | G5: 1 | H5: 0 | I5: 0 | J5: 0 | K5: 0 | L5: 0 | M5: 0.2 | N5: 1 | O5: 0 | P5: 0 | Q5: 0 | R5: 0 | S5: =SUMPRODUCT(C5:Q5,C5:Q5)^0.5
B6: Single Name A | C6: Equity | D6: 35 | E6: 35 | F6: 1 | G6: 1.2 | H6: 0 | I6: 0 | J6: 0 | K6: 0 | L6: 0 | M6: 1 | N6: 1.2 | O6: 0 | P6: 0.1 | Q6: 0 | R6: 0.1 | S6: =SUMPRODUCT(C6:Q6,C6:Q6)^0.5
B7: Single Name Put | C7: Option | D7: 8 | E7: 25 | F7: -0.35 | G7: -0.4 | H7: 0 | I7: 0 | J7: 0 | K7: 0.18 | L7: 0 | M7: 1.5 | N7: -0.4 | O7: 0 | P7: 0 | Q7: 0 | R7: 0.8 | S7: =SUMPRODUCT(C7:Q7,C7:Q7)^0.5
B8: 10Y Treasury | C8: Rates | D8: 50 | E8: 50 | F8: 1 | G8: 0 | H8: 8.2 | I8: 0 | J8: 0.041 | K8: 0 | L8: 0 | M8: 0.5 | N8: 0 | O8: -8.2 | P8: 0 | Q8: 0 | R8: 0 | S8: =SUMPRODUCT(C8:Q8,C8:Q8)^0.5
B9: IG Credit ETF | C9: Credit | D9: 32 | E9: 50 | F9: 1 | G9: 0.35 | H9: 5.5 | I9: 5 | J9: 0.018 | K9: 0 | L9: 0 | M9: 1 | N9: 0.35 | O9: -2 | P9: -5 | Q9: 0 | R9: 0 | S9: =SUMPRODUCT(C9:Q9,C9:Q9)^0.5
B10: HY Bond | C10: Credit | D10: 28 | E10: 40 | F10: 1 | G10: 0.55 | H10: 4 | I10: 3.8 | J10: 0.011 | K10: 0 | L10: 0 | M10: 4 | N10: 0.55 | O10: -1 | P10: -3.8 | Q10: 0 | R10: 0 | S10: =SUMPRODUCT(C10:Q10,C10:Q10)^0.5
B11: EURUSD Forward | C11: FX | D11: 5 | E11: 80 | F11: 1 | G11: 0 | H11: 0 | I11: 0 | J11: 0 | K11: 0 | L11: 80 | M11: 0.3 | N11: 0 | O11: 0 | P11: 0 | Q11: 1 | R11: 0 | S11: =SUMPRODUCT(C11:Q11,C11:Q11)^0.5
B12: Commodity Future | C12: Commodity | D12: 20 | E12: 65 | F12: 1 | G12: 0.25 | H12: 0 | I12: 0 | J12: 0 | K12: 0 | L12: 0 | M12: 0.5 | N12: 0.25 | O12: 0 | P12: 0.2 | Q12: 0.1 | R12: 0.1 | S12: =SUMPRODUCT(C12:Q12,C12:Q12)^0.5
B13: Variance Swap | C13: Volatility | D13: 6 | E13: 30 | F13: 0 | G13: 0 | H13: 0 | I13: 0 | J13: 0 | K13: 0.45 | L13: 0 | M13: 2 | N13: 0 | O13: 0 | P13: 0 | Q13: 0 | R13: 1 | S13: =SUMPRODUCT(C13:Q13,C13:Q13)^0.5
B14: Private Credit Position | C14: Private | D14: 40 | E14: 40 | F14: 1 | G14: 0.2 | H14: 2 | I14: 2.5 | J14: 0.008 | K14: 0 | L14: 0 | M14: 20 | N14: 0.2 | O14: -0.5 | P14: -2.5 | Q14: 0 | R14: 0 | S14: =SUMPRODUCT(C14:Q14,C14:Q14)^0.5
B15: Cash | C15: Cash | D15: 25 | E15: 25 | F15: 1 | G15: 0 | H15: 0 | I15: 0 | J15: 0 | K15: 0 | L15: 0 | M15: 0 | N15: 0 | O15: 0 | P15: 0 | Q15: 0 | R15: 0 | S15: =SUMPRODUCT(C15:Q15,C15:Q15)^0.5
B16: Short Equity Basket | C16: Equity | D16: -18 | E16: 60 | F16: -1 | G16: -0.9 | H16: 0 | I16: 0 | J16: 0 | K16: 0 | L16: 0 | M16: 0.5 | N16: -0.9 | O16: 0 | P16: -0.1 | Q16: 0 | R16: 0 | S16: =SUMPRODUCT(C16:Q16,C16:Q16)^0.5
B18: Portfolio total | D18: =SUM(D5:D16) | E18: =SUM(E5:E16) | J18: =SUM(J5:J16) | K18: =SUM(K5:K16) | L18: =SUM(L5:L16) | S18: =SUM(S5:S16)

Sheet Factors
B2: Factor Exposure and Covariance
B4: Factor | C4: Exposure | D4: Annual vol | E4: Equity | F4: Rates | G4: Credit | H4: FX | I4: Volatility
B5: Equity | C5: =SUMPRODUCT(Positions!$D$5:$D$16,Positions!$N$5:$N$16) | D5: =Assumptions!E7 | E5: 1 | F5: -0.2 | G5: 0.35 | H5: 0.1 | I5: 0.45
B6: Rates | C6: =SUMPRODUCT(Positions!$D$5:$D$16,Positions!$O$5:$O$16) | D6: =Assumptions!E8 | E6: -0.2 | F6: 1 | G6: -0.25 | H6: 0.05 | I6: -0.1
B7: Credit | C7: =SUMPRODUCT(Positions!$D$5:$D$16,Positions!$P$5:$P$16) | D7: =Assumptions!E9 | E7: 0.35 | F7: -0.25 | G7: 1 | H7: 0.1 | I7: 0.3
B8: FX | C8: =SUMPRODUCT(Positions!$D$5:$D$16,Positions!$Q$5:$Q$16) | D8: =Assumptions!E10 | E8: 0.1 | F8: 0.05 | G8: 0.1 | H8: 1 | I8: 0.1
B9: Volatility | C9: =SUMPRODUCT(Positions!$D$5:$D$16,Positions!$R$5:$R$16) | D9: =Assumptions!E11 | E9: 0.45 | F9: -0.1 | G9: 0.3 | H9: 0.1 | I9: 1
B12: Annual portfolio variance | C12: =$C$5*$C$5*$D$5*$D$5*E5+$C$5*$C$6*$D$5*$D$6*F5+$C$5*$C$7*$D$5*$D$7*G5+$C$5*$C$8*$D$5*$D$8*H5+$C$5*$C$9*$D$5*$D$9*I5+$C$6*$C$5*$D$6*$D$5*E6+$C$6*$C$6*$D$6*$D$6*F6+$C$6*$C$7*$D$6*$D$7*G6+$C$6*$C$8*$D$6*$D$8*H6+$C$6*$C$9*$D$6*$D$9*I6+$C$7*$C$5*$D$7*$D$5*E7+$C$7*$C$6*$D$7*$D$6*F7+$C$7*$C$7*$D$7*$D$7*G7+$C$7*$C$8*$D$7*$D$8*H7+$C$7*$C$9*$D$7*$D$9*I7+$C$8*$C$5*$D$8*$D$5*E8+$C$8*$C$6*$D$8*$D$6*F8+$C$8*$C$7*$D$8*$D$7*G8+$C$8*$C$8*$D$8*$D$8*H8+$C$8*$C$9*$D$8*$D$9*I8+$C$9*$C$5*$D$9*$D$5*E9+$C$9*$C$6*$D$9*$D$6*F9+$C$9*$C$7*$D$9*$D$7*G9+$C$9*$C$8*$D$9*$D$8*H9+$C$9*$C$9*$D$9*$D$9*I9
B13: Annual portfolio volatility | C13: =SQRT(MAX(0,C12))

Sheet VaR & ES
B2: Parametric VaR and Expected Shortfall
B4: Metric | C4: Value | D4: Units | E4: Method
B5: Annual portfolio volatility | C5: =Factors!C13 | D5: $mm | E5: factor covariance
B6: Daily portfolio volatility | C6: =C5/SQRT(Assumptions!E6) | D6: $mm | E6: annual / sqrt(days)
B7: Normal quantile | C7: =-NORMSINV(1-Assumptions!E5) | D7: z | E7: confidence quantile
B8: One-day VaR | C8: =C6*C7 | D8: $mm | E8: sigma x z
B9: One-day expected shortfall | C9: =C6*(EXP(-((C7)^2)/2)/SQRT(2*PI()))/(1-Assumptions!E5) | D9: $mm | E9: normal tail expectation
B10: VaR / NAV | C10: =C8/Assumptions!E18 | D10: % | E10: capital consumption
B11: Diversification benefit | C11: =1-C5/SUMPRODUCT(ABS(Factors!C5:C9),Factors!D5:D9) | D11: % | E11: 1 - portfolio / standalone

Sheet Risk Contributions
B2: Position-Level VaR, Stress, and Liquidity Contributions
B4: Instrument | C4: Gross notional | D4: Standalone VaR | E4: Component VaR | F4: % portfolio VaR | G4: Worst stress loss | H4: Liquidation loss | I4: Liquidity-adjusted risk | J4: Risk concentration
B5: =Positions!B5 | C5: =ABS(Positions!E5) | D5: ='VaR & ES'!$C$7*SQRT(MAX(0,((Positions!$E$5*Positions!$N$5)*(Positions!$E$5*Positions!$N$5)*Factors!$D$5*Factors!$D$5*Factors!$E$5+(Positions!$E$5*Positions!$N$5)*(Positions!$E$5*Positions!$O$5)*Factors!$D$5*Factors!$D$6*Factors!$F$5+(Positions!$E$5*Positions!$N$5)*(Positions!$E$5*Positions!$P$5)*Factors!$D$5*Factors!$D$7*Factors!$G$5+(Positions!$E$5*Positions!$N$5)*(Positions!$E$5*Positions!$Q$5)*Factors!$D$5*Factors!$D$8*Factors!$H$5+(Positions!$E$5*Positions!$N$5)*(Positions!$E$5*Positions!$R$5)*Factors!$D$5*Factors!$D$9*Factors!$I$5+(Positions!$E$5*Positions!$O$5)*(Positions!$E$5*Positions!$N$5)*Factors!$D$6*Factors!$D$5*Factors!$E$6+(Positions!$E$5*Positions!$O$5)*(Positions!$E$5*Positions!$O$5)*Factors!$D$6*Factors!$D$6*Factors!$F$6+(Positions!$E$5*Positions!$O$5)*(Positions!$E$5*Positions!$P$5)*Factors!$D$6*Factors!$D$7*Factors!$G$6+(Positions!$E$5*Positions!$O$5)*(Positions!$E$5*Positions!$Q$5)*Factors!$D$6*Factors!$D$8*Factors!$H$6+(Positions!$E$5*Positions!$O$5)*(Positions!$E$5*Positions!$R$5)*Factors!$D$6*Factors!$D$9*Factors!$I$6+(Positions!$E$5*Positions!$P$5)*(Positions!$E$5*Positions!$N$5)*Factors!$D$7*Factors!$D$5*Factors!$E$7+(Positions!$E$5*Positions!$P$5)*(Positions!$E$5*Positions!$O$5)*Factors!$D$7*Factors!$D$6*Factors!$F$7+(Positions!$E$5*Positions!$P$5)*(Positions!$E$5*Positions!$P$5)*Factors!$D$7*Factors!$D$7*Factors!$G$7+(Positions!$E$5*Positions!$P$5)*(Positions!$E$5*Positions!$Q$5)*Factors!$D$7*Factors!$D$8*Factors!$H$7+(Positions!$E$5*Positions!$P$5)*(Positions!$E$5*Positions!$R$5)*Factors!$D$7*Factors!$D$9*Factors!$I$7+(Positions!$E$5*Positions!$Q$5)*(Positions!$E$5*Positions!$N$5)*Factors!$D$8*Factors!$D$5*Factors!$E$8+(Positions!$E$5*Positions!$Q$5)*(Positions!$E$5*Positions!$O$5)*Factors!$D$8*Factors!$D$6*Factors!$F$8+(Positions!$E$5*Positions!$Q$5)*(Positions!$E$5*Positions!$P$5)*Factors!$D$8*Factors!$D$7*Factors!$G$8+(Positions!$E$5*Positions!$Q$5)*(Positions!$E$5*Positions!$Q$5)*Factors!$D$8*Factors!$D$8*Factors!$H$8+(Positions!$E$5*Positions!$Q$5)*(Positions!$E$5*Positions!$R$5)*Factors!$D$8*Factors!$D$9*Factors!$I$8+(Positions!$E$5*Positions!$R$5)*(Positions!$E$5*Positions!$N$5)*Factors!$D$9*Factors!$D$5*Factors!$E$9+(Positions!$E$5*Positions!$R$5)*(Positions!$E$5*Positions!$O$5)*Factors!$D$9*Factors!$D$6*Factors!$F$9+(Positions!$E$5*Positions!$R$5)*(Positions!$E$5*Positions!$P$5)*Factors!$D$9*Factors!$D$7*Factors!$G$9+(Positions!$E$5*Positions!$R$5)*(Positions!$E$5*Positions!$Q$5)*Factors!$D$9*Factors!$D$8*Factors!$H$9+(Positions!$E$5*Positions!$R$5)*(Positions!$E$5*Positions!$R$5)*Factors!$D$9*Factors!$D$9*Factors!$I$9)/Assumptions!$E$6)) | E5: =IFERROR('VaR & ES'!$C$7*((Positions!$E$5*Positions!$N$5)*Factors!$D$5*Factors!$C$5*Factors!$D$5*Factors!$E$5+(Positions!$E$5*Positions!$N$5)*Factors!$D$5*Factors!$C$6*Factors!$D$6*Factors!$F$5+(Positions!$E$5*Positions!$N$5)*Factors!$D$5*Factors!$C$7*Factors!$D$7*Factors!$G$5+(Positions!$E$5*Positions!$N$5)*Factors!$D$5*Factors!$C$8*Factors!$D$8*Factors!$H$5+(Positions!$E$5*Positions!$N$5)*Factors!$D$5*Factors!$C$9*Factors!$D$9*Factors!$I$5+(Positions!$E$5*Positions!$O$5)*Factors!$D$6*Factors!$C$5*Factors!$D$5*Factors!$E$6+(Positions!$E$5*Positions!$O$5)*Factors!$D$6*Factors!$C$6*Factors!$D$6*Factors!$F$6+(Positions!$E$5*Positions!$O$5)*Factors!$D$6*Factors!$C$7*Factors!$D$7*Factors!$G$6+(Positions!$E$5*Positions!$O$5)*Factors!$D$6*Factors!$C$8*Factors!$D$8*Factors!$H$6+(Positions!$E$5*Positions!$O$5)*Factors!$D$6*Factors!$C$9*Factors!$D$9*Factors!$I$6+(Positions!$E$5*Positions!$P$5)*Factors!$D$7*Factors!$C$5*Factors!$D$5*Factors!$E$7+(Positions!$E$5*Positions!$P$5)*Factors!$D$7*Factors!$C$6*Factors!$D$6*Factors!$F$7+(Positions!$E$5*Positions!$P$5)*Factors!$D$7*Factors!$C$7*Factors!$D$7*Factors!$G$7+(Positions!$E$5*Positions!$P$5)*Factors!$D$7*Factors!$C$8*Factors!$D$8*Factors!$H$7+(Positions!$E$5*Positions!$P$5)*Factors!$D$7*Factors!$C$9*Factors!$D$9*Factors!$I$7+(Positions!$E$5*Positions!$Q$5)*Factors!$D$8*Factors!$C$5*Factors!$D$5*Factors!$E$8+(Positions!$E$5*Positions!$Q$5)*Factors!$D$8*Factors!$C$6*Factors!$D$6*Factors!$F$8+(Positions!$E$5*Positions!$Q$5)*Factors!$D$8*Factors!$C$7*Factors!$D$7*Factors!$G$8+(Positions!$E$5*Positions!$Q$5)*Factors!$D$8*Factors!$C$8*Factors!$D$8*Factors!$H$8+(Positions!$E$5*Positions!$Q$5)*Factors!$D$8*Factors!$C$9*Factors!$D$9*Factors!$I$8+(Positions!$E$5*Positions!$R$5)*Factors!$D$9*Factors!$C$5*Factors!$D$5*Factors!$E$9+(Positions!$E$5*Positions!$R$5)*Factors!$D$9*Factors!$C$6*Factors!$D$6*Factors!$F$9+(Positions!$E$5*Positions!$R$5)*Factors!$D$9*Factors!$C$7*Factors!$D$7*Factors!$G$9+(Positions!$E$5*Positions!$R$5)*Factors!$D$9*Factors!$C$8*Factors!$D$8*Factors!$H$9+(Positions!$E$5*Positions!$R$5)*Factors!$D$9*Factors!$C$9*Factors!$D$9*Factors!$I$9)/(Factors!$C$13*SQRT(Assumptions!$E$6)),0) | F5: =IFERROR(E5/'VaR & ES'!$C$8,0) | G5: =-MIN((Positions!$E$5*Positions!$N$5*Stress!$C$5+Positions!$E$5*Positions!$O$5*Stress!$D$5+Positions!$E$5*Positions!$P$5*Stress!$E$5+Positions!$E$5*Positions!$Q$5*Stress!$F$5+Positions!$E$5*Positions!$R$5*Stress!$G$5),(Positions!$E$5*Positions!$N$5*Stress!$C$6+Positions!$E$5*Positions!$O$5*Stress!$D$6+Positions!$E$5*Positions!$P$5*Stress!$E$6+Positions!$E$5*Positions!$Q$5*Stress!$F$6+Positions!$E$5*Positions!$R$5*Stress!$G$6),(Positions!$E$5*Positions!$N$5*Stress!$C$7+Positions!$E$5*Positions!$O$5*Stress!$D$7+Positions!$E$5*Positions!$P$5*Stress!$E$7+Positions!$E$5*Positions!$Q$5*Stress!$F$7+Positions!$E$5*Positions!$R$5*Stress!$G$7),(Positions!$E$5*Positions!$N$5*Stress!$C$8+Positions!$E$5*Positions!$O$5*Stress!$D$8+Positions!$E$5*Positions!$P$5*Stress!$E$8+Positions!$E$5*Positions!$Q$5*Stress!$F$8+Positions!$E$5*Positions!$R$5*Stress!$G$8),(Positions!$E$5*Positions!$N$5*Stress!$C$9+Positions!$E$5*Positions!$O$5*Stress!$D$9+Positions!$E$5*Positions!$P$5*Stress!$E$9+Positions!$E$5*Positions!$Q$5*Stress!$F$9+Positions!$E$5*Positions!$R$5*Stress!$G$9),(Positions!$E$5*Positions!$N$5*Stress!$C$10+Positions!$E$5*Positions!$O$5*Stress!$D$10+Positions!$E$5*Positions!$P$5*Stress!$E$10+Positions!$E$5*Positions!$Q$5*Stress!$F$10+Positions!$E$5*Positions!$R$5*Stress!$G$10)) | H5: =Liquidity!G5 | I5: =ABS(E5)+G5+H5 | J5: =IFERROR(I5/SUM($I$5:$I$16),0)
B6: =Positions!B6 | C6: =ABS(Positions!E6) | D6: ='VaR & ES'!$C$7*SQRT(MAX(0,((Positions!$E$6*Positions!$N$6)*(Positions!$E$6*Positions!$N$6)*Factors!$D$5*Factors!$D$5*Factors!$E$5+(Positions!$E$6*Positions!$N$6)*(Positions!$E$6*Positions!$O$6)*Factors!$D$5*Factors!$D$6*Factors!$F$5+(Positions!$E$6*Positions!$N$6)*(Positions!$E$6*Positions!$P$6)*Factors!$D$5*Factors!$D$7*Factors!$G$5+(Positions!$E$6*Positions!$N$6)*(Positions!$E$6*Positions!$Q$6)*Factors!$D$5*Factors!$D$8*Factors!$H$5+(Positions!$E$6*Positions!$N$6)*(Positions!$E$6*Positions!$R$6)*Factors!$D$5*Factors!$D$9*Factors!$I$5+(Positions!$E$6*Positions!$O$6)*(Positions!$E$6*Positions!$N$6)*Factors!$D$6*Factors!$D$5*Factors!$E$6+(Positions!$E$6*Positions!$O$6)*(Positions!$E$6*Positions!$O$6)*Factors!$D$6*Factors!$D$6*Factors!$F$6+(Positions!$E$6*Positions!$O$6)*(Positions!$E$6*Positions!$P$6)*Factors!$D$6*Factors!$D$7*Factors!$G$6+(Positions!$E$6*Positions!$O$6)*(Positions!$E$6*Positions!$Q$6)*Factors!$D$6*Factors!$D$8*Factors!$H$6+(Positions!$E$6*Positions!$O$6)*(Positions!$E$6*Positions!$R$6)*Factors!$D$6*Factors!$D$9*Factors!$I$6+(Positions!$E$6*Positions!$P$6)*(Positions!$E$6*Positions!$N$6)*Factors!$D$7*Factors!$D$5*Factors!$E$7+(Positions!$E$6*Positions!$P$6)*(Positions!$E$6*Positions!$O$6)*Factors!$D$7*Factors!$D$6*Factors!$F$7+(Positions!$E$6*Positions!$P$6)*(Positions!$E$6*Positions!$P$6)*Factors!$D$7*Factors!$D$7*Factors!$G$7+(Positions!$E$6*Positions!$P$6)*(Positions!$E$6*Positions!$Q$6)*Factors!$D$7*Factors!$D$8*Factors!$H$7+(Positions!$E$6*Positions!$P$6)*(Positions!$E$6*Positions!$R$6)*Factors!$D$7*Factors!$D$9*Factors!$I$7+(Positions!$E$6*Positions!$Q$6)*(Positions!$E$6*Positions!$N$6)*Factors!$D$8*Factors!$D$5*Factors!$E$8+(Positions!$E$6*Positions!$Q$6)*(Positions!$E$6*Positions!$O$6)*Factors!$D$8*Factors!$D$6*Factors!$F$8+(Positions!$E$6*Positions!$Q$6)*(Positions!$E$6*Positions!$P$6)*Factors!$D$8*Factors!$D$7*Factors!$G$8+(Positions!$E$6*Positions!$Q$6)*(Positions!$E$6*Positions!$Q$6)*Factors!$D$8*Factors!$D$8*Factors!$H$8+(Positions!$E$6*Positions!$Q$6)*(Positions!$E$6*Positions!$R$6)*Factors!$D$8*Factors!$D$9*Factors!$I$8+(Positions!$E$6*Positions!$R$6)*(Positions!$E$6*Positions!$N$6)*Factors!$D$9*Factors!$D$5*Factors!$E$9+(Positions!$E$6*Positions!$R$6)*(Positions!$E$6*Positions!$O$6)*Factors!$D$9*Factors!$D$6*Factors!$F$9+(Positions!$E$6*Positions!$R$6)*(Positions!$E$6*Positions!$P$6)*Factors!$D$9*Factors!$D$7*Factors!$G$9+(Positions!$E$6*Positions!$R$6)*(Positions!$E$6*Positions!$Q$6)*Factors!$D$9*Factors!$D$8*Factors!$H$9+(Positions!$E$6*Positions!$R$6)*(Positions!$E$6*Positions!$R$6)*Factors!$D$9*Factors!$D$9*Factors!$I$9)/Assumptions!$E$6)) | E6: =IFERROR('VaR & ES'!$C$7*((Positions!$E$6*Positions!$N$6)*Factors!$D$5*Factors!$C$5*Factors!$D$5*Factors!$E$5+(Positions!$E$6*Positions!$N$6)*Factors!$D$5*Factors!$C$6*Factors!$D$6*Factors!$F$5+(Positions!$E$6*Positions!$N$6)*Factors!$D$5*Factors!$C$7*Factors!$D$7*Factors!$G$5+(Positions!$E$6*Positions!$N$6)*Factors!$D$5*Factors!$C$8*Factors!$D$8*Factors!$H$5+(Positions!$E$6*Positions!$N$6)*Factors!$D$5*Factors!$C$9*Factors!$D$9*Factors!$I$5+(Positions!$E$6*Positions!$O$6)*Factors!$D$6*Factors!$C$5*Factors!$D$5*Factors!$E$6+(Positions!$E$6*Positions!$O$6)*Factors!$D$6*Factors!$C$6*Factors!$D$6*Factors!$F$6+(Positions!$E$6*Positions!$O$6)*Factors!$D$6*Factors!$C$7*Factors!$D$7*Factors!$G$6+(Positions!$E$6*Positions!$O$6)*Factors!$D$6*Factors!$C$8*Factors!$D$8*Factors!$H$6+(Positions!$E$6*Positions!$O$6)*Factors!$D$6*Factors!$C$9*Factors!$D$9*Factors!$I$6+(Positions!$E$6*Positions!$P$6)*Factors!$D$7*Factors!$C$5*Factors!$D$5*Factors!$E$7+(Positions!$E$6*Positions!$P$6)*Factors!$D$7*Factors!$C$6*Factors!$D$6*Factors!$F$7+(Positions!$E$6*Positions!$P$6)*Factors!$D$7*Factors!$C$7*Factors!$D$7*Factors!$G$7+(Positions!$E$6*Positions!$P$6)*Factors!$D$7*Factors!$C$8*Factors!$D$8*Factors!$H$7+(Positions!$E$6*Positions!$P$6)*Factors!$D$7*Factors!$C$9*Factors!$D$9*Factors!$I$7+(Positions!$E$6*Positions!$Q$6)*Factors!$D$8*Factors!$C$5*Factors!$D$5*Factors!$E$8+(Positions!$E$6*Positions!$Q$6)*Factors!$D$8*Factors!$C$6*Factors!$D$6*Factors!$F$8+(Positions!$E$6*Positions!$Q$6)*Factors!$D$8*Factors!$C$7*Factors!$D$7*Factors!$G$8+(Positions!$E$6*Positions!$Q$6)*Factors!$D$8*Factors!$C$8*Factors!$D$8*Factors!$H$8+(Positions!$E$6*Positions!$Q$6)*Factors!$D$8*Factors!$C$9*Factors!$D$9*Factors!$I$8+(Positions!$E$6*Positions!$R$6)*Factors!$D$9*Factors!$C$5*Factors!$D$5*Factors!$E$9+(Positions!$E$6*Positions!$R$6)*Factors!$D$9*Factors!$C$6*Factors!$D$6*Factors!$F$9+(Positions!$E$6*Positions!$R$6)*Factors!$D$9*Factors!$C$7*Factors!$D$7*Factors!$G$9+(Positions!$E$6*Positions!$R$6)*Factors!$D$9*Factors!$C$8*Factors!$D$8*Factors!$H$9+(Positions!$E$6*Positions!$R$6)*Factors!$D$9*Factors!$C$9*Factors!$D$9*Factors!$I$9)/(Factors!$C$13*SQRT(Assumptions!$E$6)),0) | F6: =IFERROR(E6/'VaR & ES'!$C$8,0) | G6: =-MIN((Positions!$E$6*Positions!$N$6*Stress!$C$5+Positions!$E$6*Positions!$O$6*Stress!$D$5+Positions!$E$6*Positions!$P$6*Stress!$E$5+Positions!$E$6*Positions!$Q$6*Stress!$F$5+Positions!$E$6*Positions!$R$6*Stress!$G$5),(Positions!$E$6*Positions!$N$6*Stress!$C$6+Positions!$E$6*Positions!$O$6*Stress!$D$6+Positions!$E$6*Positions!$P$6*Stress!$E$6+Positions!$E$6*Positions!$Q$6*Stress!$F$6+Positions!$E$6*Positions!$R$6*Stress!$G$6),(Positions!$E$6*Positions!$N$6*Stress!$C$7+Positions!$E$6*Positions!$O$6*Stress!$D$7+Positions!$E$6*Positions!$P$6*Stress!$E$7+Positions!$E$6*Positions!$Q$6*Stress!$F$7+Positions!$E$6*Positions!$R$6*Stress!$G$7),(Positions!$E$6*Positions!$N$6*Stress!$C$8+Positions!$E$6*Positions!$O$6*Stress!$D$8+Positions!$E$6*Positions!$P$6*Stress!$E$8+Positions!$E$6*Positions!$Q$6*Stress!$F$8+Positions!$E$6*Positions!$R$6*Stress!$G$8),(Positions!$E$6*Positions!$N$6*Stress!$C$9+Positions!$E$6*Positions!$O$6*Stress!$D$9+Positions!$E$6*Positions!$P$6*Stress!$E$9+Positions!$E$6*Positions!$Q$6*Stress!$F$9+Positions!$E$6*Positions!$R$6*Stress!$G$9),(Positions!$E$6*Positions!$N$6*Stress!$C$10+Positions!$E$6*Positions!$O$6*Stress!$D$10+Positions!$E$6*Positions!$P$6*Stress!$E$10+Positions!$E$6*Positions!$Q$6*Stress!$F$10+Positions!$E$6*Positions!$R$6*Stress!$G$10)) | H6: =Liquidity!G6 | I6: =ABS(E6)+G6+H6 | J6: =IFERROR(I6/SUM($I$5:$I$16),0)
B7: =Positions!B7 | C7: =ABS(Positions!E7) | D7: ='VaR & ES'!$C$7*SQRT(MAX(0,((Positions!$E$7*Positions!$N$7)*(Positions!$E$7*Positions!$N$7)*Factors!$D$5*Factors!$D$5*Factors!$E$5+(Positions!$E$7*Positions!$N$7)*(Positions!$E$7*Positions!$O$7)*Factors!$D$5*Factors!$D$6*Factors!$F$5+(Positions!$E$7*Positions!$N$7)*(Positions!$E$7*Positions!$P$7)*Factors!$D$5*Factors!$D$7*Factors!$G$5+(Positions!$E$7*Positions!$N$7)*(Positions!$E$7*Positions!$Q$7)*Factors!$D$5*Factors!$D$8*Factors!$H$5+(Positions!$E$7*Positions!$N$7)*(Positions!$E$7*Positions!$R$7)*Factors!$D$5*Factors!$D$9*Factors!$I$5+(Positions!$E$7*Positions!$O$7)*(Positions!$E$7*Positions!$N$7)*Factors!$D$6*Factors!$D$5*Factors!$E$6+(Positions!$E$7*Positions!$O$7)*(Positions!$E$7*Positions!$O$7)*Factors!$D$6*Factors!$D$6*Factors!$F$6+(Positions!$E$7*Positions!$O$7)*(Positions!$E$7*Positions!$P$7)*Factors!$D$6*Factors!$D$7*Factors!$G$6+(Positions!$E$7*Positions!$O$7)*(Positions!$E$7*Positions!$Q$7)*Factors!$D$6*Factors!$D$8*Factors!$H$6+(Positions!$E$7*Positions!$O$7)*(Positions!$E$7*Positions!$R$7)*Factors!$D$6*Factors!$D$9*Factors!$I$6+(Positions!$E$7*Positions!$P$7)*(Positions!$E$7*Positions!$N$7)*Factors!$D$7*Factors!$D$5*Factors!$E$7+(Positions!$E$7*Positions!$P$7)*(Positions!$E$7*Positions!$O$7)*Factors!$D$7*Factors!$D$6*Factors!$F$7+(Positions!$E$7*Positions!$P$7)*(Positions!$E$7*Positions!$P$7)*Factors!$D$7*Factors!$D$7*Factors!$G$7+(Positions!$E$7*Positions!$P$7)*(Positions!$E$7*Positions!$Q$7)*Factors!$D$7*Factors!$D$8*Factors!$H$7+(Positions!$E$7*Positions!$P$7)*(Positions!$E$7*Positions!$R$7)*Factors!$D$7*Factors!$D$9*Factors!$I$7+(Positions!$E$7*Positions!$Q$7)*(Positions!$E$7*Positions!$N$7)*Factors!$D$8*Factors!$D$5*Factors!$E$8+(Positions!$E$7*Positions!$Q$7)*(Positions!$E$7*Positions!$O$7)*Factors!$D$8*Factors!$D$6*Factors!$F$8+(Positions!$E$7*Positions!$Q$7)*(Positions!$E$7*Positions!$P$7)*Factors!$D$8*Factors!$D$7*Factors!$G$8+(Positions!$E$7*Positions!$Q$7)*(Positions!$E$7*Positions!$Q$7)*Factors!$D$8*Factors!$D$8*Factors!$H$8+(Positions!$E$7*Positions!$Q$7)*(Positions!$E$7*Positions!$R$7)*Factors!$D$8*Factors!$D$9*Factors!$I$8+(Positions!$E$7*Positions!$R$7)*(Positions!$E$7*Positions!$N$7)*Factors!$D$9*Factors!$D$5*Factors!$E$9+(Positions!$E$7*Positions!$R$7)*(Positions!$E$7*Positions!$O$7)*Factors!$D$9*Factors!$D$6*Factors!$F$9+(Positions!$E$7*Positions!$R$7)*(Positions!$E$7*Positions!$P$7)*Factors!$D$9*Factors!$D$7*Factors!$G$9+(Positions!$E$7*Positions!$R$7)*(Positions!$E$7*Positions!$Q$7)*Factors!$D$9*Factors!$D$8*Factors!$H$9+(Positions!$E$7*Positions!$R$7)*(Positions!$E$7*Positions!$R$7)*Factors!$D$9*Factors!$D$9*Factors!$I$9)/Assumptions!$E$6)) | E7: =IFERROR('VaR & ES'!$C$7*((Positions!$E$7*Positions!$N$7)*Factors!$D$5*Factors!$C$5*Factors!$D$5*Factors!$E$5+(Positions!$E$7*Positions!$N$7)*Factors!$D$5*Factors!$C$6*Factors!$D$6*Factors!$F$5+(Positions!$E$7*Positions!$N$7)*Factors!$D$5*Factors!$C$7*Factors!$D$7*Factors!$G$5+(Positions!$E$7*Positions!$N$7)*Factors!$D$5*Factors!$C$8*Factors!$D$8*Factors!$H$5+(Positions!$E$7*Positions!$N$7)*Factors!$D$5*Factors!$C$9*Factors!$D$9*Factors!$I$5+(Positions!$E$7*Positions!$O$7)*Factors!$D$6*Factors!$C$5*Factors!$D$5*Factors!$E$6+(Positions!$E$7*Positions!$O$7)*Factors!$D$6*Factors!$C$6*Factors!$D$6*Factors!$F$6+(Positions!$E$7*Positions!$O$7)*Factors!$D$6*Factors!$C$7*Factors!$D$7*Factors!$G$6+(Positions!$E$7*Positions!$O$7)*Factors!$D$6*Factors!$C$8*Factors!$D$8*Factors!$H$6+(Positions!$E$7*Positions!$O$7)*Factors!$D$6*Factors!$C$9*Factors!$D$9*Factors!$I$6+(Positions!$E$7*Positions!$P$7)*Factors!$D$7*Factors!$C$5*Factors!$D$5*Factors!$E$7+(Positions!$E$7*Positions!$P$7)*Factors!$D$7*Factors!$C$6*Factors!$D$6*Factors!$F$7+(Positions!$E$7*Positions!$P$7)*Factors!$D$7*Factors!$C$7*Factors!$D$7*Factors!$G$7+(Positions!$E$7*Positions!$P$7)*Factors!$D$7*Factors!$C$8*Factors!$D$8*Factors!$H$7+(Positions!$E$7*Positions!$P$7)*Factors!$D$7*Factors!$C$9*Factors!$D$9*Factors!$I$7+(Positions!$E$7*Positions!$Q$7)*Factors!$D$8*Factors!$C$5*Factors!$D$5*Factors!$E$8+(Positions!$E$7*Positions!$Q$7)*Factors!$D$8*Factors!$C$6*Factors!$D$6*Factors!$F$8+(Positions!$E$7*Positions!$Q$7)*Factors!$D$8*Factors!$C$7*Factors!$D$7*Factors!$G$8+(Positions!$E$7*Positions!$Q$7)*Factors!$D$8*Factors!$C$8*Factors!$D$8*Factors!$H$8+(Positions!$E$7*Positions!$Q$7)*Factors!$D$8*Factors!$C$9*Factors!$D$9*Factors!$I$8+(Positions!$E$7*Positions!$R$7)*Factors!$D$9*Factors!$C$5*Factors!$D$5*Factors!$E$9+(Positions!$E$7*Positions!$R$7)*Factors!$D$9*Factors!$C$6*Factors!$D$6*Factors!$F$9+(Positions!$E$7*Positions!$R$7)*Factors!$D$9*Factors!$C$7*Factors!$D$7*Factors!$G$9+(Positions!$E$7*Positions!$R$7)*Factors!$D$9*Factors!$C$8*Factors!$D$8*Factors!$H$9+(Positions!$E$7*Positions!$R$7)*Factors!$D$9*Factors!$C$9*Factors!$D$9*Factors!$I$9)/(Factors!$C$13*SQRT(Assumptions!$E$6)),0) | F7: =IFERROR(E7/'VaR & ES'!$C$8,0) | G7: =-MIN((Positions!$E$7*Positions!$N$7*Stress!$C$5+Positions!$E$7*Positions!$O$7*Stress!$D$5+Positions!$E$7*Positions!$P$7*Stress!$E$5+Positions!$E$7*Positions!$Q$7*Stress!$F$5+Positions!$E$7*Positions!$R$7*Stress!$G$5),(Positions!$E$7*Positions!$N$7*Stress!$C$6+Positions!$E$7*Positions!$O$7*Stress!$D$6+Positions!$E$7*Positions!$P$7*Stress!$E$6+Positions!$E$7*Positions!$Q$7*Stress!$F$6+Positions!$E$7*Positions!$R$7*Stress!$G$6),(Positions!$E$7*Positions!$N$7*Stress!$C$7+Positions!$E$7*Positions!$O$7*Stress!$D$7+Positions!$E$7*Positions!$P$7*Stress!$E$7+Positions!$E$7*Positions!$Q$7*Stress!$F$7+Positions!$E$7*Positions!$R$7*Stress!$G$7),(Positions!$E$7*Positions!$N$7*Stress!$C$8+Positions!$E$7*Positions!$O$7*Stress!$D$8+Positions!$E$7*Positions!$P$7*Stress!$E$8+Positions!$E$7*Positions!$Q$7*Stress!$F$8+Positions!$E$7*Positions!$R$7*Stress!$G$8),(Positions!$E$7*Positions!$N$7*Stress!$C$9+Positions!$E$7*Positions!$O$7*Stress!$D$9+Positions!$E$7*Positions!$P$7*Stress!$E$9+Positions!$E$7*Positions!$Q$7*Stress!$F$9+Positions!$E$7*Positions!$R$7*Stress!$G$9),(Positions!$E$7*Positions!$N$7*Stress!$C$10+Positions!$E$7*Positions!$O$7*Stress!$D$10+Positions!$E$7*Positions!$P$7*Stress!$E$10+Positions!$E$7*Positions!$Q$7*Stress!$F$10+Positions!$E$7*Positions!$R$7*Stress!$G$10)) | H7: =Liquidity!G7 | I7: =ABS(E7)+G7+H7 | J7: =IFERROR(I7/SUM($I$5:$I$16),0)
B8: =Positions!B8 | C8: =ABS(Positions!E8) | D8: ='VaR & ES'!$C$7*SQRT(MAX(0,((Positions!$E$8*Positions!$N$8)*(Positions!$E$8*Positions!$N$8)*Factors!$D$5*Factors!$D$5*Factors!$E$5+(Positions!$E$8*Positions!$N$8)*(Positions!$E$8*Positions!$O$8)*Factors!$D$5*Factors!$D$6*Factors!$F$5+(Positions!$E$8*Positions!$N$8)*(Positions!$E$8*Positions!$P$8)*Factors!$D$5*Factors!$D$7*Factors!$G$5+(Positions!$E$8*Positions!$N$8)*(Positions!$E$8*Positions!$Q$8)*Factors!$D$5*Factors!$D$8*Factors!$H$5+(Positions!$E$8*Positions!$N$8)*(Positions!$E$8*Positions!$R$8)*Factors!$D$5*Factors!$D$9*Factors!$I$5+(Positions!$E$8*Positions!$O$8)*(Positions!$E$8*Positions!$N$8)*Factors!$D$6*Factors!$D$5*Factors!$E$6+(Positions!$E$8*Positions!$O$8)*(Positions!$E$8*Positions!$O$8)*Factors!$D$6*Factors!$D$6*Factors!$F$6+(Positions!$E$8*Positions!$O$8)*(Positions!$E$8*Positions!$P$8)*Factors!$D$6*Factors!$D$7*Factors!$G$6+(Positions!$E$8*Positions!$O$8)*(Positions!$E$8*Positions!$Q$8)*Factors!$D$6*Factors!$D$8*Factors!$H$6+(Positions!$E$8*Positions!$O$8)*(Positions!$E$8*Positions!$R$8)*Factors!$D$6*Factors!$D$9*Factors!$I$6+(Positions!$E$8*Positions!$P$8)*(Positions!$E$8*Positions!$N$8)*Factors!$D$7*Factors!$D$5*Factors!$E$7+(Positions!$E$8*Positions!$P$8)*(Positions!$E$8*Positions!$O$8)*Factors!$D$7*Factors!$D$6*Factors!$F$7+(Positions!$E$8*Positions!$P$8)*(Positions!$E$8*Positions!$P$8)*Factors!$D$7*Factors!$D$7*Factors!$G$7+(Positions!$E$8*Positions!$P$8)*(Positions!$E$8*Positions!$Q$8)*Factors!$D$7*Factors!$D$8*Factors!$H$7+(Positions!$E$8*Positions!$P$8)*(Positions!$E$8*Positions!$R$8)*Factors!$D$7*Factors!$D$9*Factors!$I$7+(Positions!$E$8*Positions!$Q$8)*(Positions!$E$8*Positions!$N$8)*Factors!$D$8*Factors!$D$5*Factors!$E$8+(Positions!$E$8*Positions!$Q$8)*(Positions!$E$8*Positions!$O$8)*Factors!$D$8*Factors!$D$6*Factors!$F$8+(Positions!$E$8*Positions!$Q$8)*(Positions!$E$8*Positions!$P$8)*Factors!$D$8*Factors!$D$7*Factors!$G$8+(Positions!$E$8*Positions!$Q$8)*(Positions!$E$8*Positions!$Q$8)*Factors!$D$8*Factors!$D$8*Factors!$H$8+(Positions!$E$8*Positions!$Q$8)*(Positions!$E$8*Positions!$R$8)*Factors!$D$8*Factors!$D$9*Factors!$I$8+(Positions!$E$8*Positions!$R$8)*(Positions!$E$8*Positions!$N$8)*Factors!$D$9*Factors!$D$5*Factors!$E$9+(Positions!$E$8*Positions!$R$8)*(Positions!$E$8*Positions!$O$8)*Factors!$D$9*Factors!$D$6*Factors!$F$9+(Positions!$E$8*Positions!$R$8)*(Positions!$E$8*Positions!$P$8)*Factors!$D$9*Factors!$D$7*Factors!$G$9+(Positions!$E$8*Positions!$R$8)*(Positions!$E$8*Positions!$Q$8)*Factors!$D$9*Factors!$D$8*Factors!$H$9+(Positions!$E$8*Positions!$R$8)*(Positions!$E$8*Positions!$R$8)*Factors!$D$9*Factors!$D$9*Factors!$I$9)/Assumptions!$E$6)) | E8: =IFERROR('VaR & ES'!$C$7*((Positions!$E$8*Positions!$N$8)*Factors!$D$5*Factors!$C$5*Factors!$D$5*Factors!$E$5+(Positions!$E$8*Positions!$N$8)*Factors!$D$5*Factors!$C$6*Factors!$D$6*Factors!$F$5+(Positions!$E$8*Positions!$N$8)*Factors!$D$5*Factors!$C$7*Factors!$D$7*Factors!$G$5+(Positions!$E$8*Positions!$N$8)*Factors!$D$5*Factors!$C$8*Factors!$D$8*Factors!$H$5+(Positions!$E$8*Positions!$N$8)*Factors!$D$5*Factors!$C$9*Factors!$D$9*Factors!$I$5+(Positions!$E$8*Positions!$O$8)*Factors!$D$6*Factors!$C$5*Factors!$D$5*Factors!$E$6+(Positions!$E$8*Positions!$O$8)*Factors!$D$6*Factors!$C$6*Factors!$D$6*Factors!$F$6+(Positions!$E$8*Positions!$O$8)*Factors!$D$6*Factors!$C$7*Factors!$D$7*Factors!$G$6+(Positions!$E$8*Positions!$O$8)*Factors!$D$6*Factors!$C$8*Factors!$D$8*Factors!$H$6+(Positions!$E$8*Positions!$O$8)*Factors!$D$6*Factors!$C$9*Factors!$D$9*Factors!$I$6+(Positions!$E$8*Positions!$P$8)*Factors!$D$7*Factors!$C$5*Factors!$D$5*Factors!$E$7+(Positions!$E$8*Positions!$P$8)*Factors!$D$7*Factors!$C$6*Factors!$D$6*Factors!$F$7+(Positions!$E$8*Positions!$P$8)*Factors!$D$7*Factors!$C$7*Factors!$D$7*Factors!$G$7+(Positions!$E$8*Positions!$P$8)*Factors!$D$7*Factors!$C$8*Factors!$D$8*Factors!$H$7+(Positions!$E$8*Positions!$P$8)*Factors!$D$7*Factors!$C$9*Factors!$D$9*Factors!$I$7+(Positions!$E$8*Positions!$Q$8)*Factors!$D$8*Factors!$C$5*Factors!$D$5*Factors!$E$8+(Positions!$E$8*Positions!$Q$8)*Factors!$D$8*Factors!$C$6*Factors!$D$6*Factors!$F$8+(Positions!$E$8*Positions!$Q$8)*Factors!$D$8*Factors!$C$7*Factors!$D$7*Factors!$G$8+(Positions!$E$8*Positions!$Q$8)*Factors!$D$8*Factors!$C$8*Factors!$D$8*Factors!$H$8+(Positions!$E$8*Positions!$Q$8)*Factors!$D$8*Factors!$C$9*Factors!$D$9*Factors!$I$8+(Positions!$E$8*Positions!$R$8)*Factors!$D$9*Factors!$C$5*Factors!$D$5*Factors!$E$9+(Positions!$E$8*Positions!$R$8)*Factors!$D$9*Factors!$C$6*Factors!$D$6*Factors!$F$9+(Positions!$E$8*Positions!$R$8)*Factors!$D$9*Factors!$C$7*Factors!$D$7*Factors!$G$9+(Positions!$E$8*Positions!$R$8)*Factors!$D$9*Factors!$C$8*Factors!$D$8*Factors!$H$9+(Positions!$E$8*Positions!$R$8)*Factors!$D$9*Factors!$C$9*Factors!$D$9*Factors!$I$9)/(Factors!$C$13*SQRT(Assumptions!$E$6)),0) | F8: =IFERROR(E8/'VaR & ES'!$C$8,0) | G8: =-MIN((Positions!$E$8*Positions!$N$8*Stress!$C$5+Positions!$E$8*Positions!$O$8*Stress!$D$5+Positions!$E$8*Positions!$P$8*Stress!$E$5+Positions!$E$8*Positions!$Q$8*Stress!$F$5+Positions!$E$8*Positions!$R$8*Stress!$G$5),(Positions!$E$8*Positions!$N$8*Stress!$C$6+Positions!$E$8*Positions!$O$8*Stress!$D$6+Positions!$E$8*Positions!$P$8*Stress!$E$6+Positions!$E$8*Positions!$Q$8*Stress!$F$6+Positions!$E$8*Positions!$R$8*Stress!$G$6),(Positions!$E$8*Positions!$N$8*Stress!$C$7+Positions!$E$8*Positions!$O$8*Stress!$D$7+Positions!$E$8*Positions!$P$8*Stress!$E$7+Positions!$E$8*Positions!$Q$8*Stress!$F$7+Positions!$E$8*Positions!$R$8*Stress!$G$7),(Positions!$E$8*Positions!$N$8*Stress!$C$8+Positions!$E$8*Positions!$O$8*Stress!$D$8+Positions!$E$8*Positions!$P$8*Stress!$E$8+Positions!$E$8*Positions!$Q$8*Stress!$F$8+Positions!$E$8*Positions!$R$8*Stress!$G$8),(Positions!$E$8*Positions!$N$8*Stress!$C$9+Positions!$E$8*Positions!$O$8*Stress!$D$9+Positions!$E$8*Positions!$P$8*Stress!$E$9+Positions!$E$8*Positions!$Q$8*Stress!$F$9+Positions!$E$8*Positions!$R$8*Stress!$G$9),(Positions!$E$8*Positions!$N$8*Stress!$C$10+Positions!$E$8*Positions!$O$8*Stress!$D$10+Positions!$E$8*Positions!$P$8*Stress!$E$10+Positions!$E$8*Positions!$Q$8*Stress!$F$10+Positions!$E$8*Positions!$R$8*Stress!$G$10)) | H8: =Liquidity!G8 | I8: =ABS(E8)+G8+H8 | J8: =IFERROR(I8/SUM($I$5:$I$16),0)
B9: =Positions!B9 | C9: =ABS(Positions!E9) | D9: ='VaR & ES'!$C$7*SQRT(MAX(0,((Positions!$E$9*Positions!$N$9)*(Positions!$E$9*Positions!$N$9)*Factors!$D$5*Factors!$D$5*Factors!$E$5+(Positions!$E$9*Positions!$N$9)*(Positions!$E$9*Positions!$O$9)*Factors!$D$5*Factors!$D$6*Factors!$F$5+(Positions!$E$9*Positions!$N$9)*(Positions!$E$9*Positions!$P$9)*Factors!$D$5*Factors!$D$7*Factors!$G$5+(Positions!$E$9*Positions!$N$9)*(Positions!$E$9*Positions!$Q$9)*Factors!$D$5*Factors!$D$8*Factors!$H$5+(Positions!$E$9*Positions!$N$9)*(Positions!$E$9*Positions!$R$9)*Factors!$D$5*Factors!$D$9*Factors!$I$5+(Positions!$E$9*Positions!$O$9)*(Positions!$E$9*Positions!$N$9)*Factors!$D$6*Factors!$D$5*Factors!$E$6+(Positions!$E$9*Positions!$O$9)*(Positions!$E$9*Positions!$O$9)*Factors!$D$6*Factors!$D$6*Factors!$F$6+(Positions!$E$9*Positions!$O$9)*(Positions!$E$9*Positions!$P$9)*Factors!$D$6*Factors!$D$7*Factors!$G$6+(Positions!$E$9*Positions!$O$9)*(Positions!$E$9*Positions!$Q$9)*Factors!$D$6*Factors!$D$8*Factors!$H$6+(Positions!$E$9*Positions!$O$9)*(Positions!$E$9*Positions!$R$9)*Factors!$D$6*Factors!$D$9*Factors!$I$6+(Positions!$E$9*Positions!$P$9)*(Positions!$E$9*Positions!$N$9)*Factors!$D$7*Factors!$D$5*Factors!$E$7+(Positions!$E$9*Positions!$P$9)*(Positions!$E$9*Positions!$O$9)*Factors!$D$7*Factors!$D$6*Factors!$F$7+(Positions!$E$9*Positions!$P$9)*(Positions!$E$9*Positions!$P$9)*Factors!$D$7*Factors!$D$7*Factors!$G$7+(Positions!$E$9*Positions!$P$9)*(Positions!$E$9*Positions!$Q$9)*Factors!$D$7*Factors!$D$8*Factors!$H$7+(Positions!$E$9*Positions!$P$9)*(Positions!$E$9*Positions!$R$9)*Factors!$D$7*Factors!$D$9*Factors!$I$7+(Positions!$E$9*Positions!$Q$9)*(Positions!$E$9*Positions!$N$9)*Factors!$D$8*Factors!$D$5*Factors!$E$8+(Positions!$E$9*Positions!$Q$9)*(Positions!$E$9*Positions!$O$9)*Factors!$D$8*Factors!$D$6*Factors!$F$8+(Positions!$E$9*Positions!$Q$9)*(Positions!$E$9*Positions!$P$9)*Factors!$D$8*Factors!$D$7*Factors!$G$8+(Positions!$E$9*Positions!$Q$9)*(Positions!$E$9*Positions!$Q$9)*Factors!$D$8*Factors!$D$8*Factors!$H$8+(Positions!$E$9*Positions!$Q$9)*(Positions!$E$9*Positions!$R$9)*Factors!$D$8*Factors!$D$9*Factors!$I$8+(Positions!$E$9*Positions!$R$9)*(Positions!$E$9*Positions!$N$9)*Factors!$D$9*Factors!$D$5*Factors!$E$9+(Positions!$E$9*Positions!$R$9)*(Positions!$E$9*Positions!$O$9)*Factors!$D$9*Factors!$D$6*Factors!$F$9+(Positions!$E$9*Positions!$R$9)*(Positions!$E$9*Positions!$P$9)*Factors!$D$9*Factors!$D$7*Factors!$G$9+(Positions!$E$9*Positions!$R$9)*(Positions!$E$9*Positions!$Q$9)*Factors!$D$9*Factors!$D$8*Factors!$H$9+(Positions!$E$9*Positions!$R$9)*(Positions!$E$9*Positions!$R$9)*Factors!$D$9*Factors!$D$9*Factors!$I$9)/Assumptions!$E$6)) | E9: =IFERROR('VaR & ES'!$C$7*((Positions!$E$9*Positions!$N$9)*Factors!$D$5*Factors!$C$5*Factors!$D$5*Factors!$E$5+(Positions!$E$9*Positions!$N$9)*Factors!$D$5*Factors!$C$6*Factors!$D$6*Factors!$F$5+(Positions!$E$9*Positions!$N$9)*Factors!$D$5*Factors!$C$7*Factors!$D$7*Factors!$G$5+(Positions!$E$9*Positions!$N$9)*Factors!$D$5*Factors!$C$8*Factors!$D$8*Factors!$H$5+(Positions!$E$9*Positions!$N$9)*Factors!$D$5*Factors!$C$9*Factors!$D$9*Factors!$I$5+(Positions!$E$9*Positions!$O$9)*Factors!$D$6*Factors!$C$5*Factors!$D$5*Factors!$E$6+(Positions!$E$9*Positions!$O$9)*Factors!$D$6*Factors!$C$6*Factors!$D$6*Factors!$F$6+(Positions!$E$9*Positions!$O$9)*Factors!$D$6*Factors!$C$7*Factors!$D$7*Factors!$G$6+(Positions!$E$9*Positions!$O$9)*Factors!$D$6*Factors!$C$8*Factors!$D$8*Factors!$H$6+(Positions!$E$9*Positions!$O$9)*Factors!$D$6*Factors!$C$9*Factors!$D$9*Factors!$I$6+(Positions!$E$9*Positions!$P$9)*Factors!$D$7*Factors!$C$5*Factors!$D$5*Factors!$E$7+(Positions!$E$9*Positions!$P$9)*Factors!$D$7*Factors!$C$6*Factors!$D$6*Factors!$F$7+(Positions!$E$9*Positions!$P$9)*Factors!$D$7*Factors!$C$7*Factors!$D$7*Factors!$G$7+(Positions!$E$9*Positions!$P$9)*Factors!$D$7*Factors!$C$8*Factors!$D$8*Factors!$H$7+(Positions!$E$9*Positions!$P$9)*Factors!$D$7*Factors!$C$9*Factors!$D$9*Factors!$I$7+(Positions!$E$9*Positions!$Q$9)*Factors!$D$8*Factors!$C$5*Factors!$D$5*Factors!$E$8+(Positions!$E$9*Positions!$Q$9)*Factors!$D$8*Factors!$C$6*Factors!$D$6*Factors!$F$8+(Positions!$E$9*Positions!$Q$9)*Factors!$D$8*Factors!$C$7*Factors!$D$7*Factors!$G$8+(Positions!$E$9*Positions!$Q$9)*Factors!$D$8*Factors!$C$8*Factors!$D$8*Factors!$H$8+(Positions!$E$9*Positions!$Q$9)*Factors!$D$8*Factors!$C$9*Factors!$D$9*Factors!$I$8+(Positions!$E$9*Positions!$R$9)*Factors!$D$9*Factors!$C$5*Factors!$D$5*Factors!$E$9+(Positions!$E$9*Positions!$R$9)*Factors!$D$9*Factors!$C$6*Factors!$D$6*Factors!$F$9+(Positions!$E$9*Positions!$R$9)*Factors!$D$9*Factors!$C$7*Factors!$D$7*Factors!$G$9+(Positions!$E$9*Positions!$R$9)*Factors!$D$9*Factors!$C$8*Factors!$D$8*Factors!$H$9+(Positions!$E$9*Positions!$R$9)*Factors!$D$9*Factors!$C$9*Factors!$D$9*Factors!$I$9)/(Factors!$C$13*SQRT(Assumptions!$E$6)),0) | F9: =IFERROR(E9/'VaR & ES'!$C$8,0) | G9: =-MIN((Positions!$E$9*Positions!$N$9*Stress!$C$5+Positions!$E$9*Positions!$O$9*Stress!$D$5+Positions!$E$9*Positions!$P$9*Stress!$E$5+Positions!$E$9*Positions!$Q$9*Stress!$F$5+Positions!$E$9*Positions!$R$9*Stress!$G$5),(Positions!$E$9*Positions!$N$9*Stress!$C$6+Positions!$E$9*Positions!$O$9*Stress!$D$6+Positions!$E$9*Positions!$P$9*Stress!$E$6+Positions!$E$9*Positions!$Q$9*Stress!$F$6+Positions!$E$9*Positions!$R$9*Stress!$G$6),(Positions!$E$9*Positions!$N$9*Stress!$C$7+Positions!$E$9*Positions!$O$9*Stress!$D$7+Positions!$E$9*Positions!$P$9*Stress!$E$7+Positions!$E$9*Positions!$Q$9*Stress!$F$7+Positions!$E$9*Positions!$R$9*Stress!$G$7),(Positions!$E$9*Positions!$N$9*Stress!$C$8+Positions!$E$9*Positions!$O$9*Stress!$D$8+Positions!$E$9*Positions!$P$9*Stress!$E$8+Positions!$E$9*Positions!$Q$9*Stress!$F$8+Positions!$E$9*Positions!$R$9*Stress!$G$8),(Positions!$E$9*Positions!$N$9*Stress!$C$9+Positions!$E$9*Positions!$O$9*Stress!$D$9+Positions!$E$9*Positions!$P$9*Stress!$E$9+Positions!$E$9*Positions!$Q$9*Stress!$F$9+Positions!$E$9*Positions!$R$9*Stress!$G$9),(Positions!$E$9*Positions!$N$9*Stress!$C$10+Positions!$E$9*Positions!$O$9*Stress!$D$10+Positions!$E$9*Positions!$P$9*Stress!$E$10+Positions!$E$9*Positions!$Q$9*Stress!$F$10+Positions!$E$9*Positions!$R$9*Stress!$G$10)) | H9: =Liquidity!G9 | I9: =ABS(E9)+G9+H9 | J9: =IFERROR(I9/SUM($I$5:$I$16),0)
B10: =Positions!B10 | C10: =ABS(Positions!E10) | D10: ='VaR & ES'!$C$7*SQRT(MAX(0,((Positions!$E$10*Positions!$N$10)*(Positions!$E$10*Positions!$N$10)*Factors!$D$5*Factors!$D$5*Factors!$E$5+(Positions!$E$10*Positions!$N$10)*(Positions!$E$10*Positions!$O$10)*Factors!$D$5*Factors!$D$6*Factors!$F$5+(Positions!$E$10*Positions!$N$10)*(Positions!$E$10*Positions!$P$10)*Factors!$D$5*Factors!$D$7*Factors!$G$5+(Positions!$E$10*Positions!$N$10)*(Positions!$E$10*Positions!$Q$10)*Factors!$D$5*Factors!$D$8*Factors!$H$5+(Positions!$E$10*Positions!$N$10)*(Positions!$E$10*Positions!$R$10)*Factors!$D$5*Factors!$D$9*Factors!$I$5+(Positions!$E$10*Positions!$O$10)*(Positions!$E$10*Positions!$N$10)*Factors!$D$6*Factors!$D$5*Factors!$E$6+(Positions!$E$10*Positions!$O$10)*(Positions!$E$10*Positions!$O$10)*Factors!$D$6*Factors!$D$6*Factors!$F$6+(Positions!$E$10*Positions!$O$10)*(Positions!$E$10*Positions!$P$10)*Factors!$D$6*Factors!$D$7*Factors!$G$6+(Positions!$E$10*Positions!$O$10)*(Positions!$E$10*Positions!$Q$10)*Factors!$D$6*Factors!$D$8*Factors!$H$6+(Positions!$E$10*Positions!$O$10)*(Positions!$E$10*Positions!$R$10)*Factors!$D$6*Factors!$D$9*Factors!$I$6+(Positions!$E$10*Positions!$P$10)*(Positions!$E$10*Positions!$N$10)*Factors!$D$7*Factors!$D$5*Factors!$E$7+(Positions!$E$10*Positions!$P$10)*(Positions!$E$10*Positions!$O$10)*Factors!$D$7*Factors!$D$6*Factors!$F$7+(Positions!$E$10*Positions!$P$10)*(Positions!$E$10*Positions!$P$10)*Factors!$D$7*Factors!$D$7*Factors!$G$7+(Positions!$E$10*Positions!$P$10)*(Positions!$E$10*Positions!$Q$10)*Factors!$D$7*Factors!$D$8*Factors!$H$7+(Positions!$E$10*Positions!$P$10)*(Positions!$E$10*Positions!$R$10)*Factors!$D$7*Factors!$D$9*Factors!$I$7+(Positions!$E$10*Positions!$Q$10)*(Positions!$E$10*Positions!$N$10)*Factors!$D$8*Factors!$D$5*Factors!$E$8+(Positions!$E$10*Positions!$Q$10)*(Positions!$E$10*Positions!$O$10)*Factors!$D$8*Factors!$D$6*Factors!$F$8+(Positions!$E$10*Positions!$Q$10)*(Positions!$E$10*Positions!$P$10)*Factors!$D$8*Factors!$D$7*Factors!$G$8+(Positions!$E$10*Positions!$Q$10)*(Positions!$E$10*Positions!$Q$10)*Factors!$D$8*Factors!$D$8*Factors!$H$8+(Positions!$E$10*Positions!$Q$10)*(Positions!$E$10*Positions!$R$10)*Factors!$D$8*Factors!$D$9*Factors!$I$8+(Positions!$E$10*Positions!$R$10)*(Positions!$E$10*Positions!$N$10)*Factors!$D$9*Factors!$D$5*Factors!$E$9+(Positions!$E$10*Positions!$R$10)*(Positions!$E$10*Positions!$O$10)*Factors!$D$9*Factors!$D$6*Factors!$F$9+(Positions!$E$10*Positions!$R$10)*(Positions!$E$10*Positions!$P$10)*Factors!$D$9*Factors!$D$7*Factors!$G$9+(Positions!$E$10*Positions!$R$10)*(Positions!$E$10*Positions!$Q$10)*Factors!$D$9*Factors!$D$8*Factors!$H$9+(Positions!$E$10*Positions!$R$10)*(Positions!$E$10*Positions!$R$10)*Factors!$D$9*Factors!$D$9*Factors!$I$9)/Assumptions!$E$6)) | E10: =IFERROR('VaR & ES'!$C$7*((Positions!$E$10*Positions!$N$10)*Factors!$D$5*Factors!$C$5*Factors!$D$5*Factors!$E$5+(Positions!$E$10*Positions!$N$10)*Factors!$D$5*Factors!$C$6*Factors!$D$6*Factors!$F$5+(Positions!$E$10*Positions!$N$10)*Factors!$D$5*Factors!$C$7*Factors!$D$7*Factors!$G$5+(Positions!$E$10*Positions!$N$10)*Factors!$D$5*Factors!$C$8*Factors!$D$8*Factors!$H$5+(Positions!$E$10*Positions!$N$10)*Factors!$D$5*Factors!$C$9*Factors!$D$9*Factors!$I$5+(Positions!$E$10*Positions!$O$10)*Factors!$D$6*Factors!$C$5*Factors!$D$5*Factors!$E$6+(Positions!$E$10*Positions!$O$10)*Factors!$D$6*Factors!$C$6*Factors!$D$6*Factors!$F$6+(Positions!$E$10*Positions!$O$10)*Factors!$D$6*Factors!$C$7*Factors!$D$7*Factors!$G$6+(Positions!$E$10*Positions!$O$10)*Factors!$D$6*Factors!$C$8*Factors!$D$8*Factors!$H$6+(Positions!$E$10*Positions!$O$10)*Factors!$D$6*Factors!$C$9*Factors!$D$9*Factors!$I$6+(Positions!$E$10*Positions!$P$10)*Factors!$D$7*Factors!$C$5*Factors!$D$5*Factors!$E$7+(Positions!$E$10*Positions!$P$10)*Factors!$D$7*Factors!$C$6*Factors!$D$6*Factors!$F$7+(Positions!$E$10*Positions!$P$10)*Factors!$D$7*Factors!$C$7*Factors!$D$7*Factors!$G$7+(Positions!$E$10*Positions!$P$10)*Factors!$D$7*Factors!$C$8*Factors!$D$8*Factors!$H$7+(Positions!$E$10*Positions!$P$10)*Factors!$D$7*Factors!$C$9*Factors!$D$9*Factors!$I$7+(Positions!$E$10*Positions!$Q$10)*Factors!$D$8*Factors!$C$5*Factors!$D$5*Factors!$E$8+(Positions!$E$10*Positions!$Q$10)*Factors!$D$8*Factors!$C$6*Factors!$D$6*Factors!$F$8+(Positions!$E$10*Positions!$Q$10)*Factors!$D$8*Factors!$C$7*Factors!$D$7*Factors!$G$8+(Positions!$E$10*Positions!$Q$10)*Factors!$D$8*Factors!$C$8*Factors!$D$8*Factors!$H$8+(Positions!$E$10*Positions!$Q$10)*Factors!$D$8*Factors!$C$9*Factors!$D$9*Factors!$I$8+(Positions!$E$10*Positions!$R$10)*Factors!$D$9*Factors!$C$5*Factors!$D$5*Factors!$E$9+(Positions!$E$10*Positions!$R$10)*Factors!$D$9*Factors!$C$6*Factors!$D$6*Factors!$F$9+(Positions!$E$10*Positions!$R$10)*Factors!$D$9*Factors!$C$7*Factors!$D$7*Factors!$G$9+(Positions!$E$10*Positions!$R$10)*Factors!$D$9*Factors!$C$8*Factors!$D$8*Factors!$H$9+(Positions!$E$10*Positions!$R$10)*Factors!$D$9*Factors!$C$9*Factors!$D$9*Factors!$I$9)/(Factors!$C$13*SQRT(Assumptions!$E$6)),0) | F10: =IFERROR(E10/'VaR & ES'!$C$8,0) | G10: =-MIN((Positions!$E$10*Positions!$N$10*Stress!$C$5+Positions!$E$10*Positions!$O$10*Stress!$D$5+Positions!$E$10*Positions!$P$10*Stress!$E$5+Positions!$E$10*Positions!$Q$10*Stress!$F$5+Positions!$E$10*Positions!$R$10*Stress!$G$5),(Positions!$E$10*Positions!$N$10*Stress!$C$6+Positions!$E$10*Positions!$O$10*Stress!$D$6+Positions!$E$10*Positions!$P$10*Stress!$E$6+Positions!$E$10*Positions!$Q$10*Stress!$F$6+Positions!$E$10*Positions!$R$10*Stress!$G$6),(Positions!$E$10*Positions!$N$10*Stress!$C$7+Positions!$E$10*Positions!$O$10*Stress!$D$7+Positions!$E$10*Positions!$P$10*Stress!$E$7+Positions!$E$10*Positions!$Q$10*Stress!$F$7+Positions!$E$10*Positions!$R$10*Stress!$G$7),(Positions!$E$10*Positions!$N$10*Stress!$C$8+Positions!$E$10*Positions!$O$10*Stress!$D$8+Positions!$E$10*Positions!$P$10*Stress!$E$8+Positions!$E$10*Positions!$Q$10*Stress!$F$8+Positions!$E$10*Positions!$R$10*Stress!$G$8),(Positions!$E$10*Positions!$N$10*Stress!$C$9+Positions!$E$10*Positions!$O$10*Stress!$D$9+Positions!$E$10*Positions!$P$10*Stress!$E$9+Positions!$E$10*Positions!$Q$10*Stress!$F$9+Positions!$E$10*Positions!$R$10*Stress!$G$9),(Positions!$E$10*Positions!$N$10*Stress!$C$10+Positions!$E$10*Positions!$O$10*Stress!$D$10+Positions!$E$10*Positions!$P$10*Stress!$E$10+Positions!$E$10*Positions!$Q$10*Stress!$F$10+Positions!$E$10*Positions!$R$10*Stress!$G$10)) | H10: =Liquidity!G10 | I10: =ABS(E10)+G10+H10 | J10: =IFERROR(I10/SUM($I$5:$I$16),0)
B11: =Positions!B11 | C11: =ABS(Positions!E11) | D11: ='VaR & ES'!$C$7*SQRT(MAX(0,((Positions!$E$11*Positions!$N$11)*(Positions!$E$11*Positions!$N$11)*Factors!$D$5*Factors!$D$5*Factors!$E$5+(Positions!$E$11*Positions!$N$11)*(Positions!$E$11*Positions!$O$11)*Factors!$D$5*Factors!$D$6*Factors!$F$5+(Positions!$E$11*Positions!$N$11)*(Positions!$E$11*Positions!$P$11)*Factors!$D$5*Factors!$D$7*Factors!$G$5+(Positions!$E$11*Positions!$N$11)*(Positions!$E$11*Positions!$Q$11)*Factors!$D$5*Factors!$D$8*Factors!$H$5+(Positions!$E$11*Positions!$N$11)*(Positions!$E$11*Positions!$R$11)*Factors!$D$5*Factors!$D$9*Factors!$I$5+(Positions!$E$11*Positions!$O$11)*(Positions!$E$11*Positions!$N$11)*Factors!$D$6*Factors!$D$5*Factors!$E$6+(Positions!$E$11*Positions!$O$11)*(Positions!$E$11*Positions!$O$11)*Factors!$D$6*Factors!$D$6*Factors!$F$6+(Positions!$E$11*Positions!$O$11)*(Positions!$E$11*Positions!$P$11)*Factors!$D$6*Factors!$D$7*Factors!$G$6+(Positions!$E$11*Positions!$O$11)*(Positions!$E$11*Positions!$Q$11)*Factors!$D$6*Factors!$D$8*Factors!$H$6+(Positions!$E$11*Positions!$O$11)*(Positions!$E$11*Positions!$R$11)*Factors!$D$6*Factors!$D$9*Factors!$I$6+(Positions!$E$11*Positions!$P$11)*(Positions!$E$11*Positions!$N$11)*Factors!$D$7*Factors!$D$5*Factors!$E$7+(Positions!$E$11*Positions!$P$11)*(Positions!$E$11*Positions!$O$11)*Factors!$D$7*Factors!$D$6*Factors!$F$7+(Positions!$E$11*Positions!$P$11)*(Positions!$E$11*Positions!$P$11)*Factors!$D$7*Factors!$D$7*Factors!$G$7+(Positions!$E$11*Positions!$P$11)*(Positions!$E$11*Positions!$Q$11)*Factors!$D$7*Factors!$D$8*Factors!$H$7+(Positions!$E$11*Positions!$P$11)*(Positions!$E$11*Positions!$R$11)*Factors!$D$7*Factors!$D$9*Factors!$I$7+(Positions!$E$11*Positions!$Q$11)*(Positions!$E$11*Positions!$N$11)*Factors!$D$8*Factors!$D$5*Factors!$E$8+(Positions!$E$11*Positions!$Q$11)*(Positions!$E$11*Positions!$O$11)*Factors!$D$8*Factors!$D$6*Factors!$F$8+(Positions!$E$11*Positions!$Q$11)*(Positions!$E$11*Positions!$P$11)*Factors!$D$8*Factors!$D$7*Factors!$G$8+(Positions!$E$11*Positions!$Q$11)*(Positions!$E$11*Positions!$Q$11)*Factors!$D$8*Factors!$D$8*Factors!$H$8+(Positions!$E$11*Positions!$Q$11)*(Positions!$E$11*Positions!$R$11)*Factors!$D$8*Factors!$D$9*Factors!$I$8+(Positions!$E$11*Positions!$R$11)*(Positions!$E$11*Positions!$N$11)*Factors!$D$9*Factors!$D$5*Factors!$E$9+(Positions!$E$11*Positions!$R$11)*(Positions!$E$11*Positions!$O$11)*Factors!$D$9*Factors!$D$6*Factors!$F$9+(Positions!$E$11*Positions!$R$11)*(Positions!$E$11*Positions!$P$11)*Factors!$D$9*Factors!$D$7*Factors!$G$9+(Positions!$E$11*Positions!$R$11)*(Positions!$E$11*Positions!$Q$11)*Factors!$D$9*Factors!$D$8*Factors!$H$9+(Positions!$E$11*Positions!$R$11)*(Positions!$E$11*Positions!$R$11)*Factors!$D$9*Factors!$D$9*Factors!$I$9)/Assumptions!$E$6)) | E11: =IFERROR('VaR & ES'!$C$7*((Positions!$E$11*Positions!$N$11)*Factors!$D$5*Factors!$C$5*Factors!$D$5*Factors!$E$5+(Positions!$E$11*Positions!$N$11)*Factors!$D$5*Factors!$C$6*Factors!$D$6*Factors!$F$5+(Positions!$E$11*Positions!$N$11)*Factors!$D$5*Factors!$C$7*Factors!$D$7*Factors!$G$5+(Positions!$E$11*Positions!$N$11)*Factors!$D$5*Factors!$C$8*Factors!$D$8*Factors!$H$5+(Positions!$E$11*Positions!$N$11)*Factors!$D$5*Factors!$C$9*Factors!$D$9*Factors!$I$5+(Positions!$E$11*Positions!$O$11)*Factors!$D$6*Factors!$C$5*Factors!$D$5*Factors!$E$6+(Positions!$E$11*Positions!$O$11)*Factors!$D$6*Factors!$C$6*Factors!$D$6*Factors!$F$6+(Positions!$E$11*Positions!$O$11)*Factors!$D$6*Factors!$C$7*Factors!$D$7*Factors!$G$6+(Positions!$E$11*Positions!$O$11)*Factors!$D$6*Factors!$C$8*Factors!$D$8*Factors!$H$6+(Positions!$E$11*Positions!$O$11)*Factors!$D$6*Factors!$C$9*Factors!$D$9*Factors!$I$6+(Positions!$E$11*Positions!$P$11)*Factors!$D$7*Factors!$C$5*Factors!$D$5*Factors!$E$7+(Positions!$E$11*Positions!$P$11)*Factors!$D$7*Factors!$C$6*Factors!$D$6*Factors!$F$7+(Positions!$E$11*Positions!$P$11)*Factors!$D$7*Factors!$C$7*Factors!$D$7*Factors!$G$7+(Positions!$E$11*Positions!$P$11)*Factors!$D$7*Factors!$C$8*Factors!$D$8*Factors!$H$7+(Positions!$E$11*Positions!$P$11)*Factors!$D$7*Factors!$C$9*Factors!$D$9*Factors!$I$7+(Positions!$E$11*Positions!$Q$11)*Factors!$D$8*Factors!$C$5*Factors!$D$5*Factors!$E$8+(Positions!$E$11*Positions!$Q$11)*Factors!$D$8*Factors!$C$6*Factors!$D$6*Factors!$F$8+(Positions!$E$11*Positions!$Q$11)*Factors!$D$8*Factors!$C$7*Factors!$D$7*Factors!$G$8+(Positions!$E$11*Positions!$Q$11)*Factors!$D$8*Factors!$C$8*Factors!$D$8*Factors!$H$8+(Positions!$E$11*Positions!$Q$11)*Factors!$D$8*Factors!$C$9*Factors!$D$9*Factors!$I$8+(Positions!$E$11*Positions!$R$11)*Factors!$D$9*Factors!$C$5*Factors!$D$5*Factors!$E$9+(Positions!$E$11*Positions!$R$11)*Factors!$D$9*Factors!$C$6*Factors!$D$6*Factors!$F$9+(Positions!$E$11*Positions!$R$11)*Factors!$D$9*Factors!$C$7*Factors!$D$7*Factors!$G$9+(Positions!$E$11*Positions!$R$11)*Factors!$D$9*Factors!$C$8*Factors!$D$8*Factors!$H$9+(Positions!$E$11*Positions!$R$11)*Factors!$D$9*Factors!$C$9*Factors!$D$9*Factors!$I$9)/(Factors!$C$13*SQRT(Assumptions!$E$6)),0) | F11: =IFERROR(E11/'VaR & ES'!$C$8,0) | G11: =-MIN((Positions!$E$11*Positions!$N$11*Stress!$C$5+Positions!$E$11*Positions!$O$11*Stress!$D$5+Positions!$E$11*Positions!$P$11*Stress!$E$5+Positions!$E$11*Positions!$Q$11*Stress!$F$5+Positions!$E$11*Positions!$R$11*Stress!$G$5),(Positions!$E$11*Positions!$N$11*Stress!$C$6+Positions!$E$11*Positions!$O$11*Stress!$D$6+Positions!$E$11*Positions!$P$11*Stress!$E$6+Positions!$E$11*Positions!$Q$11*Stress!$F$6+Positions!$E$11*Positions!$R$11*Stress!$G$6),(Positions!$E$11*Positions!$N$11*Stress!$C$7+Positions!$E$11*Positions!$O$11*Stress!$D$7+Positions!$E$11*Positions!$P$11*Stress!$E$7+Positions!$E$11*Positions!$Q$11*Stress!$F$7+Positions!$E$11*Positions!$R$11*Stress!$G$7),(Positions!$E$11*Positions!$N$11*Stress!$C$8+Positions!$E$11*Positions!$O$11*Stress!$D$8+Positions!$E$11*Positions!$P$11*Stress!$E$8+Positions!$E$11*Positions!$Q$11*Stress!$F$8+Positions!$E$11*Positions!$R$11*Stress!$G$8),(Positions!$E$11*Positions!$N$11*Stress!$C$9+Positions!$E$11*Positions!$O$11*Stress!$D$9+Positions!$E$11*Positions!$P$11*Stress!$E$9+Positions!$E$11*Positions!$Q$11*Stress!$F$9+Positions!$E$11*Positions!$R$11*Stress!$G$9),(Positions!$E$11*Positions!$N$11*Stress!$C$10+Positions!$E$11*Positions!$O$11*Stress!$D$10+Positions!$E$11*Positions!$P$11*Stress!$E$10+Positions!$E$11*Positions!$Q$11*Stress!$F$10+Positions!$E$11*Positions!$R$11*Stress!$G$10)) | H11: =Liquidity!G11 | I11: =ABS(E11)+G11+H11 | J11: =IFERROR(I11/SUM($I$5:$I$16),0)
B12: =Positions!B12 | C12: =ABS(Positions!E12) | D12: ='VaR & ES'!$C$7*SQRT(MAX(0,((Positions!$E$12*Positions!$N$12)*(Positions!$E$12*Positions!$N$12)*Factors!$D$5*Factors!$D$5*Factors!$E$5+(Positions!$E$12*Positions!$N$12)*(Positions!$E$12*Positions!$O$12)*Factors!$D$5*Factors!$D$6*Factors!$F$5+(Positions!$E$12*Positions!$N$12)*(Positions!$E$12*Positions!$P$12)*Factors!$D$5*Factors!$D$7*Factors!$G$5+(Positions!$E$12*Positions!$N$12)*(Positions!$E$12*Positions!$Q$12)*Factors!$D$5*Factors!$D$8*Factors!$H$5+(Positions!$E$12*Positions!$N$12)*(Positions!$E$12*Positions!$R$12)*Factors!$D$5*Factors!$D$9*Factors!$I$5+(Positions!$E$12*Positions!$O$12)*(Positions!$E$12*Positions!$N$12)*Factors!$D$6*Factors!$D$5*Factors!$E$6+(Positions!$E$12*Positions!$O$12)*(Positions!$E$12*Positions!$O$12)*Factors!$D$6*Factors!$D$6*Factors!$F$6+(Positions!$E$12*Positions!$O$12)*(Positions!$E$12*Positions!$P$12)*Factors!$D$6*Factors!$D$7*Factors!$G$6+(Positions!$E$12*Positions!$O$12)*(Positions!$E$12*Positions!$Q$12)*Factors!$D$6*Factors!$D$8*Factors!$H$6+(Positions!$E$12*Positions!$O$12)*(Positions!$E$12*Positions!$R$12)*Factors!$D$6*Factors!$D$9*Factors!$I$6+(Positions!$E$12*Positions!$P$12)*(Positions!$E$12*Positions!$N$12)*Factors!$D$7*Factors!$D$5*Factors!$E$7+(Positions!$E$12*Positions!$P$12)*(Positions!$E$12*Positions!$O$12)*Factors!$D$7*Factors!$D$6*Factors!$F$7+(Positions!$E$12*Positions!$P$12)*(Positions!$E$12*Positions!$P$12)*Factors!$D$7*Factors!$D$7*Factors!$G$7+(Positions!$E$12*Positions!$P$12)*(Positions!$E$12*Positions!$Q$12)*Factors!$D$7*Factors!$D$8*Factors!$H$7+(Positions!$E$12*Positions!$P$12)*(Positions!$E$12*Positions!$R$12)*Factors!$D$7*Factors!$D$9*Factors!$I$7+(Positions!$E$12*Positions!$Q$12)*(Positions!$E$12*Positions!$N$12)*Factors!$D$8*Factors!$D$5*Factors!$E$8+(Positions!$E$12*Positions!$Q$12)*(Positions!$E$12*Positions!$O$12)*Factors!$D$8*Factors!$D$6*Factors!$F$8+(Positions!$E$12*Positions!$Q$12)*(Positions!$E$12*Positions!$P$12)*Factors!$D$8*Factors!$D$7*Factors!$G$8+(Positions!$E$12*Positions!$Q$12)*(Positions!$E$12*Positions!$Q$12)*Factors!$D$8*Factors!$D$8*Factors!$H$8+(Positions!$E$12*Positions!$Q$12)*(Positions!$E$12*Positions!$R$12)*Factors!$D$8*Factors!$D$9*Factors!$I$8+(Positions!$E$12*Positions!$R$12)*(Positions!$E$12*Positions!$N$12)*Factors!$D$9*Factors!$D$5*Factors!$E$9+(Positions!$E$12*Positions!$R$12)*(Positions!$E$12*Positions!$O$12)*Factors!$D$9*Factors!$D$6*Factors!$F$9+(Positions!$E$12*Positions!$R$12)*(Positions!$E$12*Positions!$P$12)*Factors!$D$9*Factors!$D$7*Factors!$G$9+(Positions!$E$12*Positions!$R$12)*(Positions!$E$12*Positions!$Q$12)*Factors!$D$9*Factors!$D$8*Factors!$H$9+(Positions!$E$12*Positions!$R$12)*(Positions!$E$12*Positions!$R$12)*Factors!$D$9*Factors!$D$9*Factors!$I$9)/Assumptions!$E$6)) | E12: =IFERROR('VaR & ES'!$C$7*((Positions!$E$12*Positions!$N$12)*Factors!$D$5*Factors!$C$5*Factors!$D$5*Factors!$E$5+(Positions!$E$12*Positions!$N$12)*Factors!$D$5*Factors!$C$6*Factors!$D$6*Factors!$F$5+(Positions!$E$12*Positions!$N$12)*Factors!$D$5*Factors!$C$7*Factors!$D$7*Factors!$G$5+(Positions!$E$12*Positions!$N$12)*Factors!$D$5*Factors!$C$8*Factors!$D$8*Factors!$H$5+(Positions!$E$12*Positions!$N$12)*Factors!$D$5*Factors!$C$9*Factors!$D$9*Factors!$I$5+(Positions!$E$12*Positions!$O$12)*Factors!$D$6*Factors!$C$5*Factors!$D$5*Factors!$E$6+(Positions!$E$12*Positions!$O$12)*Factors!$D$6*Factors!$C$6*Factors!$D$6*Factors!$F$6+(Positions!$E$12*Positions!$O$12)*Factors!$D$6*Factors!$C$7*Factors!$D$7*Factors!$G$6+(Positions!$E$12*Positions!$O$12)*Factors!$D$6*Factors!$C$8*Factors!$D$8*Factors!$H$6+(Positions!$E$12*Positions!$O$12)*Factors!$D$6*Factors!$C$9*Factors!$D$9*Factors!$I$6+(Positions!$E$12*Positions!$P$12)*Factors!$D$7*Factors!$C$5*Factors!$D$5*Factors!$E$7+(Positions!$E$12*Positions!$P$12)*Factors!$D$7*Factors!$C$6*Factors!$D$6*Factors!$F$7+(Positions!$E$12*Positions!$P$12)*Factors!$D$7*Factors!$C$7*Factors!$D$7*Factors!$G$7+(Positions!$E$12*Positions!$P$12)*Factors!$D$7*Factors!$C$8*Factors!$D$8*Factors!$H$7+(Positions!$E$12*Positions!$P$12)*Factors!$D$7*Factors!$C$9*Factors!$D$9*Factors!$I$7+(Positions!$E$12*Positions!$Q$12)*Factors!$D$8*Factors!$C$5*Factors!$D$5*Factors!$E$8+(Positions!$E$12*Positions!$Q$12)*Factors!$D$8*Factors!$C$6*Factors!$D$6*Factors!$F$8+(Positions!$E$12*Positions!$Q$12)*Factors!$D$8*Factors!$C$7*Factors!$D$7*Factors!$G$8+(Positions!$E$12*Positions!$Q$12)*Factors!$D$8*Factors!$C$8*Factors!$D$8*Factors!$H$8+(Positions!$E$12*Positions!$Q$12)*Factors!$D$8*Factors!$C$9*Factors!$D$9*Factors!$I$8+(Positions!$E$12*Positions!$R$12)*Factors!$D$9*Factors!$C$5*Factors!$D$5*Factors!$E$9+(Positions!$E$12*Positions!$R$12)*Factors!$D$9*Factors!$C$6*Factors!$D$6*Factors!$F$9+(Positions!$E$12*Positions!$R$12)*Factors!$D$9*Factors!$C$7*Factors!$D$7*Factors!$G$9+(Positions!$E$12*Positions!$R$12)*Factors!$D$9*Factors!$C$8*Factors!$D$8*Factors!$H$9+(Positions!$E$12*Positions!$R$12)*Factors!$D$9*Factors!$C$9*Factors!$D$9*Factors!$I$9)/(Factors!$C$13*SQRT(Assumptions!$E$6)),0) | F12: =IFERROR(E12/'VaR & ES'!$C$8,0) | G12: =-MIN((Positions!$E$12*Positions!$N$12*Stress!$C$5+Positions!$E$12*Positions!$O$12*Stress!$D$5+Positions!$E$12*Positions!$P$12*Stress!$E$5+Positions!$E$12*Positions!$Q$12*Stress!$F$5+Positions!$E$12*Positions!$R$12*Stress!$G$5),(Positions!$E$12*Positions!$N$12*Stress!$C$6+Positions!$E$12*Positions!$O$12*Stress!$D$6+Positions!$E$12*Positions!$P$12*Stress!$E$6+Positions!$E$12*Positions!$Q$12*Stress!$F$6+Positions!$E$12*Positions!$R$12*Stress!$G$6),(Positions!$E$12*Positions!$N$12*Stress!$C$7+Positions!$E$12*Positions!$O$12*Stress!$D$7+Positions!$E$12*Positions!$P$12*Stress!$E$7+Positions!$E$12*Positions!$Q$12*Stress!$F$7+Positions!$E$12*Positions!$R$12*Stress!$G$7),(Positions!$E$12*Positions!$N$12*Stress!$C$8+Positions!$E$12*Positions!$O$12*Stress!$D$8+Positions!$E$12*Positions!$P$12*Stress!$E$8+Positions!$E$12*Positions!$Q$12*Stress!$F$8+Positions!$E$12*Positions!$R$12*Stress!$G$8),(Positions!$E$12*Positions!$N$12*Stress!$C$9+Positions!$E$12*Positions!$O$12*Stress!$D$9+Positions!$E$12*Positions!$P$12*Stress!$E$9+Positions!$E$12*Positions!$Q$12*Stress!$F$9+Positions!$E$12*Positions!$R$12*Stress!$G$9),(Positions!$E$12*Positions!$N$12*Stress!$C$10+Positions!$E$12*Positions!$O$12*Stress!$D$10+Positions!$E$12*Positions!$P$12*Stress!$E$10+Positions!$E$12*Positions!$Q$12*Stress!$F$10+Positions!$E$12*Positions!$R$12*Stress!$G$10)) | H12: =Liquidity!G12 | I12: =ABS(E12)+G12+H12 | J12: =IFERROR(I12/SUM($I$5:$I$16),0)
B13: =Positions!B13 | C13: =ABS(Positions!E13) | D13: ='VaR & ES'!$C$7*SQRT(MAX(0,((Positions!$E$13*Positions!$N$13)*(Positions!$E$13*Positions!$N$13)*Factors!$D$5*Factors!$D$5*Factors!$E$5+(Positions!$E$13*Positions!$N$13)*(Positions!$E$13*Positions!$O$13)*Factors!$D$5*Factors!$D$6*Factors!$F$5+(Positions!$E$13*Positions!$N$13)*(Positions!$E$13*Positions!$P$13)*Factors!$D$5*Factors!$D$7*Factors!$G$5+(Positions!$E$13*Positions!$N$13)*(Positions!$E$13*Positions!$Q$13)*Factors!$D$5*Factors!$D$8*Factors!$H$5+(Positions!$E$13*Positions!$N$13)*(Positions!$E$13*Positions!$R$13)*Factors!$D$5*Factors!$D$9*Factors!$I$5+(Positions!$E$13*Positions!$O$13)*(Positions!$E$13*Positions!$N$13)*Factors!$D$6*Factors!$D$5*Factors!$E$6+(Positions!$E$13*Positions!$O$13)*(Positions!$E$13*Positions!$O$13)*Factors!$D$6*Factors!$D$6*Factors!$F$6+(Positions!$E$13*Positions!$O$13)*(Positions!$E$13*Positions!$P$13)*Factors!$D$6*Factors!$D$7*Factors!$G$6+(Positions!$E$13*Positions!$O$13)*(Positions!$E$13*Positions!$Q$13)*Factors!$D$6*Factors!$D$8*Factors!$H$6+(Positions!$E$13*Positions!$O$13)*(Positions!$E$13*Positions!$R$13)*Factors!$D$6*Factors!$D$9*Factors!$I$6+(Positions!$E$13*Positions!$P$13)*(Positions!$E$13*Positions!$N$13)*Factors!$D$7*Factors!$D$5*Factors!$E$7+(Positions!$E$13*Positions!$P$13)*(Positions!$E$13*Positions!$O$13)*Factors!$D$7*Factors!$D$6*Factors!$F$7+(Positions!$E$13*Positions!$P$13)*(Positions!$E$13*Positions!$P$13)*Factors!$D$7*Factors!$D$7*Factors!$G$7+(Positions!$E$13*Positions!$P$13)*(Positions!$E$13*Positions!$Q$13)*Factors!$D$7*Factors!$D$8*Factors!$H$7+(Positions!$E$13*Positions!$P$13)*(Positions!$E$13*Positions!$R$13)*Factors!$D$7*Factors!$D$9*Factors!$I$7+(Positions!$E$13*Positions!$Q$13)*(Positions!$E$13*Positions!$N$13)*Factors!$D$8*Factors!$D$5*Factors!$E$8+(Positions!$E$13*Positions!$Q$13)*(Positions!$E$13*Positions!$O$13)*Factors!$D$8*Factors!$D$6*Factors!$F$8+(Positions!$E$13*Positions!$Q$13)*(Positions!$E$13*Positions!$P$13)*Factors!$D$8*Factors!$D$7*Factors!$G$8+(Positions!$E$13*Positions!$Q$13)*(Positions!$E$13*Positions!$Q$13)*Factors!$D$8*Factors!$D$8*Factors!$H$8+(Positions!$E$13*Positions!$Q$13)*(Positions!$E$13*Positions!$R$13)*Factors!$D$8*Factors!$D$9*Factors!$I$8+(Positions!$E$13*Positions!$R$13)*(Positions!$E$13*Positions!$N$13)*Factors!$D$9*Factors!$D$5*Factors!$E$9+(Positions!$E$13*Positions!$R$13)*(Positions!$E$13*Positions!$O$13)*Factors!$D$9*Factors!$D$6*Factors!$F$9+(Positions!$E$13*Positions!$R$13)*(Positions!$E$13*Positions!$P$13)*Factors!$D$9*Factors!$D$7*Factors!$G$9+(Positions!$E$13*Positions!$R$13)*(Positions!$E$13*Positions!$Q$13)*Factors!$D$9*Factors!$D$8*Factors!$H$9+(Positions!$E$13*Positions!$R$13)*(Positions!$E$13*Positions!$R$13)*Factors!$D$9*Factors!$D$9*Factors!$I$9)/Assumptions!$E$6)) | E13: =IFERROR('VaR & ES'!$C$7*((Positions!$E$13*Positions!$N$13)*Factors!$D$5*Factors!$C$5*Factors!$D$5*Factors!$E$5+(Positions!$E$13*Positions!$N$13)*Factors!$D$5*Factors!$C$6*Factors!$D$6*Factors!$F$5+(Positions!$E$13*Positions!$N$13)*Factors!$D$5*Factors!$C$7*Factors!$D$7*Factors!$G$5+(Positions!$E$13*Positions!$N$13)*Factors!$D$5*Factors!$C$8*Factors!$D$8*Factors!$H$5+(Positions!$E$13*Positions!$N$13)*Factors!$D$5*Factors!$C$9*Factors!$D$9*Factors!$I$5+(Positions!$E$13*Positions!$O$13)*Factors!$D$6*Factors!$C$5*Factors!$D$5*Factors!$E$6+(Positions!$E$13*Positions!$O$13)*Factors!$D$6*Factors!$C$6*Factors!$D$6*Factors!$F$6+(Positions!$E$13*Positions!$O$13)*Factors!$D$6*Factors!$C$7*Factors!$D$7*Factors!$G$6+(Positions!$E$13*Positions!$O$13)*Factors!$D$6*Factors!$C$8*Factors!$D$8*Factors!$H$6+(Positions!$E$13*Positions!$O$13)*Factors!$D$6*Factors!$C$9*Factors!$D$9*Factors!$I$6+(Positions!$E$13*Positions!$P$13)*Factors!$D$7*Factors!$C$5*Factors!$D$5*Factors!$E$7+(Positions!$E$13*Positions!$P$13)*Factors!$D$7*Factors!$C$6*Factors!$D$6*Factors!$F$7+(Positions!$E$13*Positions!$P$13)*Factors!$D$7*Factors!$C$7*Factors!$D$7*Factors!$G$7+(Positions!$E$13*Positions!$P$13)*Factors!$D$7*Factors!$C$8*Factors!$D$8*Factors!$H$7+(Positions!$E$13*Positions!$P$13)*Factors!$D$7*Factors!$C$9*Factors!$D$9*Factors!$I$7+(Positions!$E$13*Positions!$Q$13)*Factors!$D$8*Factors!$C$5*Factors!$D$5*Factors!$E$8+(Positions!$E$13*Positions!$Q$13)*Factors!$D$8*Factors!$C$6*Factors!$D$6*Factors!$F$8+(Positions!$E$13*Positions!$Q$13)*Factors!$D$8*Factors!$C$7*Factors!$D$7*Factors!$G$8+(Positions!$E$13*Positions!$Q$13)*Factors!$D$8*Factors!$C$8*Factors!$D$8*Factors!$H$8+(Positions!$E$13*Positions!$Q$13)*Factors!$D$8*Factors!$C$9*Factors!$D$9*Factors!$I$8+(Positions!$E$13*Positions!$R$13)*Factors!$D$9*Factors!$C$5*Factors!$D$5*Factors!$E$9+(Positions!$E$13*Positions!$R$13)*Factors!$D$9*Factors!$C$6*Factors!$D$6*Factors!$F$9+(Positions!$E$13*Positions!$R$13)*Factors!$D$9*Factors!$C$7*Factors!$D$7*Factors!$G$9+(Positions!$E$13*Positions!$R$13)*Factors!$D$9*Factors!$C$8*Factors!$D$8*Factors!$H$9+(Positions!$E$13*Positions!$R$13)*Factors!$D$9*Factors!$C$9*Factors!$D$9*Factors!$I$9)/(Factors!$C$13*SQRT(Assumptions!$E$6)),0) | F13: =IFERROR(E13/'VaR & ES'!$C$8,0) | G13: =-MIN((Positions!$E$13*Positions!$N$13*Stress!$C$5+Positions!$E$13*Positions!$O$13*Stress!$D$5+Positions!$E$13*Positions!$P$13*Stress!$E$5+Positions!$E$13*Positions!$Q$13*Stress!$F$5+Positions!$E$13*Positions!$R$13*Stress!$G$5),(Positions!$E$13*Positions!$N$13*Stress!$C$6+Positions!$E$13*Positions!$O$13*Stress!$D$6+Positions!$E$13*Positions!$P$13*Stress!$E$6+Positions!$E$13*Positions!$Q$13*Stress!$F$6+Positions!$E$13*Positions!$R$13*Stress!$G$6),(Positions!$E$13*Positions!$N$13*Stress!$C$7+Positions!$E$13*Positions!$O$13*Stress!$D$7+Positions!$E$13*Positions!$P$13*Stress!$E$7+Positions!$E$13*Positions!$Q$13*Stress!$F$7+Positions!$E$13*Positions!$R$13*Stress!$G$7),(Positions!$E$13*Positions!$N$13*Stress!$C$8+Positions!$E$13*Positions!$O$13*Stress!$D$8+Positions!$E$13*Positions!$P$13*Stress!$E$8+Positions!$E$13*Positions!$Q$13*Stress!$F$8+Positions!$E$13*Positions!$R$13*Stress!$G$8),(Positions!$E$13*Positions!$N$13*Stress!$C$9+Positions!$E$13*Positions!$O$13*Stress!$D$9+Positions!$E$13*Positions!$P$13*Stress!$E$9+Positions!$E$13*Positions!$Q$13*Stress!$F$9+Positions!$E$13*Positions!$R$13*Stress!$G$9),(Positions!$E$13*Positions!$N$13*Stress!$C$10+Positions!$E$13*Positions!$O$13*Stress!$D$10+Positions!$E$13*Positions!$P$13*Stress!$E$10+Positions!$E$13*Positions!$Q$13*Stress!$F$10+Positions!$E$13*Positions!$R$13*Stress!$G$10)) | H13: =Liquidity!G13 | I13: =ABS(E13)+G13+H13 | J13: =IFERROR(I13/SUM($I$5:$I$16),0)
B14: =Positions!B14 | C14: =ABS(Positions!E14) | D14: ='VaR & ES'!$C$7*SQRT(MAX(0,((Positions!$E$14*Positions!$N$14)*(Positions!$E$14*Positions!$N$14)*Factors!$D$5*Factors!$D$5*Factors!$E$5+(Positions!$E$14*Positions!$N$14)*(Positions!$E$14*Positions!$O$14)*Factors!$D$5*Factors!$D$6*Factors!$F$5+(Positions!$E$14*Positions!$N$14)*(Positions!$E$14*Positions!$P$14)*Factors!$D$5*Factors!$D$7*Factors!$G$5+(Positions!$E$14*Positions!$N$14)*(Positions!$E$14*Positions!$Q$14)*Factors!$D$5*Factors!$D$8*Factors!$H$5+(Positions!$E$14*Positions!$N$14)*(Positions!$E$14*Positions!$R$14)*Factors!$D$5*Factors!$D$9*Factors!$I$5+(Positions!$E$14*Positions!$O$14)*(Positions!$E$14*Positions!$N$14)*Factors!$D$6*Factors!$D$5*Factors!$E$6+(Positions!$E$14*Positions!$O$14)*(Positions!$E$14*Positions!$O$14)*Factors!$D$6*Factors!$D$6*Factors!$F$6+(Positions!$E$14*Positions!$O$14)*(Positions!$E$14*Positions!$P$14)*Factors!$D$6*Factors!$D$7*Factors!$G$6+(Positions!$E$14*Positions!$O$14)*(Positions!$E$14*Positions!$Q$14)*Factors!$D$6*Factors!$D$8*Factors!$H$6+(Positions!$E$14*Positions!$O$14)*(Positions!$E$14*Positions!$R$14)*Factors!$D$6*Factors!$D$9*Factors!$I$6+(Positions!$E$14*Positions!$P$14)*(Positions!$E$14*Positions!$N$14)*Factors!$D$7*Factors!$D$5*Factors!$E$7+(Positions!$E$14*Positions!$P$14)*(Positions!$E$14*Positions!$O$14)*Factors!$D$7*Factors!$D$6*Factors!$F$7+(Positions!$E$14*Positions!$P$14)*(Positions!$E$14*Positions!$P$14)*Factors!$D$7*Factors!$D$7*Factors!$G$7+(Positions!$E$14*Positions!$P$14)*(Positions!$E$14*Positions!$Q$14)*Factors!$D$7*Factors!$D$8*Factors!$H$7+(Positions!$E$14*Positions!$P$14)*(Positions!$E$14*Positions!$R$14)*Factors!$D$7*Factors!$D$9*Factors!$I$7+(Positions!$E$14*Positions!$Q$14)*(Positions!$E$14*Positions!$N$14)*Factors!$D$8*Factors!$D$5*Factors!$E$8+(Positions!$E$14*Positions!$Q$14)*(Positions!$E$14*Positions!$O$14)*Factors!$D$8*Factors!$D$6*Factors!$F$8+(Positions!$E$14*Positions!$Q$14)*(Positions!$E$14*Positions!$P$14)*Factors!$D$8*Factors!$D$7*Factors!$G$8+(Positions!$E$14*Positions!$Q$14)*(Positions!$E$14*Positions!$Q$14)*Factors!$D$8*Factors!$D$8*Factors!$H$8+(Positions!$E$14*Positions!$Q$14)*(Positions!$E$14*Positions!$R$14)*Factors!$D$8*Factors!$D$9*Factors!$I$8+(Positions!$E$14*Positions!$R$14)*(Positions!$E$14*Positions!$N$14)*Factors!$D$9*Factors!$D$5*Factors!$E$9+(Positions!$E$14*Positions!$R$14)*(Positions!$E$14*Positions!$O$14)*Factors!$D$9*Factors!$D$6*Factors!$F$9+(Positions!$E$14*Positions!$R$14)*(Positions!$E$14*Positions!$P$14)*Factors!$D$9*Factors!$D$7*Factors!$G$9+(Positions!$E$14*Positions!$R$14)*(Positions!$E$14*Positions!$Q$14)*Factors!$D$9*Factors!$D$8*Factors!$H$9+(Positions!$E$14*Positions!$R$14)*(Positions!$E$14*Positions!$R$14)*Factors!$D$9*Factors!$D$9*Factors!$I$9)/Assumptions!$E$6)) | E14: =IFERROR('VaR & ES'!$C$7*((Positions!$E$14*Positions!$N$14)*Factors!$D$5*Factors!$C$5*Factors!$D$5*Factors!$E$5+(Positions!$E$14*Positions!$N$14)*Factors!$D$5*Factors!$C$6*Factors!$D$6*Factors!$F$5+(Positions!$E$14*Positions!$N$14)*Factors!$D$5*Factors!$C$7*Factors!$D$7*Factors!$G$5+(Positions!$E$14*Positions!$N$14)*Factors!$D$5*Factors!$C$8*Factors!$D$8*Factors!$H$5+(Positions!$E$14*Positions!$N$14)*Factors!$D$5*Factors!$C$9*Factors!$D$9*Factors!$I$5+(Positions!$E$14*Positions!$O$14)*Factors!$D$6*Factors!$C$5*Factors!$D$5*Factors!$E$6+(Positions!$E$14*Positions!$O$14)*Factors!$D$6*Factors!$C$6*Factors!$D$6*Factors!$F$6+(Positions!$E$14*Positions!$O$14)*Factors!$D$6*Factors!$C$7*Factors!$D$7*Factors!$G$6+(Positions!$E$14*Positions!$O$14)*Factors!$D$6*Factors!$C$8*Factors!$D$8*Factors!$H$6+(Positions!$E$14*Positions!$O$14)*Factors!$D$6*Factors!$C$9*Factors!$D$9*Factors!$I$6+(Positions!$E$14*Positions!$P$14)*Factors!$D$7*Factors!$C$5*Factors!$D$5*Factors!$E$7+(Positions!$E$14*Positions!$P$14)*Factors!$D$7*Factors!$C$6*Factors!$D$6*Factors!$F$7+(Positions!$E$14*Positions!$P$14)*Factors!$D$7*Factors!$C$7*Factors!$D$7*Factors!$G$7+(Positions!$E$14*Positions!$P$14)*Factors!$D$7*Factors!$C$8*Factors!$D$8*Factors!$H$7+(Positions!$E$14*Positions!$P$14)*Factors!$D$7*Factors!$C$9*Factors!$D$9*Factors!$I$7+(Positions!$E$14*Positions!$Q$14)*Factors!$D$8*Factors!$C$5*Factors!$D$5*Factors!$E$8+(Positions!$E$14*Positions!$Q$14)*Factors!$D$8*Factors!$C$6*Factors!$D$6*Factors!$F$8+(Positions!$E$14*Positions!$Q$14)*Factors!$D$8*Factors!$C$7*Factors!$D$7*Factors!$G$8+(Positions!$E$14*Positions!$Q$14)*Factors!$D$8*Factors!$C$8*Factors!$D$8*Factors!$H$8+(Positions!$E$14*Positions!$Q$14)*Factors!$D$8*Factors!$C$9*Factors!$D$9*Factors!$I$8+(Positions!$E$14*Positions!$R$14)*Factors!$D$9*Factors!$C$5*Factors!$D$5*Factors!$E$9+(Positions!$E$14*Positions!$R$14)*Factors!$D$9*Factors!$C$6*Factors!$D$6*Factors!$F$9+(Positions!$E$14*Positions!$R$14)*Factors!$D$9*Factors!$C$7*Factors!$D$7*Factors!$G$9+(Positions!$E$14*Positions!$R$14)*Factors!$D$9*Factors!$C$8*Factors!$D$8*Factors!$H$9+(Positions!$E$14*Positions!$R$14)*Factors!$D$9*Factors!$C$9*Factors!$D$9*Factors!$I$9)/(Factors!$C$13*SQRT(Assumptions!$E$6)),0) | F14: =IFERROR(E14/'VaR & ES'!$C$8,0) | G14: =-MIN((Positions!$E$14*Positions!$N$14*Stress!$C$5+Positions!$E$14*Positions!$O$14*Stress!$D$5+Positions!$E$14*Positions!$P$14*Stress!$E$5+Positions!$E$14*Positions!$Q$14*Stress!$F$5+Positions!$E$14*Positions!$R$14*Stress!$G$5),(Positions!$E$14*Positions!$N$14*Stress!$C$6+Positions!$E$14*Positions!$O$14*Stress!$D$6+Positions!$E$14*Positions!$P$14*Stress!$E$6+Positions!$E$14*Positions!$Q$14*Stress!$F$6+Positions!$E$14*Positions!$R$14*Stress!$G$6),(Positions!$E$14*Positions!$N$14*Stress!$C$7+Positions!$E$14*Positions!$O$14*Stress!$D$7+Positions!$E$14*Positions!$P$14*Stress!$E$7+Positions!$E$14*Positions!$Q$14*Stress!$F$7+Positions!$E$14*Positions!$R$14*Stress!$G$7),(Positions!$E$14*Positions!$N$14*Stress!$C$8+Positions!$E$14*Positions!$O$14*Stress!$D$8+Positions!$E$14*Positions!$P$14*Stress!$E$8+Positions!$E$14*Positions!$Q$14*Stress!$F$8+Positions!$E$14*Positions!$R$14*Stress!$G$8),(Positions!$E$14*Positions!$N$14*Stress!$C$9+Positions!$E$14*Positions!$O$14*Stress!$D$9+Positions!$E$14*Positions!$P$14*Stress!$E$9+Positions!$E$14*Positions!$Q$14*Stress!$F$9+Positions!$E$14*Positions!$R$14*Stress!$G$9),(Positions!$E$14*Positions!$N$14*Stress!$C$10+Positions!$E$14*Positions!$O$14*Stress!$D$10+Positions!$E$14*Positions!$P$14*Stress!$E$10+Positions!$E$14*Positions!$Q$14*Stress!$F$10+Positions!$E$14*Positions!$R$14*Stress!$G$10)) | H14: =Liquidity!G14 | I14: =ABS(E14)+G14+H14 | J14: =IFERROR(I14/SUM($I$5:$I$16),0)
B15: =Positions!B15 | C15: =ABS(Positions!E15) | D15: ='VaR & ES'!$C$7*SQRT(MAX(0,((Positions!$E$15*Positions!$N$15)*(Positions!$E$15*Positions!$N$15)*Factors!$D$5*Factors!$D$5*Factors!$E$5+(Positions!$E$15*Positions!$N$15)*(Positions!$E$15*Positions!$O$15)*Factors!$D$5*Factors!$D$6*Factors!$F$5+(Positions!$E$15*Positions!$N$15)*(Positions!$E$15*Positions!$P$15)*Factors!$D$5*Factors!$D$7*Factors!$G$5+(Positions!$E$15*Positions!$N$15)*(Positions!$E$15*Positions!$Q$15)*Factors!$D$5*Factors!$D$8*Factors!$H$5+(Positions!$E$15*Positions!$N$15)*(Positions!$E$15*Positions!$R$15)*Factors!$D$5*Factors!$D$9*Factors!$I$5+(Positions!$E$15*Positions!$O$15)*(Positions!$E$15*Positions!$N$15)*Factors!$D$6*Factors!$D$5*Factors!$E$6+(Positions!$E$15*Positions!$O$15)*(Positions!$E$15*Positions!$O$15)*Factors!$D$6*Factors!$D$6*Factors!$F$6+(Positions!$E$15*Positions!$O$15)*(Positions!$E$15*Positions!$P$15)*Factors!$D$6*Factors!$D$7*Factors!$G$6+(Positions!$E$15*Positions!$O$15)*(Positions!$E$15*Positions!$Q$15)*Factors!$D$6*Factors!$D$8*Factors!$H$6+(Positions!$E$15*Positions!$O$15)*(Positions!$E$15*Positions!$R$15)*Factors!$D$6*Factors!$D$9*Factors!$I$6+(Positions!$E$15*Positions!$P$15)*(Positions!$E$15*Positions!$N$15)*Factors!$D$7*Factors!$D$5*Factors!$E$7+(Positions!$E$15*Positions!$P$15)*(Positions!$E$15*Positions!$O$15)*Factors!$D$7*Factors!$D$6*Factors!$F$7+(Positions!$E$15*Positions!$P$15)*(Positions!$E$15*Positions!$P$15)*Factors!$D$7*Factors!$D$7*Factors!$G$7+(Positions!$E$15*Positions!$P$15)*(Positions!$E$15*Positions!$Q$15)*Factors!$D$7*Factors!$D$8*Factors!$H$7+(Positions!$E$15*Positions!$P$15)*(Positions!$E$15*Positions!$R$15)*Factors!$D$7*Factors!$D$9*Factors!$I$7+(Positions!$E$15*Positions!$Q$15)*(Positions!$E$15*Positions!$N$15)*Factors!$D$8*Factors!$D$5*Factors!$E$8+(Positions!$E$15*Positions!$Q$15)*(Positions!$E$15*Positions!$O$15)*Factors!$D$8*Factors!$D$6*Factors!$F$8+(Positions!$E$15*Positions!$Q$15)*(Positions!$E$15*Positions!$P$15)*Factors!$D$8*Factors!$D$7*Factors!$G$8+(Positions!$E$15*Positions!$Q$15)*(Positions!$E$15*Positions!$Q$15)*Factors!$D$8*Factors!$D$8*Factors!$H$8+(Positions!$E$15*Positions!$Q$15)*(Positions!$E$15*Positions!$R$15)*Factors!$D$8*Factors!$D$9*Factors!$I$8+(Positions!$E$15*Positions!$R$15)*(Positions!$E$15*Positions!$N$15)*Factors!$D$9*Factors!$D$5*Factors!$E$9+(Positions!$E$15*Positions!$R$15)*(Positions!$E$15*Positions!$O$15)*Factors!$D$9*Factors!$D$6*Factors!$F$9+(Positions!$E$15*Positions!$R$15)*(Positions!$E$15*Positions!$P$15)*Factors!$D$9*Factors!$D$7*Factors!$G$9+(Positions!$E$15*Positions!$R$15)*(Positions!$E$15*Positions!$Q$15)*Factors!$D$9*Factors!$D$8*Factors!$H$9+(Positions!$E$15*Positions!$R$15)*(Positions!$E$15*Positions!$R$15)*Factors!$D$9*Factors!$D$9*Factors!$I$9)/Assumptions!$E$6)) | E15: =IFERROR('VaR & ES'!$C$7*((Positions!$E$15*Positions!$N$15)*Factors!$D$5*Factors!$C$5*Factors!$D$5*Factors!$E$5+(Positions!$E$15*Positions!$N$15)*Factors!$D$5*Factors!$C$6*Factors!$D$6*Factors!$F$5+(Positions!$E$15*Positions!$N$15)*Factors!$D$5*Factors!$C$7*Factors!$D$7*Factors!$G$5+(Positions!$E$15*Positions!$N$15)*Factors!$D$5*Factors!$C$8*Factors!$D$8*Factors!$H$5+(Positions!$E$15*Positions!$N$15)*Factors!$D$5*Factors!$C$9*Factors!$D$9*Factors!$I$5+(Positions!$E$15*Positions!$O$15)*Factors!$D$6*Factors!$C$5*Factors!$D$5*Factors!$E$6+(Positions!$E$15*Positions!$O$15)*Factors!$D$6*Factors!$C$6*Factors!$D$6*Factors!$F$6+(Positions!$E$15*Positions!$O$15)*Factors!$D$6*Factors!$C$7*Factors!$D$7*Factors!$G$6+(Positions!$E$15*Positions!$O$15)*Factors!$D$6*Factors!$C$8*Factors!$D$8*Factors!$H$6+(Positions!$E$15*Positions!$O$15)*Factors!$D$6*Factors!$C$9*Factors!$D$9*Factors!$I$6+(Positions!$E$15*Positions!$P$15)*Factors!$D$7*Factors!$C$5*Factors!$D$5*Factors!$E$7+(Positions!$E$15*Positions!$P$15)*Factors!$D$7*Factors!$C$6*Factors!$D$6*Factors!$F$7+(Positions!$E$15*Positions!$P$15)*Factors!$D$7*Factors!$C$7*Factors!$D$7*Factors!$G$7+(Positions!$E$15*Positions!$P$15)*Factors!$D$7*Factors!$C$8*Factors!$D$8*Factors!$H$7+(Positions!$E$15*Positions!$P$15)*Factors!$D$7*Factors!$C$9*Factors!$D$9*Factors!$I$7+(Positions!$E$15*Positions!$Q$15)*Factors!$D$8*Factors!$C$5*Factors!$D$5*Factors!$E$8+(Positions!$E$15*Positions!$Q$15)*Factors!$D$8*Factors!$C$6*Factors!$D$6*Factors!$F$8+(Positions!$E$15*Positions!$Q$15)*Factors!$D$8*Factors!$C$7*Factors!$D$7*Factors!$G$8+(Positions!$E$15*Positions!$Q$15)*Factors!$D$8*Factors!$C$8*Factors!$D$8*Factors!$H$8+(Positions!$E$15*Positions!$Q$15)*Factors!$D$8*Factors!$C$9*Factors!$D$9*Factors!$I$8+(Positions!$E$15*Positions!$R$15)*Factors!$D$9*Factors!$C$5*Factors!$D$5*Factors!$E$9+(Positions!$E$15*Positions!$R$15)*Factors!$D$9*Factors!$C$6*Factors!$D$6*Factors!$F$9+(Positions!$E$15*Positions!$R$15)*Factors!$D$9*Factors!$C$7*Factors!$D$7*Factors!$G$9+(Positions!$E$15*Positions!$R$15)*Factors!$D$9*Factors!$C$8*Factors!$D$8*Factors!$H$9+(Positions!$E$15*Positions!$R$15)*Factors!$D$9*Factors!$C$9*Factors!$D$9*Factors!$I$9)/(Factors!$C$13*SQRT(Assumptions!$E$6)),0) | F15: =IFERROR(E15/'VaR & ES'!$C$8,0) | G15: =-MIN((Positions!$E$15*Positions!$N$15*Stress!$C$5+Positions!$E$15*Positions!$O$15*Stress!$D$5+Positions!$E$15*Positions!$P$15*Stress!$E$5+Positions!$E$15*Positions!$Q$15*Stress!$F$5+Positions!$E$15*Positions!$R$15*Stress!$G$5),(Positions!$E$15*Positions!$N$15*Stress!$C$6+Positions!$E$15*Positions!$O$15*Stress!$D$6+Positions!$E$15*Positions!$P$15*Stress!$E$6+Positions!$E$15*Positions!$Q$15*Stress!$F$6+Positions!$E$15*Positions!$R$15*Stress!$G$6),(Positions!$E$15*Positions!$N$15*Stress!$C$7+Positions!$E$15*Positions!$O$15*Stress!$D$7+Positions!$E$15*Positions!$P$15*Stress!$E$7+Positions!$E$15*Positions!$Q$15*Stress!$F$7+Positions!$E$15*Positions!$R$15*Stress!$G$7),(Positions!$E$15*Positions!$N$15*Stress!$C$8+Positions!$E$15*Positions!$O$15*Stress!$D$8+Positions!$E$15*Positions!$P$15*Stress!$E$8+Positions!$E$15*Positions!$Q$15*Stress!$F$8+Positions!$E$15*Positions!$R$15*Stress!$G$8),(Positions!$E$15*Positions!$N$15*Stress!$C$9+Positions!$E$15*Positions!$O$15*Stress!$D$9+Positions!$E$15*Positions!$P$15*Stress!$E$9+Positions!$E$15*Positions!$Q$15*Stress!$F$9+Positions!$E$15*Positions!$R$15*Stress!$G$9),(Positions!$E$15*Positions!$N$15*Stress!$C$10+Positions!$E$15*Positions!$O$15*Stress!$D$10+Positions!$E$15*Positions!$P$15*Stress!$E$10+Positions!$E$15*Positions!$Q$15*Stress!$F$10+Positions!$E$15*Positions!$R$15*Stress!$G$10)) | H15: =Liquidity!G15 | I15: =ABS(E15)+G15+H15 | J15: =IFERROR(I15/SUM($I$5:$I$16),0)
B16: =Positions!B16 | C16: =ABS(Positions!E16) | D16: ='VaR & ES'!$C$7*SQRT(MAX(0,((Positions!$E$16*Positions!$N$16)*(Positions!$E$16*Positions!$N$16)*Factors!$D$5*Factors!$D$5*Factors!$E$5+(Positions!$E$16*Positions!$N$16)*(Positions!$E$16*Positions!$O$16)*Factors!$D$5*Factors!$D$6*Factors!$F$5+(Positions!$E$16*Positions!$N$16)*(Positions!$E$16*Positions!$P$16)*Factors!$D$5*Factors!$D$7*Factors!$G$5+(Positions!$E$16*Positions!$N$16)*(Positions!$E$16*Positions!$Q$16)*Factors!$D$5*Factors!$D$8*Factors!$H$5+(Positions!$E$16*Positions!$N$16)*(Positions!$E$16*Positions!$R$16)*Factors!$D$5*Factors!$D$9*Factors!$I$5+(Positions!$E$16*Positions!$O$16)*(Positions!$E$16*Positions!$N$16)*Factors!$D$6*Factors!$D$5*Factors!$E$6+(Positions!$E$16*Positions!$O$16)*(Positions!$E$16*Positions!$O$16)*Factors!$D$6*Factors!$D$6*Factors!$F$6+(Positions!$E$16*Positions!$O$16)*(Positions!$E$16*Positions!$P$16)*Factors!$D$6*Factors!$D$7*Factors!$G$6+(Positions!$E$16*Positions!$O$16)*(Positions!$E$16*Positions!$Q$16)*Factors!$D$6*Factors!$D$8*Factors!$H$6+(Positions!$E$16*Positions!$O$16)*(Positions!$E$16*Positions!$R$16)*Factors!$D$6*Factors!$D$9*Factors!$I$6+(Positions!$E$16*Positions!$P$16)*(Positions!$E$16*Positions!$N$16)*Factors!$D$7*Factors!$D$5*Factors!$E$7+(Positions!$E$16*Positions!$P$16)*(Positions!$E$16*Positions!$O$16)*Factors!$D$7*Factors!$D$6*Factors!$F$7+(Positions!$E$16*Positions!$P$16)*(Positions!$E$16*Positions!$P$16)*Factors!$D$7*Factors!$D$7*Factors!$G$7+(Positions!$E$16*Positions!$P$16)*(Positions!$E$16*Positions!$Q$16)*Factors!$D$7*Factors!$D$8*Factors!$H$7+(Positions!$E$16*Positions!$P$16)*(Positions!$E$16*Positions!$R$16)*Factors!$D$7*Factors!$D$9*Factors!$I$7+(Positions!$E$16*Positions!$Q$16)*(Positions!$E$16*Positions!$N$16)*Factors!$D$8*Factors!$D$5*Factors!$E$8+(Positions!$E$16*Positions!$Q$16)*(Positions!$E$16*Positions!$O$16)*Factors!$D$8*Factors!$D$6*Factors!$F$8+(Positions!$E$16*Positions!$Q$16)*(Positions!$E$16*Positions!$P$16)*Factors!$D$8*Factors!$D$7*Factors!$G$8+(Positions!$E$16*Positions!$Q$16)*(Positions!$E$16*Positions!$Q$16)*Factors!$D$8*Factors!$D$8*Factors!$H$8+(Positions!$E$16*Positions!$Q$16)*(Positions!$E$16*Positions!$R$16)*Factors!$D$8*Factors!$D$9*Factors!$I$8+(Positions!$E$16*Positions!$R$16)*(Positions!$E$16*Positions!$N$16)*Factors!$D$9*Factors!$D$5*Factors!$E$9+(Positions!$E$16*Positions!$R$16)*(Positions!$E$16*Positions!$O$16)*Factors!$D$9*Factors!$D$6*Factors!$F$9+(Positions!$E$16*Positions!$R$16)*(Positions!$E$16*Positions!$P$16)*Factors!$D$9*Factors!$D$7*Factors!$G$9+(Positions!$E$16*Positions!$R$16)*(Positions!$E$16*Positions!$Q$16)*Factors!$D$9*Factors!$D$8*Factors!$H$9+(Positions!$E$16*Positions!$R$16)*(Positions!$E$16*Positions!$R$16)*Factors!$D$9*Factors!$D$9*Factors!$I$9)/Assumptions!$E$6)) | E16: =IFERROR('VaR & ES'!$C$7*((Positions!$E$16*Positions!$N$16)*Factors!$D$5*Factors!$C$5*Factors!$D$5*Factors!$E$5+(Positions!$E$16*Positions!$N$16)*Factors!$D$5*Factors!$C$6*Factors!$D$6*Factors!$F$5+(Positions!$E$16*Positions!$N$16)*Factors!$D$5*Factors!$C$7*Factors!$D$7*Factors!$G$5+(Positions!$E$16*Positions!$N$16)*Factors!$D$5*Factors!$C$8*Factors!$D$8*Factors!$H$5+(Positions!$E$16*Positions!$N$16)*Factors!$D$5*Factors!$C$9*Factors!$D$9*Factors!$I$5+(Positions!$E$16*Positions!$O$16)*Factors!$D$6*Factors!$C$5*Factors!$D$5*Factors!$E$6+(Positions!$E$16*Positions!$O$16)*Factors!$D$6*Factors!$C$6*Factors!$D$6*Factors!$F$6+(Positions!$E$16*Positions!$O$16)*Factors!$D$6*Factors!$C$7*Factors!$D$7*Factors!$G$6+(Positions!$E$16*Positions!$O$16)*Factors!$D$6*Factors!$C$8*Factors!$D$8*Factors!$H$6+(Positions!$E$16*Positions!$O$16)*Factors!$D$6*Factors!$C$9*Factors!$D$9*Factors!$I$6+(Positions!$E$16*Positions!$P$16)*Factors!$D$7*Factors!$C$5*Factors!$D$5*Factors!$E$7+(Positions!$E$16*Positions!$P$16)*Factors!$D$7*Factors!$C$6*Factors!$D$6*Factors!$F$7+(Positions!$E$16*Positions!$P$16)*Factors!$D$7*Factors!$C$7*Factors!$D$7*Factors!$G$7+(Positions!$E$16*Positions!$P$16)*Factors!$D$7*Factors!$C$8*Factors!$D$8*Factors!$H$7+(Positions!$E$16*Positions!$P$16)*Factors!$D$7*Factors!$C$9*Factors!$D$9*Factors!$I$7+(Positions!$E$16*Positions!$Q$16)*Factors!$D$8*Factors!$C$5*Factors!$D$5*Factors!$E$8+(Positions!$E$16*Positions!$Q$16)*Factors!$D$8*Factors!$C$6*Factors!$D$6*Factors!$F$8+(Positions!$E$16*Positions!$Q$16)*Factors!$D$8*Factors!$C$7*Factors!$D$7*Factors!$G$8+(Positions!$E$16*Positions!$Q$16)*Factors!$D$8*Factors!$C$8*Factors!$D$8*Factors!$H$8+(Positions!$E$16*Positions!$Q$16)*Factors!$D$8*Factors!$C$9*Factors!$D$9*Factors!$I$8+(Positions!$E$16*Positions!$R$16)*Factors!$D$9*Factors!$C$5*Factors!$D$5*Factors!$E$9+(Positions!$E$16*Positions!$R$16)*Factors!$D$9*Factors!$C$6*Factors!$D$6*Factors!$F$9+(Positions!$E$16*Positions!$R$16)*Factors!$D$9*Factors!$C$7*Factors!$D$7*Factors!$G$9+(Positions!$E$16*Positions!$R$16)*Factors!$D$9*Factors!$C$8*Factors!$D$8*Factors!$H$9+(Positions!$E$16*Positions!$R$16)*Factors!$D$9*Factors!$C$9*Factors!$D$9*Factors!$I$9)/(Factors!$C$13*SQRT(Assumptions!$E$6)),0) | F16: =IFERROR(E16/'VaR & ES'!$C$8,0) | G16: =-MIN((Positions!$E$16*Positions!$N$16*Stress!$C$5+Positions!$E$16*Positions!$O$16*Stress!$D$5+Positions!$E$16*Positions!$P$16*Stress!$E$5+Positions!$E$16*Positions!$Q$16*Stress!$F$5+Positions!$E$16*Positions!$R$16*Stress!$G$5),(Positions!$E$16*Positions!$N$16*Stress!$C$6+Positions!$E$16*Positions!$O$16*Stress!$D$6+Positions!$E$16*Positions!$P$16*Stress!$E$6+Positions!$E$16*Positions!$Q$16*Stress!$F$6+Positions!$E$16*Positions!$R$16*Stress!$G$6),(Positions!$E$16*Positions!$N$16*Stress!$C$7+Positions!$E$16*Positions!$O$16*Stress!$D$7+Positions!$E$16*Positions!$P$16*Stress!$E$7+Positions!$E$16*Positions!$Q$16*Stress!$F$7+Positions!$E$16*Positions!$R$16*Stress!$G$7),(Positions!$E$16*Positions!$N$16*Stress!$C$8+Positions!$E$16*Positions!$O$16*Stress!$D$8+Positions!$E$16*Positions!$P$16*Stress!$E$8+Positions!$E$16*Positions!$Q$16*Stress!$F$8+Positions!$E$16*Positions!$R$16*Stress!$G$8),(Positions!$E$16*Positions!$N$16*Stress!$C$9+Positions!$E$16*Positions!$O$16*Stress!$D$9+Positions!$E$16*Positions!$P$16*Stress!$E$9+Positions!$E$16*Positions!$Q$16*Stress!$F$9+Positions!$E$16*Positions!$R$16*Stress!$G$9),(Positions!$E$16*Positions!$N$16*Stress!$C$10+Positions!$E$16*Positions!$O$16*Stress!$D$10+Positions!$E$16*Positions!$P$16*Stress!$E$10+Positions!$E$16*Positions!$Q$16*Stress!$F$10+Positions!$E$16*Positions!$R$16*Stress!$G$10)) | H16: =Liquidity!G16 | I16: =ABS(E16)+G16+H16 | J16: =IFERROR(I16/SUM($I$5:$I$16),0)
B18: Portfolio total | C18: =SUM(C5:C16) | D18: =SUM(D5:D16) | E18: =SUM(E5:E16) | F18: =SUM(F5:F16) | G18: =SUM(G5:G16) | H18: =SUM(H5:H16) | I18: =SUM(I5:I16) | J18: =SUM(J5:J16)
B20: Component VaR reconciliation | C20: =E18-'VaR & ES'!C8 | D20: =IF(ABS(C20)<0.01,"PASS","REVIEW")
B21: Largest risk concentration | C21: =MAX(J5:J16)
B22: Largest contributor | C22: =INDEX(B5:B16,MATCH(MAX(J5:J16),J5:J16,0))

Sheet Stress
B2: Portfolio Stress Matrix
B4: Scenario | C4: Equity | D4: Rates | E4: Credit | F4: FX | G4: Vol | H4: Liquidity | I4: P&L
B5: Global risk-off | C5: -0.18 | D5: -0.015 | E5: -0.025 | F5: -0.08 | G5: 0.4 | H5: 0.5 | I5: =(Factors!$C$5*C5+Factors!$C$6*D5+Factors!$C$7*E5+Factors!$C$8*F5+Factors!$C$9*G5)-(ABS(Positions!$D$5)*MAX(0,Positions!$M$5-1)+ABS(Positions!$D$6)*MAX(0,Positions!$M$6-1)+ABS(Positions!$D$7)*MAX(0,Positions!$M$7-1)+ABS(Positions!$D$8)*MAX(0,Positions!$M$8-1)+ABS(Positions!$D$9)*MAX(0,Positions!$M$9-1)+ABS(Positions!$D$10)*MAX(0,Positions!$M$10-1)+ABS(Positions!$D$11)*MAX(0,Positions!$M$11-1)+ABS(Positions!$D$12)*MAX(0,Positions!$M$12-1)+ABS(Positions!$D$13)*MAX(0,Positions!$M$13-1)+ABS(Positions!$D$14)*MAX(0,Positions!$M$14-1)+ABS(Positions!$D$15)*MAX(0,Positions!$M$15-1)+ABS(Positions!$D$16)*MAX(0,Positions!$M$16-1))*Assumptions!$E$17*(1-H5)
B6: Inflation / rates shock | C6: -0.08 | D6: 0.025 | E6: 0.012 | F6: 0.05 | G6: 0.2 | H6: 0.7 | I6: =(Factors!$C$5*C6+Factors!$C$6*D6+Factors!$C$7*E6+Factors!$C$8*F6+Factors!$C$9*G6)-(ABS(Positions!$D$5)*MAX(0,Positions!$M$5-1)+ABS(Positions!$D$6)*MAX(0,Positions!$M$6-1)+ABS(Positions!$D$7)*MAX(0,Positions!$M$7-1)+ABS(Positions!$D$8)*MAX(0,Positions!$M$8-1)+ABS(Positions!$D$9)*MAX(0,Positions!$M$9-1)+ABS(Positions!$D$10)*MAX(0,Positions!$M$10-1)+ABS(Positions!$D$11)*MAX(0,Positions!$M$11-1)+ABS(Positions!$D$12)*MAX(0,Positions!$M$12-1)+ABS(Positions!$D$13)*MAX(0,Positions!$M$13-1)+ABS(Positions!$D$14)*MAX(0,Positions!$M$14-1)+ABS(Positions!$D$15)*MAX(0,Positions!$M$15-1)+ABS(Positions!$D$16)*MAX(0,Positions!$M$16-1))*Assumptions!$E$17*(1-H6)
B7: Credit crisis | C7: -0.12 | D7: -0.01 | E7: -0.05 | F7: -0.04 | G7: 0.35 | H7: 0.35 | I7: =(Factors!$C$5*C7+Factors!$C$6*D7+Factors!$C$7*E7+Factors!$C$8*F7+Factors!$C$9*G7)-(ABS(Positions!$D$5)*MAX(0,Positions!$M$5-1)+ABS(Positions!$D$6)*MAX(0,Positions!$M$6-1)+ABS(Positions!$D$7)*MAX(0,Positions!$M$7-1)+ABS(Positions!$D$8)*MAX(0,Positions!$M$8-1)+ABS(Positions!$D$9)*MAX(0,Positions!$M$9-1)+ABS(Positions!$D$10)*MAX(0,Positions!$M$10-1)+ABS(Positions!$D$11)*MAX(0,Positions!$M$11-1)+ABS(Positions!$D$12)*MAX(0,Positions!$M$12-1)+ABS(Positions!$D$13)*MAX(0,Positions!$M$13-1)+ABS(Positions!$D$14)*MAX(0,Positions!$M$14-1)+ABS(Positions!$D$15)*MAX(0,Positions!$M$15-1)+ABS(Positions!$D$16)*MAX(0,Positions!$M$16-1))*Assumptions!$E$17*(1-H7)
B8: Dollar squeeze | C8: -0.07 | D8: 0.01 | E8: -0.015 | F8: 0.12 | G8: 0.25 | H8: 0.45 | I8: =(Factors!$C$5*C8+Factors!$C$6*D8+Factors!$C$7*E8+Factors!$C$8*F8+Factors!$C$9*G8)-(ABS(Positions!$D$5)*MAX(0,Positions!$M$5-1)+ABS(Positions!$D$6)*MAX(0,Positions!$M$6-1)+ABS(Positions!$D$7)*MAX(0,Positions!$M$7-1)+ABS(Positions!$D$8)*MAX(0,Positions!$M$8-1)+ABS(Positions!$D$9)*MAX(0,Positions!$M$9-1)+ABS(Positions!$D$10)*MAX(0,Positions!$M$10-1)+ABS(Positions!$D$11)*MAX(0,Positions!$M$11-1)+ABS(Positions!$D$12)*MAX(0,Positions!$M$12-1)+ABS(Positions!$D$13)*MAX(0,Positions!$M$13-1)+ABS(Positions!$D$14)*MAX(0,Positions!$M$14-1)+ABS(Positions!$D$15)*MAX(0,Positions!$M$15-1)+ABS(Positions!$D$16)*MAX(0,Positions!$M$16-1))*Assumptions!$E$17*(1-H8)
B9: Volatility normalization | C9: 0.05 | D9: 0.005 | E9: 0.005 | F9: 0 | G9: -0.3 | H9: 1 | I9: =(Factors!$C$5*C9+Factors!$C$6*D9+Factors!$C$7*E9+Factors!$C$8*F9+Factors!$C$9*G9)-(ABS(Positions!$D$5)*MAX(0,Positions!$M$5-1)+ABS(Positions!$D$6)*MAX(0,Positions!$M$6-1)+ABS(Positions!$D$7)*MAX(0,Positions!$M$7-1)+ABS(Positions!$D$8)*MAX(0,Positions!$M$8-1)+ABS(Positions!$D$9)*MAX(0,Positions!$M$9-1)+ABS(Positions!$D$10)*MAX(0,Positions!$M$10-1)+ABS(Positions!$D$11)*MAX(0,Positions!$M$11-1)+ABS(Positions!$D$12)*MAX(0,Positions!$M$12-1)+ABS(Positions!$D$13)*MAX(0,Positions!$M$13-1)+ABS(Positions!$D$14)*MAX(0,Positions!$M$14-1)+ABS(Positions!$D$15)*MAX(0,Positions!$M$15-1)+ABS(Positions!$D$16)*MAX(0,Positions!$M$16-1))*Assumptions!$E$17*(1-H9)
B10: Idiosyncratic concentration | C10: -0.25 | D10: 0 | E10: -0.01 | F10: 0 | G10: 0.2 | H10: 0.3 | I10: =(Factors!$C$5*C10+Factors!$C$6*D10+Factors!$C$7*E10+Factors!$C$8*F10+Factors!$C$9*G10)-(ABS(Positions!$D$5)*MAX(0,Positions!$M$5-1)+ABS(Positions!$D$6)*MAX(0,Positions!$M$6-1)+ABS(Positions!$D$7)*MAX(0,Positions!$M$7-1)+ABS(Positions!$D$8)*MAX(0,Positions!$M$8-1)+ABS(Positions!$D$9)*MAX(0,Positions!$M$9-1)+ABS(Positions!$D$10)*MAX(0,Positions!$M$10-1)+ABS(Positions!$D$11)*MAX(0,Positions!$M$11-1)+ABS(Positions!$D$12)*MAX(0,Positions!$M$12-1)+ABS(Positions!$D$13)*MAX(0,Positions!$M$13-1)+ABS(Positions!$D$14)*MAX(0,Positions!$M$14-1)+ABS(Positions!$D$15)*MAX(0,Positions!$M$15-1)+ABS(Positions!$D$16)*MAX(0,Positions!$M$16-1))*Assumptions!$E$17*(1-H10)

Sheet Liquidity
B2: Liquidity and Liquidation Cost
B4: Instrument | C4: Gross notional | D4: Days | E4: ADV participation proxy | F4: Impact loss | G4: Liquidation loss | H4: Illiquid?
B5: =Positions!B5 | C5: =ABS(Positions!E5) | D5: =Positions!M5 | E5: =MIN(1,C5/MAX(1,Assumptions!$E$18)/MAX(1,D5)) | F5: =Assumptions!$E$17*E5^1.5 | G5: =C5*F5 | H5: =IF(D5>5,"YES","NO")
B6: =Positions!B6 | C6: =ABS(Positions!E6) | D6: =Positions!M6 | E6: =MIN(1,C6/MAX(1,Assumptions!$E$18)/MAX(1,D6)) | F6: =Assumptions!$E$17*E6^1.5 | G6: =C6*F6 | H6: =IF(D6>5,"YES","NO")
B7: =Positions!B7 | C7: =ABS(Positions!E7) | D7: =Positions!M7 | E7: =MIN(1,C7/MAX(1,Assumptions!$E$18)/MAX(1,D7)) | F7: =Assumptions!$E$17*E7^1.5 | G7: =C7*F7 | H7: =IF(D7>5,"YES","NO")
B8: =Positions!B8 | C8: =ABS(Positions!E8) | D8: =Positions!M8 | E8: =MIN(1,C8/MAX(1,Assumptions!$E$18)/MAX(1,D8)) | F8: =Assumptions!$E$17*E8^1.5 | G8: =C8*F8 | H8: =IF(D8>5,"YES","NO")
B9: =Positions!B9 | C9: =ABS(Positions!E9) | D9: =Positions!M9 | E9: =MIN(1,C9/MAX(1,Assumptions!$E$18)/MAX(1,D9)) | F9: =Assumptions!$E$17*E9^1.5 | G9: =C9*F9 | H9: =IF(D9>5,"YES","NO")
B10: =Positions!B10 | C10: =ABS(Positions!E10) | D10: =Positions!M10 | E10: =MIN(1,C10/MAX(1,Assumptions!$E$18)/MAX(1,D10)) | F10: =Assumptions!$E$17*E10^1.5 | G10: =C10*F10 | H10: =IF(D10>5,"YES","NO")
B11: =Positions!B11 | C11: =ABS(Positions!E11) | D11: =Positions!M11 | E11: =MIN(1,C11/MAX(1,Assumptions!$E$18)/MAX(1,D11)) | F11: =Assumptions!$E$17*E11^1.5 | G11: =C11*F11 | H11: =IF(D11>5,"YES","NO")
B12: =Positions!B12 | C12: =ABS(Positions!E12) | D12: =Positions!M12 | E12: =MIN(1,C12/MAX(1,Assumptions!$E$18)/MAX(1,D12)) | F12: =Assumptions!$E$17*E12^1.5 | G12: =C12*F12 | H12: =IF(D12>5,"YES","NO")
B13: =Positions!B13 | C13: =ABS(Positions!E13) | D13: =Positions!M13 | E13: =MIN(1,C13/MAX(1,Assumptions!$E$18)/MAX(1,D13)) | F13: =Assumptions!$E$17*E13^1.5 | G13: =C13*F13 | H13: =IF(D13>5,"YES","NO")
B14: =Positions!B14 | C14: =ABS(Positions!E14) | D14: =Positions!M14 | E14: =MIN(1,C14/MAX(1,Assumptions!$E$18)/MAX(1,D14)) | F14: =Assumptions!$E$17*E14^1.5 | G14: =C14*F14 | H14: =IF(D14>5,"YES","NO")
B15: =Positions!B15 | C15: =ABS(Positions!E15) | D15: =Positions!M15 | E15: =MIN(1,C15/MAX(1,Assumptions!$E$18)/MAX(1,D15)) | F15: =Assumptions!$E$17*E15^1.5 | G15: =C15*F15 | H15: =IF(D15>5,"YES","NO")
B16: =Positions!B16 | C16: =ABS(Positions!E16) | D16: =Positions!M16 | E16: =MIN(1,C16/MAX(1,Assumptions!$E$18)/MAX(1,D16)) | F16: =Assumptions!$E$17*E16^1.5 | G16: =C16*F16 | H16: =IF(D16>5,"YES","NO")
B19: Illiquid gross notional | C19: =SUMIF(H5:H16,"YES",C5:C16)
B20: Illiquid NAV ratio | C20: =C19/Assumptions!E18
B21: Total modeled liquidation loss | C21: =SUM(G5:G16)

Sheet P&L Explain
B2: Daily P&L Explain
B4: Driver | C4: Exposure | D4: Move | E4: First-order P&L | F4: Convexity / residual | G4: Explained P&L | H4: Notes
B5: Equity | C5: =Factors!C5 | D5: -0.012 | E5: =C5*D5 | F5: 0.5 | G5: =E5+F5 | H5: delta/beta
B6: Rates | C6: =Factors!C6 | D6: 0.0015 | E6: =C6*D6 | F6: 0 | G6: =E6+F6 | H6: duration
B7: Credit | C7: =Factors!C7 | D7: 0.002 | E7: =C7*D7 | F7: 0 | G7: =E7+F7 | H7: spread duration
B8: FX | C8: =Factors!C8 | D8: -0.006 | E8: =C8*D8 | F8: 0 | G8: =E8+F8 | H8: currency delta
B9: Volatility | C9: =Factors!C9 | D9: 0.025 | E9: =C9*D9 | F9: 0.8 | G9: =E9+F9 | H9: vega / convexity
B12: Explained P&L | G12: =SUM(G5:G9)
B13: Actual P&L | G13: -1.5
B14: Unexplained P&L | G14: =G13-G12

Sheet Limits
B2: Risk Limit Dashboard
B4: Limit | C4: Actual | D4: Threshold | E4: Headroom | F4: Status
B5: One-day VaR | C5: ='VaR & ES'!C8 | D5: =Assumptions!E12 | E5: =D5-C5 | F5: =IF(C5<=D5,"PASS","BREACH")
B6: Worst stress loss | C6: =-MIN(Stress!I5:I10) | D6: =Assumptions!E13 | E6: =D6-C6 | F6: =IF(C6<=D6,"PASS","BREACH")
B7: Illiquid NAV | C7: =Liquidity!C20 | D7: =Assumptions!E14 | E7: =D7-C7 | F7: =IF(C7<=D7,"PASS","BREACH")
B8: Single-name concentration | C8: =MAX(ABS(Positions!D5:D16))/Assumptions!E18 | D8: =Assumptions!E15 | E8: =D8-C8 | F8: =IF(C8<=D8,"PASS","BREACH")
B9: Gross leverage | C9: =SUM(ABS(Positions!E5:E16))/Assumptions!E18 | D9: =Assumptions!E16 | E9: =D9-C9 | F9: =IF(C9<=D9,"PASS","BREACH")
B10: Unexplained P&L | C10: =ABS('P&L Explain'!G14) | D10: 5 | E10: =D10-C10 | F10: =IF(C10<=D10,"PASS","BREACH")

Sheet Checks
B2: Risk Model Checks
B4: Check | C4: Status
B5: Correlation diagonal equals one | C5: =IF(AND(Factors!E5=1,Factors!F6=1,Factors!G7=1,Factors!H8=1,Factors!I9=1),"PASS","FAIL")
B6: Correlation matrix bounded | C6: =IF(AND(MIN(Factors!E5:I9)>=-1,MAX(Factors!E5:I9)<=1),"PASS","FAIL")
B7: Portfolio variance nonnegative | C7: =IF(Factors!C12>=0,"PASS","FAIL")
B8: VaR and ES positive | C8: =IF(AND('VaR & ES'!C8>=0,'VaR & ES'!C9>='VaR & ES'!C8),"PASS","FAIL")
B9: No risk limit breaches | C9: =IF(COUNTIF(Limits!F5:F10,"BREACH")=0,"PASS","REVIEW")
B10: Liquidity loss nonnegative | C10: =IF(Liquidity!C21>=0,"PASS","FAIL")
B11: Position inventory populated | C11: =IF(COUNTA(Positions!B5:B16)=12,"PASS","FAIL")
B12: P&L explain complete | C12: =IF(COUNT('P&L Explain'!G5:G9)=5,"PASS","FAIL")
B13: Overall | C13: =IF(COUNTIF(C5:C12,"FAIL")=0,"PASS","FAIL")

Sheet Sources
B2: Source Register
B4: Input / dataset | C4: Source URL or document | D4: As-of | E4: Notes / transformation
B5: Position and market-value feed | C5: [OMS / risk source] | D5: [timestamp] | E5: Reconcile to books and records
B6: Factor and covariance calibration | C6: [model dataset URL] | D6: [window] | E6: Document decay, winsorization, and regime treatment
B7: Curve, spread, volatility, and FX data | C7: [market data URL] | D7: [timestamp] | E7: Record interpolation and stale-data policy
B8: Liquidity and ADV data | C8: [venue / vendor source] | D8: [period] | E8: Document liquidation horizon and impact calibration
B9: Risk limit policy | C9: [approved policy URL] | D9: [effective date] | E9: Thresholds, escalation, exceptions, and ownership

Sheet RefreshLog
B2: Refresh Log
B4: Date | C4: Trigger | D4: Source snapshot | E4: What changed | F4: Reviewer / challenge | G4: Next check
