Workbook

Sheet Cover
B2: [INSURER / BOOK] — Insurance & Actuarial Model
B4: Entity / line of business: | C4: [Name / LOB]
B5: Valuation date: | C5: [date]
B6: Last refreshed: | C6: 2024-02-23
B7: Next reserve / capital review: | C7: [date]
B8: Refresh cadence: | C8: Quarterly and on material claims events
B9: Active scenario: | C9: Base
B10: Units: | C10: $ in millions unless noted
B13: Modeling conventions
B14: Blue text / yellow fill | C14: Hardcoded input or selected scenario
B15: Black text | C15: Formula / same-sheet calculation
B16: Green text | C16: Cross-sheet formula / link
B17: Checks | C17: PASS / REVIEW / FAIL must remain visible

Sheet Assumptions
B2: Actuarial, Underwriting, and Capital Assumptions
B4: Assumption | C4: Base | D4: Downside | E4: Active | F4: Units / note
B5: Expected loss ratio | C5: 0.57 | D5: 0.78 | E5: =IF(Cover!$C$9="Downside",D5,C5) -> 0.57 | F5: %
B6: Expense ratio | C6: 0.28 | D6: 0.32 | E6: =IF(Cover!$C$9="Downside",D6,C6) -> 0.28 | F6: %
B7: Annual premium growth | C7: 0.05 | D7: -0.05 | E7: =IF(Cover!$C$9="Downside",D7,C7) -> 0.05 | F7: %
B8: Claims inflation | C8: 0.035 | D8: 0.075 | E8: =IF(Cover!$C$9="Downside",D8,C8) -> 0.035 | F8: %
B9: Discount rate | C9: 0.045 | D9: 0.035 | E9: =IF(Cover!$C$9="Downside",D9,C9) -> 0.045 | F9: %
B10: Risk margin / reserve | C10: 0.08 | D10: 0.15 | E10: =IF(Cover!$C$9="Downside",D10,C10) -> 0.08 | F10: %
B11: Opening earned premium | C11: 47359 | D11: 500 | E11: =IF(Cover!$C$9="Downside",D11,C11) -> 47359 | F11: $mm
B12: Opening invested assets | C12: 900 | D12: 900 | E12: =IF(Cover!$C$9="Downside",D12,C12) -> 900 | F12: $mm
B13: Investment yield | C13: 0.04 | D13: 0.025 | E13: =IF(Cover!$C$9="Downside",D13,C13) -> 0.04 | F13: %
B14: Opening available capital | C14: 72000 | D14: 350 | E14: =IF(Cover!$C$9="Downside",D14,C14) -> 72000 | F14: $mm
B15: Premium risk factor | C15: 0.18 | D15: 0.24 | E15: =IF(Cover!$C$9="Downside",D15,C15) -> 0.18 | F15: % premium
B16: Reserve risk factor | C16: 0.12 | D16: 0.18 | E16: =IF(Cover!$C$9="Downside",D16,C16) -> 0.12 | F16: % reserve
... B20: Projection horizon | C20: 5 | D20: 5 | E20: =IF(Cover!$C$9="Downside",D20,C20) -> 5 | F20: years

Sheet Paid Triangle
B2: Cumulative Paid Loss Triangle
B4: Accident year | C4: 12m | D4: 24m | E4: 36m | F4: 48m | G4: 60m | H4: 72m | I4: 84m | J4: 96m | K4: 108m | L4: 120m
B5: 2017 | C5: 64.4 | D5: 110.4 | E5: 144.9 | F5: 167.9 | G5: 186.3 | H5: 200.1 | I5: 209.3 | J5: 216.2 | K5: 223.1 | L5: 230
B6: 2018 | C6: 68.6 | D6: 117.6 | E6: 154.35 | F6: 178.85 | G6: 198.45 | H6: 213.15 | I6: 222.95 | J6: 230.3 | K6: 237.65
B7: 2019 | C7: 71.4 | D7: 122.4 | E7: 160.65 | F7: 186.15 | G7: 206.55 | H7: 221.85 | I7: 232.05 | J7: 239.7
B8: 2020 | C8: 75.6 | D8: 129.6 | E8: 170.1 | F8: 197.1 | G8: 218.7 | H8: 234.9 | I8: 245.7
B9: 2021 | C9: 79.8 | D9: 136.8 | E9: 179.55 | F9: 208.05 | G9: 230.85 | H9: 247.95
B10: 2022 | C10: 84 | D10: 144 | E10: 189 | F10: 219 | G10: 243
B11: 2023 | C11: 89.6 | D11: 153.6 | E11: 201.6 | F11: 233.6
B12: 2024 | C12: 93.8 | D12: 160.8 | E12: 211.05
B13: 2025 | C13: 99.4 | D13: 170.4
B14: 2026 | C14: 105

Sheet Chain Ladder
B2: Chain-Ladder Reserve Development
B4: Metric | C4: 12m | D4: 24m | E4: 36m | F4: 48m | G4: 60m | H4: 72m | I4: 84m | J4: 96m | K4: 108m | L4: 120m | M4: Ultimate | N4: Reserve
B5: Selected age-to-age factor | C5: =IFERROR(SUM('Paid Triangle'!D5:D13)/SUM('Paid Triangle'!C5:C13),1) -> 1.7142857 | D5: =IFERROR(SUM('Paid Triangle'!E5:E12)/SUM('Paid Triangle'!D5:D12),1) -> 1.3125 | E5: =IFERROR(SUM('Paid Triangle'!F5:F11)/SUM('Paid Triangle'!E5:E11),1) -> 1.1587302 | F5: =IFERROR(SUM('Paid Triangle'!G5:G10)/SUM('Paid Triangle'!F5:F10),1) -> 1.109589 | G5: =IFERROR(SUM('Paid Triangle'!H5:H9)/SUM('Paid Triangle'!G5:G9),1) -> 1.0740741 | H5: =IFERROR(SUM('Paid Triangle'!I5:I8)/SUM('Paid Triangle'!H5:H8),1) -> 1.045977 | I5: =IFERROR(SUM('Paid Triangle'!J5:J7)/SUM('Paid Triangle'!I5:I7),1) -> 1.032967 | J5: =IFERROR(SUM('Paid Triangle'!K5:K6)/SUM('Paid Triangle'!J5:J6),1) -> 1.0319149 | K5: =IFERROR(SUM('Paid Triangle'!L5:L5)/SUM('Paid Triangle'!K5:K5),1) -> 1.0309278 | L5: 1
B6: Cumulative development factor | C6: =PRODUCT(C$5:$K$5) -> 3.5714286 | D6: =PRODUCT(D$5:$K$5) -> 2.0833333 | E6: =PRODUCT(E$5:$K$5) -> 1.5873016 | F6: =PRODUCT(F$5:$K$5) -> 1.369863 | G6: =PRODUCT(G$5:$K$5) -> 1.2345679 | H6: =PRODUCT(H$5:$K$5) -> 1.1494253 | I6: =PRODUCT(I$5:$K$5) -> 1.0989011 | J6: =PRODUCT(J$5:$K$5) -> 1.0638298 | ... L6: =PRODUCT(L$5:$K$5) -> 1.0309278
B8: ='Paid Triangle'!B5 -> 2017 | C8: ='Paid Triangle'!C5 -> 64.4 | D8: ='Paid Triangle'!D5 -> 110.4 | E8: ='Paid Triangle'!E5 -> 144.9 | F8: ='Paid Triangle'!F5 -> 167.9 | G8: ='Paid Triangle'!G5 -> 186.3 | H8: ='Paid Triangle'!H5 -> 200.1 | I8: ='Paid Triangle'!I5 -> 209.3 | ... L8: ='Paid Triangle'!L5 -> 230 | M8: ='Paid Triangle'!L5*L$6 -> 237.1134 | N8: =M8-'Paid Triangle'!L5 -> 7.1134021
B9: ='Paid Triangle'!B6 -> 2018 | C9: ='Paid Triangle'!C6 -> 68.6 | D9: ='Paid Triangle'!D6 -> 117.6 | E9: ='Paid Triangle'!E6 -> 154.35 | F9: ='Paid Triangle'!F6 -> 178.85 | G9: ='Paid Triangle'!G6 -> 198.45 | H9: ='Paid Triangle'!H6 -> 213.15 | I9: ='Paid Triangle'!I6 -> 222.95 | ... K9: ='Paid Triangle'!K6 -> 237.65 | M9: ='Paid Triangle'!K6*K$6 -> 245 | N9: =M9-'Paid Triangle'!K6 -> 7.35
B10: ='Paid Triangle'!B7 -> 2019 | C10: ='Paid Triangle'!C7 -> 71.4 | D10: ='Paid Triangle'!D7 -> 122.4 | E10: ='Paid Triangle'!E7 -> 160.65 | F10: ='Paid Triangle'!F7 -> 186.15 | G10: ='Paid Triangle'!G7 -> 206.55 | H10: ='Paid Triangle'!H7 -> 221.85 | I10: ='Paid Triangle'!I7 -> 232.05 | J10: ='Paid Triangle'!J7 -> 239.7 | M10: ='Paid Triangle'!J7*J$6 -> 255 | N10: =M10-'Paid Triangle'!J7 -> 15.3
B11: ='Paid Triangle'!B8 -> 2020 | C11: ='Paid Triangle'!C8 -> 75.6 | D11: ='Paid Triangle'!D8 -> 129.6 | E11: ='Paid Triangle'!E8 -> 170.1 | F11: ='Paid Triangle'!F8 -> 197.1 | G11: ='Paid Triangle'!G8 -> 218.7 | H11: ='Paid Triangle'!H8 -> 234.9 | I11: ='Paid Triangle'!I8 -> 245.7 | M11: ='Paid Triangle'!I8*I$6 -> 270 | N11: =M11-'Paid Triangle'!I8 -> 24.3
B12: ='Paid Triangle'!B9 -> 2021 | C12: ='Paid Triangle'!C9 -> 79.8 | D12: ='Paid Triangle'!D9 -> 136.8 | E12: ='Paid Triangle'!E9 -> 179.55 | F12: ='Paid Triangle'!F9 -> 208.05 | G12: ='Paid Triangle'!G9 -> 230.85 | H12: ='Paid Triangle'!H9 -> 247.95 | M12: ='Paid Triangle'!H9*H$6 -> 285 | N12: =M12-'Paid Triangle'!H9 -> 37.05
B13: ='Paid Triangle'!B10 -> 2022 | C13: ='Paid Triangle'!C10 -> 84 | D13: ='Paid Triangle'!D10 -> 144 | E13: ='Paid Triangle'!E10 -> 189 | F13: ='Paid Triangle'!F10 -> 219 | G13: ='Paid Triangle'!G10 -> 243 | M13: ='Paid Triangle'!G10*G$6 -> 300 | N13: =M13-'Paid Triangle'!G10 -> 57
B14: ='Paid Triangle'!B11 -> 2023 | C14: ='Paid Triangle'!C11 -> 89.6 | D14: ='Paid Triangle'!D11 -> 153.6 | E14: ='Paid Triangle'!E11 -> 201.6 | F14: ='Paid Triangle'!F11 -> 233.6 | M14: ='Paid Triangle'!F11*F$6 -> 320 | N14: =M14-'Paid Triangle'!F11 -> 86.4
B15: ='Paid Triangle'!B12 -> 2024 | C15: ='Paid Triangle'!C12 -> 93.8 | D15: ='Paid Triangle'!D12 -> 160.8 | E15: ='Paid Triangle'!E12 -> 211.05 | M15: ='Paid Triangle'!E12*E$6 -> 335 | N15: =M15-'Paid Triangle'!E12 -> 123.95
B16: ='Paid Triangle'!B13 -> 2025 | C16: ='Paid Triangle'!C13 -> 99.4 | D16: ='Paid Triangle'!D13 -> 170.4 | M16: ='Paid Triangle'!D13*D$6 -> 355 | N16: =M16-'Paid Triangle'!D13 -> 184.6
B17: ='Paid Triangle'!B14 -> 2026 | C17: ='Paid Triangle'!C14 -> 105 | M17: ='Paid Triangle'!C14*C$6 -> 375 | N17: =M17-'Paid Triangle'!C14 -> 270
B18: Total | M18: =SUM(M8:M17) -> 2977.1134 | N18: =SUM(N8:N17) -> 813.0634

Sheet Bornhuetter-Ferguson
B2: Bornhuetter-Ferguson Reserve Estimate
B4: Accident year | C4: Earned premium | D4: Expected loss | E4: % paid | F4: Paid to date | G4: BF ultimate | H4: BF reserve
B5: ='Chain Ladder'!B8 -> 2017 | C5: 400 | D5: =C5*Assumptions!$E$5*(1+Assumptions!$E$8)^0 -> 228 | E5: =1/'Chain Ladder'!L$6 -> 0.97 | F5: ='Paid Triangle'!L5 -> 230 | G5: =F5+D5*(1-E5) -> 236.84 | H5: =G5-F5 -> 6.84
B6: ='Chain Ladder'!B9 -> 2018 | C6: 425 | D6: =C6*Assumptions!$E$5*(1+Assumptions!$E$8)^1 -> 250.72875 | E6: =1/'Chain Ladder'!K$6 -> 0.97 | F6: ='Paid Triangle'!K6 -> 237.65 | G6: =F6+D6*(1-E6) -> 245.17186 | H6: =G6-F6 -> 7.5218625
B7: ='Chain Ladder'!B10 -> 2019 | C7: 450 | D7: =C7*Assumptions!$E$5*(1+Assumptions!$E$8)^2 -> 274.76921 | E7: =1/'Chain Ladder'!J$6 -> 0.94 | F7: ='Paid Triangle'!J7 -> 239.7 | G7: =F7+D7*(1-E7) -> 256.18615 | H7: =G7-F7 -> 16.486153
B8: ='Chain Ladder'!B11 -> 2020 | C8: 475 | D8: =C8*Assumptions!$E$5*(1+Assumptions!$E$8)^3 -> 300.18536 | E8: =1/'Chain Ladder'!I$6 -> 0.91 | F8: ='Paid Triangle'!I8 -> 245.7 | G8: =F8+D8*(1-E8) -> 272.71668 | H8: =G8-F8 -> 27.016683
B9: ='Chain Ladder'!B12 -> 2021 | C9: 500 | D9: =C9*Assumptions!$E$5*(1+Assumptions!$E$8)^4 -> 327.04406 | E9: =1/'Chain Ladder'!H$6 -> 0.87 | F9: ='Paid Triangle'!H9 -> 247.95 | G9: =F9+D9*(1-E9) -> 290.46573 | H9: =G9-F9 -> 42.515727
B10: ='Chain Ladder'!B13 -> 2022 | C10: 525 | D10: =C10*Assumptions!$E$5*(1+Assumptions!$E$8)^5 -> 355.41513 | E10: =1/'Chain Ladder'!G$6 -> 0.81 | F10: ='Paid Triangle'!G10 -> 243 | G10: =F10+D10*(1-E10) -> 310.52887 | H10: =G10-F10 -> 67.528874
B11: ='Chain Ladder'!B14 -> 2023 | C11: 550 | D11: =C11*Assumptions!$E$5*(1+Assumptions!$E$8)^6 -> 385.37154 | E11: =1/'Chain Ladder'!F$6 -> 0.73 | F11: ='Paid Triangle'!F11 -> 233.6 | G11: =F11+D11*(1-E11) -> 337.65032 | H11: =G11-F11 -> 104.05032
B12: ='Chain Ladder'!B15 -> 2024 | C12: 575 | D12: =C12*Assumptions!$E$5*(1+Assumptions!$E$8)^7 -> 416.98953 | E12: =1/'Chain Ladder'!E$6 -> 0.63 | F12: ='Paid Triangle'!E12 -> 211.05 | G12: =F12+D12*(1-E12) -> 365.33613 | H12: =G12-F12 -> 154.28613
B13: ='Chain Ladder'!B16 -> 2025 | C13: 600 | D13: =C13*Assumptions!$E$5*(1+Assumptions!$E$8)^8 -> 450.34869 | E13: =1/'Chain Ladder'!D$6 -> 0.48 | F13: ='Paid Triangle'!D13 -> 170.4 | G13: =F13+D13*(1-E13) -> 404.58132 | H13: =G13-F13 -> 234.18132
B14: ='Chain Ladder'!B17 -> 2026 | C14: 625 | D14: =C14*Assumptions!$E$5*(1+Assumptions!$E$8)^9 -> 485.53218 | E14: =1/'Chain Ladder'!C$6 -> 0.28 | F14: ='Paid Triangle'!C14 -> 105 | G14: =F14+D14*(1-E14) -> 454.58317 | H14: =G14-F14 -> 349.58317
B15: Total | C15: =SUM(C5:C14) -> 5125 | D15: =SUM(D5:D14) -> 3474.3845 | F15: =SUM(F5:F14) -> 2164.05 | G15: =SUM(G5:G14) -> 3174.0602 | H15: =SUM(H5:H14) -> 1010.0102

Sheet Underwriting
B2: Five-Year Underwriting Forecast
B4: $mm / % | C4: Year 1 | D4: Year 2 | E4: Year 3 | F4: Year 4 | G4: Year 5
B5: Earned premium | C5: =Assumptions!E11 -> 47359 | D5: =C5*(1+Assumptions!$E$7) -> 49726.95 | E5: =D5*(1+Assumptions!$E$7) -> 52213.298 | F5: =E5*(1+Assumptions!$E$7) -> 54823.962 | G5: =F5*(1+Assumptions!$E$7) -> 57565.16
B6: Incurred losses | C6: =C5*Assumptions!$E$5*(1+Assumptions!$E$8)^0 -> 26994.63 | D6: =D5*Assumptions!$E$5*(1+Assumptions!$E$8)^1 -> 29336.414 | E6: =E5*Assumptions!$E$5*(1+Assumptions!$E$8)^2 -> 31881.348 | F6: =F5*Assumptions!$E$5*(1+Assumptions!$E$8)^3 -> 34647.055 | G6: =G5*Assumptions!$E$5*(1+Assumptions!$E$8)^4 -> 37652.687
B7: Underwriting expenses | C7: =C5*Assumptions!$E$6 -> 13260.52 | D7: =D5*Assumptions!$E$6 -> 13923.546 | E7: =E5*Assumptions!$E$6 -> 14619.723 | F7: =F5*Assumptions!$E$6 -> 15350.709 | G7: =G5*Assumptions!$E$6 -> 16118.245
B8: Underwriting result | C8: =C5-C6-C7 -> 7103.85 | D8: =D5-D6-D7 -> 6466.9898 | E8: =E5-E6-E7 -> 5712.2261 | F8: =F5-F6-F7 -> 4826.1979 | G8: =G5-G6-G7 -> 3794.2285
B9: Loss ratio | C9: =IFERROR(C6/C5,0) -> 0.57 | D9: =IFERROR(D6/D5,0) -> 0.58995 | E9: =IFERROR(E6/E5,0) -> 0.61059825 | F9: =IFERROR(F6/F5,0) -> 0.63196919 | G9: =IFERROR(G6/G5,0) -> 0.65408811
B10: Expense ratio | C10: =IFERROR(C7/C5,0) -> 0.28 | D10: =IFERROR(D7/D5,0) -> 0.28 | E10: =IFERROR(E7/E5,0) -> 0.28 | F10: =IFERROR(F7/F5,0) -> 0.28 | G10: =IFERROR(G7/G5,0) -> 0.28
B11: Combined ratio | C11: =C9+C10 -> 0.85 | D11: =D9+D10 -> 0.86995 | E11: =E9+E10 -> 0.89059825 | F11: =F9+F10 -> 0.91196919 | G11: =G9+G10 -> 0.93408811
B12: Investment income | C12: =Assumptions!$E$12*Assumptions!$E$13 -> 36 | D12: =Assumptions!$E$12*Assumptions!$E$13 -> 36 | E12: =Assumptions!$E$12*Assumptions!$E$13 -> 36 | F12: =Assumptions!$E$12*Assumptions!$E$13 -> 36 | G12: =Assumptions!$E$12*Assumptions!$E$13 -> 36
B13: Pre-tax operating income | C13: =C8+C12 -> 7139.85 | D13: =D8+D12 -> 6502.9898 | E13: =E8+E12 -> 5748.2261 | F13: =F8+F12 -> 4862.1979 | G13: =G8+G12 -> 3830.2285

Sheet Embedded Value
B2: Simplified Embedded Value
B4: Metric | C4: Year 1 | D4: Year 2 | E4: Year 3 | F4: Year 4 | G4: Year 5
B5: Pre-tax operating income | C5: =Underwriting!C13 -> 7139.85 | D5: =Underwriting!D13 -> 6502.9898 | E5: =Underwriting!E13 -> 5748.2261 | F5: =Underwriting!F13 -> 4862.1979 | G5: =Underwriting!G13 -> 3830.2285
B6: Tax at 25% | C6: =MAX(0,C5*0.25) -> 1784.9625 | D6: =MAX(0,D5*0.25) -> 1625.7475 | E6: =MAX(0,E5*0.25) -> 1437.0565 | F6: =MAX(0,F5*0.25) -> 1215.5495 | G6: =MAX(0,G5*0.25) -> 957.55713
B7: After-tax distributable earnings | C7: =C5-C6 -> 5354.8875 | D7: =D5-D6 -> 4877.2424 | E7: =E5-E6 -> 4311.1696 | F7: =F5-F6 -> 3646.6484 | G7: =G5-G6 -> 2872.6714
B8: Risk margin charge | C8: ='Bornhuetter-Ferguson'!$H$15*Assumptions!$E$10*Assumptions!$E$19 -> 8.0800819 | D8: ='Bornhuetter-Ferguson'!$H$15*Assumptions!$E$10*Assumptions!$E$19 -> 8.0800819 | E8: ='Bornhuetter-Ferguson'!$H$15*Assumptions!$E$10*Assumptions!$E$19 -> 8.0800819 | F8: ='Bornhuetter-Ferguson'!$H$15*Assumptions!$E$10*Assumptions!$E$19 -> 8.0800819 | G8: ='Bornhuetter-Ferguson'!$H$15*Assumptions!$E$10*Assumptions!$E$19 -> 8.0800819
B9: Economic earnings | C9: =C7-C8 -> 5346.8074 | D9: =D7-D8 -> 4869.1623 | E9: =E7-E8 -> 4303.0895 | F9: =F7-F8 -> 3638.5683 | G9: =G7-G8 -> 2864.5913
B10: Discount factor | C10: =1/(1+Assumptions!$E$9)^1 -> 0.9569378 | D10: =1/(1+Assumptions!$E$9)^2 -> 0.91572995 | E10: =1/(1+Assumptions!$E$9)^3 -> 0.8762966 | F10: =1/(1+Assumptions!$E$9)^4 -> 0.83856134 | G10: =1/(1+Assumptions!$E$9)^5 -> 0.80245105
B11: PV economic earnings | C11: =C9*C10 -> 5116.5621 | D11: =D9*D10 -> 4458.8378 | E11: =E9*E10 -> 3770.7827 | F11: =F9*F10 -> 3051.1627 | G11: =G9*G10 -> 2298.6943
B13: Adjusted net asset value | C13: =Assumptions!E14-'Bornhuetter-Ferguson'!H15*(1+Assumptions!E10) -> 70909.189
B14: Present value of future economic earnings | C14: =SUM(C11:G11) -> 18696.04
B15: Embedded value | C15: =C13+C14 -> 89605.229

Sheet Capital
B2: Economic and Regulatory Capital Screen
B4: Capital component | C4: Exposure | D4: Factor | E4: Requirement
B5: Premium risk | C5: =Underwriting!C5 -> 47359 | D5: =Assumptions!E15 -> 0.18 | E5: =C5*D5 -> 8524.62
B6: Reserve risk | C6: ='Bornhuetter-Ferguson'!H15 -> 1010.0102 | D6: =Assumptions!E16 -> 0.12 | E6: =C6*D6 -> 121.20123
B7: Asset risk | C7: =Assumptions!E12 -> 900 | D7: =Assumptions!E17 -> 0.08 | E7: =C7*D7 -> 72
B9: Diversified capital requirement | E9: =SQRT(SUMSQ(E5:E7)+2*0.25*(E5*E6+E5*E7+E6*E7)) -> 8574.1977
B10: Available capital | E10: =Assumptions!E14 -> 72000
B11: Capital coverage | E11: =IFERROR(E10/E9,0) -> 8.3972871
B12: Minimum coverage | E12: =Assumptions!E18 -> 1.5
B13: Capital status | E13: =IF(E11>=E12,"PASS","BREACH") -> PASS

Sheet Stress
B2: Reserve and Capital Stress Matrix
B4: Loss ratio / Asset shock | C4: -0.2 | D4: -0.1 | E4: 0 | F4: 0.1 | G4: 0.2
B5: 0 | C5: =(Assumptions!$E$14*(1+C$4)-'Bornhuetter-Ferguson'!$H$15*(1+$B5))/Capital!$E$9 -> 6.6000332 | D5: =(Assumptions!$E$14*(1+D$4)-'Bornhuetter-Ferguson'!$H$15*(1+$B5))/Capital!$E$9 -> 7.4397619 | E5: =(Assumptions!$E$14*(1+E$4)-'Bornhuetter-Ferguson'!$H$15*(1+$B5))/Capital!$E$9 -> 8.2794906 | F5: =(Assumptions!$E$14*(1+F$4)-'Bornhuetter-Ferguson'!$H$15*(1+$B5))/Capital!$E$9 -> 9.1192193 | G5: =(Assumptions!$E$14*(1+G$4)-'Bornhuetter-Ferguson'!$H$15*(1+$B5))/Capital!$E$9 -> 9.9589481
B6: 0.05 | C6: =(Assumptions!$E$14*(1+C$4)-'Bornhuetter-Ferguson'!$H$15*(1+$B6))/Capital!$E$9 -> 6.5941434 | D6: =(Assumptions!$E$14*(1+D$4)-'Bornhuetter-Ferguson'!$H$15*(1+$B6))/Capital!$E$9 -> 7.4338721 | E6: =(Assumptions!$E$14*(1+E$4)-'Bornhuetter-Ferguson'!$H$15*(1+$B6))/Capital!$E$9 -> 8.2736008 | F6: =(Assumptions!$E$14*(1+F$4)-'Bornhuetter-Ferguson'!$H$15*(1+$B6))/Capital!$E$9 -> 9.1133295 | G6: =(Assumptions!$E$14*(1+G$4)-'Bornhuetter-Ferguson'!$H$15*(1+$B6))/Capital!$E$9 -> 9.9530582
B7: 0.1 | C7: =(Assumptions!$E$14*(1+C$4)-'Bornhuetter-Ferguson'!$H$15*(1+$B7))/Capital!$E$9 -> 6.5882536 | D7: =(Assumptions!$E$14*(1+D$4)-'Bornhuetter-Ferguson'!$H$15*(1+$B7))/Capital!$E$9 -> 7.4279823 | E7: =(Assumptions!$E$14*(1+E$4)-'Bornhuetter-Ferguson'!$H$15*(1+$B7))/Capital!$E$9 -> 8.267711 | F7: =(Assumptions!$E$14*(1+F$4)-'Bornhuetter-Ferguson'!$H$15*(1+$B7))/Capital!$E$9 -> 9.1074397 | G7: =(Assumptions!$E$14*(1+G$4)-'Bornhuetter-Ferguson'!$H$15*(1+$B7))/Capital!$E$9 -> 9.9471684
B8: 0.15 | C8: =(Assumptions!$E$14*(1+C$4)-'Bornhuetter-Ferguson'!$H$15*(1+$B8))/Capital!$E$9 -> 6.5823637 | D8: =(Assumptions!$E$14*(1+D$4)-'Bornhuetter-Ferguson'!$H$15*(1+$B8))/Capital!$E$9 -> 7.4220925 | E8: =(Assumptions!$E$14*(1+E$4)-'Bornhuetter-Ferguson'!$H$15*(1+$B8))/Capital!$E$9 -> 8.2618212 | F8: =(Assumptions!$E$14*(1+F$4)-'Bornhuetter-Ferguson'!$H$15*(1+$B8))/Capital!$E$9 -> 9.1015499 | G8: =(Assumptions!$E$14*(1+G$4)-'Bornhuetter-Ferguson'!$H$15*(1+$B8))/Capital!$E$9 -> 9.9412786
B9: 0.2 | C9: =(Assumptions!$E$14*(1+C$4)-'Bornhuetter-Ferguson'!$H$15*(1+$B9))/Capital!$E$9 -> 6.5764739 | D9: =(Assumptions!$E$14*(1+D$4)-'Bornhuetter-Ferguson'!$H$15*(1+$B9))/Capital!$E$9 -> 7.4162026 | E9: =(Assumptions!$E$14*(1+E$4)-'Bornhuetter-Ferguson'!$H$15*(1+$B9))/Capital!$E$9 -> 8.2559313 | F9: =(Assumptions!$E$14*(1+F$4)-'Bornhuetter-Ferguson'!$H$15*(1+$B9))/Capital!$E$9 -> 9.0956601 | G9: =(Assumptions!$E$14*(1+G$4)-'Bornhuetter-Ferguson'!$H$15*(1+$B9))/Capital!$E$9 -> 9.9353888

Sheet Checks
B2: Actuarial Model Checks
B4: Check | C4: Status
B5: Paid triangle cumulative | C5: =IF(MIN('Paid Triangle'!D5-'Paid Triangle'!C5,'Paid Triangle'!E5-'Paid Triangle'!D5,'Paid Triangle'!F5-'Paid Triangle'!E5,'Paid Triangle'!G5-'Paid Triangle'!F5,'Paid Triangle'!H5-'Paid Triangle'!G5,'Paid Triangle'!I5-'Paid Triangle'!H5,'Paid Triangle'!J5-'Paid Triangle'!I5,'Paid Triangle'!K5-'Paid Triangle'!J5,'Paid Triangle'!L5-'Paid Triangle'!K5,'Paid Triangle'!D6-'Paid Triangle'!C6,'Paid Triangle'!E6-'Paid Triangle'!D6,'Paid Triangle'!F6-'Paid Triangle'!E6,'Paid Triangle'!G6-'Paid Triangle'!F6,'Paid Triangle'!H6-'Paid Triangle'!G6,'Paid Triangle'!I6-'Paid Triangle'!H6,'Paid Triangle'!J6-'Paid Triangle'!I6,'Paid Triangle'!K6-'Paid Triangle'!J6,'Paid Triangle'!D7-'Paid Triangle'!C7,'Paid Triangle'!E7-'Paid Triangle'!D7,'Paid Triangle'!F7-'Paid Triangle'!E7,'Paid Triangle'!G7-'Paid Triangle'!F7,'Paid Triangle'!H7-'Paid Triangle'!G7,'Paid Triangle'!I7-'Paid Triangle'!H7,'Paid Triangle'!J7-'Paid Triangle'!I7,'Paid Triangle'!D8-'Paid Triangle'!C8,'Paid Triangle'!E8-'Paid Triangle'!D8,'Paid Triangle'!F8-'Paid Triangle'!E8,'Paid Triangle'!G8-'Paid Triangle'!F8,'Paid Triangle'!H8-'Paid Triangle'!G8,'Paid Triangle'!I8-'Paid Triangle'!H8,'Paid Triangle'!D9-'Paid Triangle'!C9,'Paid Triangle'!E9-'Paid Triangle'!D9,'Paid Triangle'!F9-'Paid Triangle'!E9,'Paid Triangle'!G9-'Paid Triangle'!F9,'Paid Triangle'!H9-'Paid Triangle'!G9,'Paid Triangle'!D10-'Paid Triangle'!C10,'Paid Triangle'!E10-'Paid Triangle'!D10,'Paid Triangle'!F10-'Paid Triangle'!E10,'Paid Triangle'!G10-'Paid Triangle'!F10,'Paid Triangle'!D11-'Paid Triangle'!C11,'Paid Triangle'!E11-'Paid Triangle'!D11,'Paid Triangle'!F11-'Paid Triangle'!E11,'Paid Triangle'!D12-'Paid Triangle'!C12,'Paid Triangle'!E12-'Paid Triangle'!D12,'Paid Triangle'!D13-'Paid Triangle'!C13)>=0,"PASS","FAIL") -> PASS
B6: Development factors at least one | C6: =IF(MIN('Chain Ladder'!C5:L5)>=1,"PASS","FAIL") -> PASS
B7: Chain-ladder reserve nonnegative | C7: =IF(MIN('Chain Ladder'!N8:N17)>=0,"PASS","FAIL") -> PASS
B8: BF reserve nonnegative | C8: =IF(MIN('Bornhuetter-Ferguson'!H5:H14)>=0,"PASS","FAIL") -> PASS
B9: Combined ratio finite | C9: =IF(AND(MIN(Underwriting!C11:G11)>=0,MAX(Underwriting!C11:G11)<3),"PASS","FAIL") -> PASS
B10: Capital requirement positive | C10: =IF(Capital!E9>0,"PASS","FAIL") -> PASS
B11: Capital coverage | C11: =IF(Capital!E13="PASS","PASS","REVIEW") -> PASS
B12: Embedded value finite | C12: =IF(ABS('Embedded Value'!C15)<1000000,"PASS","FAIL") -> PASS
B13: Overall | C13: =IF(COUNTIF(C5:C12,"FAIL")=0,"PASS","FAIL") -> PASS

Sheet Sources
B2: Source Register
B4: Input / dataset | C4: Source URL or document | D4: As-of | E4: Notes / transformation
B5: Actuarial loss data | C5: [claims system / public filing] | D5: [valuation date] | E5: Paid, incurred, case reserve, claim counts
B6: Premium and exposure data | C6: [policy administration source] | D6: [period] | E6: Earned premium, rate, mix, exposure
B7: Reinsurance contracts | C7: [treaty / facultative documentation] | D7: [date] | E7: Limits, attachment, reinstatements, credit risk
B8: Capital methodology | C8: [regulator / internal methodology URL] | D8: [effective date] | E8: Risk factors, diversification, management actions
B9: Investment portfolio | C9: [asset ledger / filing] | D9: [date] | E9: Yield, duration, credit, liquidity, unrealized gains
B10: Chubb 2023 Form 10-K | C10: https://www.sec.gov/Archives/edgar/data/896159/000089615924000007/cb-20231231.htm | D10: 2024-02-23 | E10: U.S. SEC; frozen curated observation as of case date
B11: Frozen source snapshot | C11: repo://18_Insurance_Actuarial/sources/snapshots/insurance-chubb-2023.json | D11: 2024-02-23 | E11: Immutable curated observation package with SHA-256 digest

Sheet RefreshLog
B2: Refresh Log
B4: Date | C4: Trigger | D4: Source snapshot | E4: What changed | F4: Reviewer / challenge | G4: Next check
B5: 2026-08-04 | C5: External historical evidence materialization | D5: repo://18_Insurance_Actuarial/sources/snapshots/insurance-chubb-2023.json | E5: Generated public case insurance-chubb-2023 from canonical release template | F5: External historical case; human stakeholder approval remains pending | G5: On source revision, builder change, monitoring breach, or annual review
